Workbook

Sheet предлог_с
A1: Корпус | B1: utterance_id | C1: From | D1: To | E1: File | F1: Id | G1: String id | H1: Gender | I1: Year of birth | J1: Education | K1: Place of birth | L1: Place of living | M1: Left Context | N1: DMatch | O1: Right Context | P1: имя в предложной группе | Q1: Топоним | R1: деревня, город, область, страна и пр. | S1: жилище | T1: природные пространственные локации | U1: учреждения | V1: пространственные локации | W1: остальные употребления | X1: выход из контейнера | Y1: материал | Z1: армия, тюрьма, служба, фазы жизни | AA1: коллектив, группа | AB1: деньги, заработок, зарплата | AC1: Прайминг | AD1: пространственная/объектная/определительная | AE1: глагольная/именная | AF1: соответствует/не соответствует литературной норме
A2: Корпус говора деревни Пятиусово | B2: 49 | C2: 1082342 | D2: 1089680 | E2: 20231028zes1942 | M2: У нас э... А | N2: с | O2: другой деревни и шла старушка, ну она моложе меня (мене) было, ей побольше, семьдесят... | P2: деревня | Q2: 0 | R2: 1 | S2: 0 | T2: 0 | U2: 0 | V2: 0 | W2: 0 | X2: 0 | Y2: 0 | Z2: 0 | AA2: 0 | AB2: 0 | AC2: 0 | AD2: s | AE2: v | AF2: n
A3: Корпус говора деревни Пятиусово | B3: 110 | C3: 1383096 | D3: 1384946 | E3: 20231028zes1942 | M3: А вы это, не | N3: с | O3: Макеева, детка? | P3: Макеево | Q3: 1 | R3: 0 | S3: 0 | T3: 0 | U3: 0 | V3: 0 | W3: 0 | X3: 0 | Y3: 0 | Z3: 0 | AA3: 0 | AB3: 0 | AC3: 0 | AD3: a | AE3: n | AF3: n
A4: Корпус говора деревни Пятиусово | B4: 112 | C4: 1390055 | D4: 1394577 | E4: 20231028zes1942 | N4: С | O4: Макеева похожа... Там, при этом... У нас приехадчи была семья, девять детей... | P4: Макеево | Q4: 1 | R4: 0 | S4: 0 | T4: 0 | U4: 0 | V4: 0 | W4: 0 | X4: 0 | Y4: 0 | Z4: 0 | AA4: 0 | AB4: 0 | AC4: 0 | AD4: a | AE4: n | AF4: n
A5: Корпус говора деревни Пятиусово | B5: 115 | C5: 1407389 | D5: 1411911 | E5: 20231028zes1942 | M5: Она таджи = | N5: с | O5: Таджикистана... Есть такая? Государство... | P5: Таджикистан | Q5: 1 | R5: 0 | S5: 0 | T5: 0 | U5: 0 | V5: 0 | W5: 0 | X5: 0 | Y5: 0 | Z5: 0 | AA5: 0 | AB5: 0 | AC5: 0 | AD5: a | AE5: n | AF5: n
A6: Корпус говора деревни Пятиусово | B6: 135 | C6: 1495040 | D6: 1499314 | E6: 20231028zes1942 | M6: А морозы начнутся, | N6: с | O6: дому не выходили никуда, так что вот... | P6: дом | Q6: 0 | R6: 0 | S6: 1 | T6: 0 | U6: 0 | V6: 0 | W6: 0 | X6: 0 | Y6: 0 | Z6: 0 | AA6: 0 | AB6: 0 | AC6: 0 | AD6: s | AE6: v | AF6: n
A7: Корпус говора деревни Пятиусово | B7: 142 | C7: 1530129 | D7: 1537572 | E7: 20231028zes1942 | M7: Но так как у нас | N7: с | O7: деревни не было этих, вальщиков, то... Мы не возили... И родители тогда... | P7: деревня | Q7: 0 | R7: 1 | S7: 0 | T7: 0 | U7: 0 | V7: 0 | W7: 0 | X7: 0 | Y7: 0 | Z7: 0 | AA7: 0 | AB7: 0 | AC7: 0 | AD7: a | AE7: n | AF7: n
A8: Корпус говора деревни Пятиусово | B8: 188 | C8: 1850333 | D8: 1855840 | E8: 20231028zes1942 | M8: Ездил надзиратель, который выкидывал эту картошку | N8: с | O8: вёдер, если он… Если он захватит (захватить). | P8: ведра | Q8: 0 | R8: 0 | S8: 0 | T8: 0 | U8: 0 | V8: 0 | W8: 0 | X8: 1 | Y8: 0 | Z8: 0 | AA8: 0 | AB8: 0 | AC8: 0 | AD8: s | AE8: v | AF8: n
A9: Корпус говора деревни Пятиусово | B9: 206 | C9: 1953370 | D9: 1961300 | E9: 20231028zes1942 | M9: И мать привезла два мешка картошки | N9: с | O9: Антонова. Там пески, а у нас, такая, суглинистая. | P9: Антоново | Q9: 1 | R9: 0 | S9: 0 | T9: 0 | U9: 0 | V9: 0 | W9: 0 | X9: 0 | Y9: 0 | Z9: 0 | AA9: 0 | AB9: 0 | AC9: 0 | AD9: s | AE9: v | AF9: n
A10: Корпус говора деревни Пятиусово | B10: 328 | C10: 516610 | D10: 524930 | E10: 20240729evm1937 | G10: EVM1937 | I10: 1937 | J10: техникум | K10: Коковино | L10: Пятиусово | M10: Ехали нас человек пятнадцать или семнадцать отсюда, | N10: с | O10: Западной Двины в Тверь. | P10: Западная Двина | Q10: 1 | R10: 0 | S10: 0 | T10: 0 | U10: 0 | V10: 0 | W10: 0 | X10: 0 | Y10: 0 | Z10: 0 | AA10: 0 | AB10: 0 | AC10: 0 | AD10: s | AE10: v | AF10: n
A11: Корпус говора деревни Пятиусово | B11: 376 | C11: 802725 | D11: 813830 | E11: 20240729evm1937 | G11: EVM1937 | I11: 1937 | J11: техникум | K11: Коковино | L11: Пятиусово | M11: Я спускал оттуда станцию, | N11: с | O11: Бакуриани, с тягачом АТС, а сзади приёмо - передающая кабина, 20 тонн. | P11: Бакуриани | Q11: 1 | R11: 0 | S11: 0 | T11: 0 | U11: 0 | V11: 0 | W11: 0 | X11: 0 | Y11: 0 | Z11: 0 | AA11: 0 | AB11: 0 | AC11: 0 | AD11: s | AE11: v | AF11: n
A12: Корпус говора деревни Пятиусово | B12: 382 | C12: 851500 | D12: 855750 | E12: 20240729evm1937 | G12: EVM1937 | I12: 1937 | J12: техникум | K12: Коковино | L12: Пятиусово | M12: Вот оттуда эту станцию спускал | N12: с | O12: этой Бакуриани. | P12: Бакуриани | Q12: 1 | R12: 0 | S12: 0 | T12: 0 | U12: 0 | V12: 0 | W12: 0 | X12: 0 | Y12: 0 | Z12: 0 | AA12: 0 | AB12: 0 | AC12: 0 | AD12: s | AE12: v | AF12: n
A13: Корпус говора деревни Пятиусово | B13: 405 | C13: 1004680 | D13: 1014830 | E13: 20240729evm1937 | G13: EVM1937 | I13: 1937 | J13: техникум | K13: Коковино | L13: Пятиусово | M13: Они не едут этим (этом) кругом, они подъехали трактор опустили, сам из ( | N13: с | O13: ) трактора выскочил, и трактор туда до низу и добежал. | P13: трактор | Q13: 0 | R13: 0 | S13: 0 | T13: 0 | U13: 0 | V13: 0 | W13: 0 | X13: 1 | Y13: 0 | Z13: 0 | AA13: 0 | AB13: 0 | AC13: 0 | AD13: s | AE13: v | AF13: n
A14: Корпус говора деревни Пятиусово | B14: 445 | C14: 1200212 | D14: 1205425 | E14: 20240729evm1937 | G14: EVM1937 | I14: 1937 | J14: техникум | K14: Коковино | L14: Пятиусово | M14: Нас там обучилось | N14: с | O14: Западной Двины человек двенадцать. | P14: Западная Двина | Q14: 1 | R14: 0 | S14: 0 | T14: 0 | U14: 0 | V14: 0 | W14: 0 | X14: 0 | Y14: 0 | Z14: 0 | AA14: 0 | AB14: 0 | AC14: 0 | AD14: a | AE14: n | AF14: n
A15: Корпус говора деревни Пятиусово | B15: 620 | C15: 2148950 | D15: 2152260 | E15: 20240729evm1937 | G15: EVM1937 | I15: 1937 | J15: техникум | K15: Коковино | L15: Пятиусово | M15: Из ( | N15: с | O15: ) Каськово пришли? А ну Каськово вы знаете, вы в Каськово... | P15: Каськово | Q15: 1 | R15: 0 | S15: 0 | T15: 0 | U15: 0 | V15: 0 | W15: 0 | X15: 0 | Y15: 0 | Z15: 0 | AA15: 0 | AB15: 0 | AC15: 0 | AD15: s | AE15: v | AF15: n
A16: Корпус говора деревни Пятиусово | B16: 662 | C16: 2314500 | D16: 2318730 | E16: 20240729evm1937 | G16: EVM1937 | I16: 1937 | J16: техникум | K16: Коковино | L16: Пятиусово | M16: У меня товарищ бывало приезжал | N16: с | O16: Треста, с Калинина в гости. | P16: Треста | Q16: 1 | R16: 0 | S16: 0 | T16: 0 | U16: 0 | V16: 0 | W16: 0 | X16: 0 | Y16: 0 | Z16: 0 | AA16: 0 | AB16: 0 | AC16: 0 | AD16: s | AE16: v | AF16: n
A17: Корпус говора деревни Пятиусово | B17: 662 | C17: 2314500 | D17: 2318730 | E17: 20240729evm1937 | G17: EVM1937 | I17: 1937 | J17: техникум | K17: Коковино | L17: Пятиусово | M17: У меня товарищ бывало приезжал с Треста, | N17: с | O17: Калинина в гости. | P17: Калинина | Q17: 1 | R17: 0 | S17: 0 | T17: 0 | U17: 0 | V17: 0 | W17: 0 | X17: 0 | Y17: 0 | Z17: 0 | AA17: 0 | AB17: 0 | AC17: 0 | AD17: s | AE17: v | AF17: n
A18: Корпус говора деревни Пятиусово | B18: 716 | C18: 2686180 | D18: 2688610 | E18: 20240729evm1937 | G18: EVM1937 | I18: 1937 | J18: техникум | K18: Коковино | L18: Пятиусово | M18: И | N18: со | O18: со льна сделали с этого волокно. | P18: лен | Q18: 0 | R18: 0 | S18: 0 | T18: 0 | U18: 0 | V18: 0 | W18: 0 | X18: 0 | Y18: 1 | Z18: 0 | AA18: 0 | AB18: 0 | AC18: 0 | AD18: o | AE18: v | AF18: n
A19: Корпус говора деревни Пятиусово | B19: 718 | C19: 2693990 | D19: 2698740 | E19: 20240729evm1937 | G19: EVM1937 | I19: 1937 | J19: техникум | K19: Коковино | L19: Пятиусово | M19: И | N19: с | O19: этого материала шили брюки, кафтан. | P19: материал | Q19: 0 | R19: 0 | S19: 0 | T19: 0 | U19: 0 | V19: 0 | W19: 0 | X19: 0 | Y19: 1 | Z19: 0 | AA19: 0 | AB19: 0 | AC19: 0 | AD19: o | AE19: v | AF19: n
A20: Корпус говора деревни Пятиусово | B20: 743 | C20: 2802927 | D20: 2809144 | E20: 20240729evm1937 | G20: EVM1937 | I20: 1937 | J20: техникум | K20: Коковино | L20: Пятиусово | M20: Она строилась так, чтобы со всех деревень, | N20: с | O20: округи, был доступ одинаков. | P20: округи | Q20: 0 | R20: 1 | S20: 0 | T20: 0 | U20: 0 | V20: 0 | W20: 0 | X20: 0 | Y20: 0 | Z20: 0 | AA20: 0 | AB20: 0 | AC20: 0 | AD20: a | AE20: n | AF20: n
A21: Корпус говора деревни Пятиусово | B21: 764 | C21: 2909762 | D21: 2912855 | E21: 20240729evm1937 | G21: EVM1937 | I21: 1937 | J21: техникум | K21: Коковино | L21: Пятиусово | M21: Мужики приходят | N21: с | O21: деревень, которые пять - шесть киллометров. | P21: деревни | Q21: 0 | R21: 1 | S21: 0 | T21: 0 | U21: 0 | V21: 0 | W21: 0 | X21: 0 | Y21: 0 | Z21: 0 | AA21: 0 | AB21: 0 | AC21: 0 | AD21: s | AE21: v | AF21: n
... A42: Корпус говора деревни Пятиусово | B42: 1361 | C42: 1611447 | D42: 1631875 | E42: 20231023pvv1935 | G42: PVV1935 | I42: 1935 | J42: техникум | K42: Пятиусово | L42: Пятиусово | M42: И это... Посадить... То есть принесла | N42: с | O42: почты севок этом мне (мене). Ну и грядку помогла мне... Было земля под осень сделанная... Посадили, я её (ее) потихонечку пропалывал, лук поливал, чеснок не поливал. | P42: почта | Q42: 0 | R42: 0 | S42: 0 | T42: 0 | U42: 1 | V42: 0 | W42: 0 | X42: 0 | Y42: 0 | Z42: 0 | AA42: 0 | AB42: 0 | AC42: 0 | AD42: s | AE42: v | AF42: y
A43: Корпус говора деревни Пятиусово | B43: 1462 | C43: 53840 | D43: 57140 | E43: 20240728zes1942 | M43: А сейчас вроде бы дочка приехадчи, из ( | N43: с | O43: ) Ленинграда приехала. | P43: Ленинграда | Q43: 1 | R43: 0 | S43: 0 | T43: 0 | U43: 0 | V43: 0 | W43: 0 | X43: 0 | Y43: 0 | Z43: 0 | AA43: 0 | AB43: 0 | AC43: 0 | AD43: s | AE43: v | AF43: n
A44: Корпус говора деревни Пятиусово | B44: 1463 | C44: 57480 | D44: 65630 | E44: 20240728zes1942 | M44: Она живёт в своём доме. Это как и = с = из ( | N44: с | O44: ) Каськово идёте прямо, так сразу первый дом, а на правую руку голубой. | P44: Каськово | Q44: 1 | R44: 0 | S44: 0 | T44: 0 | U44: 0 | V44: 0 | W44: 0 | X44: 0 | Y44: 0 | Z44: 0 | AA44: 0 | AB44: 0 | AC44: 0 | AD44: s | AE44: v | AF44: n
A45: Корпус говора деревни Пятиусово | B45: 1464 | C45: 67240 | D45: 73340 | E45: 20240728zes1942 | M45: Да, сразу как | N45: с | O45: Каськова вышли, с Пахнова вышли, к нам идёте уже, уже Пятиусово вы пришли. | P45: Каськова | Q45: 1 | R45: 0 | S45: 0 | T45: 0 | U45: 0 | V45: 0 | W45: 0 | X45: 0 | Y45: 0 | Z45: 0 | AA45: 0 | AB45: 0 | AC45: 0 | AD45: s | AE45: v | AF45: n
A46: Корпус говора деревни Пятиусово | B46: 1464 | C46: 67240 | D46: 73340 | E46: 20240728zes1942 | M46: Да, сразу как с Каськова вышли, | N46: с | O46: Пахнова вышли, к нам идёте уже, уже Пятиусово вы пришли. | P46: Пахнова | Q46: 1 | R46: 0 | S46: 0 | T46: 0 | U46: 0 | V46: 0 | W46: 0 | X46: 0 | Y46: 0 | Z46: 0 | AA46: 0 | AB46: 0 | AC46: 0 | AD46: s | AE46: v | AF46: n
A47: Корпус говора деревни Пятиусово | B47: 1465 | C47: 73580 | D47: 81840 | E47: 20240728zes1942 | M47: Сразу этот дом направо первый, если | N47: с | O47: Каськова идти. А если... А если от нас вы пойдёте, то на левую руку последний. | P47: Каськова | Q47: 1 | R47: 0 | S47: 0 | T47: 0 | U47: 0 | V47: 0 | W47: 0 | X47: 0 | Y47: 0 | Z47: 0 | AA47: 0 | AB47: 0 | AC47: 0 | AD47: s | AE47: v | AF47: n
A48: Корпус говора деревни Пятиусово | B48: 1572 | C48: 562070 | D48: 567890 | E48: 20240728zes1942 | M48: Туда делали лепёшки | N48: с | O48: гли =. Ну, детская игра, туда ставили. Вот такая игра была. Больше ничего. | P48: глины | Q48: 0 | R48: 0 | S48: 0 | T48: 0 | U48: 0 | V48: 0 | W48: 0 | X48: 0 | Y48: 1 | Z48: 0 | AA48: 0 | AB48: 0 | AC48: 0 | AD48: o | AE48: v | AF48: n
A49: Корпус говора деревни Пятиусово | B49: 1615 | C49: 773280 | D49: 778770 | E49: 20240728zes1942 | M49: А потом вот в Даниловское. Это надо было идти из ( | N49: с | O49: ) Пятиусова два километра или три. | P49: Пятиусова | Q49: 1 | R49: 0 | S49: 0 | T49: 0 | U49: 0 | V49: 0 | W49: 0 | X49: 0 | Y49: 0 | Z49: 0 | AA49: 0 | AB49: 0 | AC49: 0 | AD49: s | AE49: v | AF49: n
A50: Корпус говора деревни Пятиусово | B50: 1711 | C50: 1255100 | D50: 1260000 | E50: 20240728zes1942 | M50: А так как она ездила на лошадях, она всегда из ( | N50: с | O50: ) Пятиусово что - то приве = привезёт. | P50: Пятиусово | Q50: 1 | R50: 0 | S50: 0 | T50: 0 | U50: 0 | V50: 0 | W50: 0 | X50: 0 | Y50: 0 | Z50: 0 | AA50: 0 | AB50: 0 | AC50: 0 | AD50: s | AE50: v | AF50: n
A51: Корпус говора деревни Пятиусово | B51: 2034 | C51: 2709900 | D51: 2713880 | E51: 20240728zes1942 | M51: Он был, я скажу: как | N51: с | O51: Торопы (Торопи) едите, так сразу. | P51: Торопы | Q51: 1 | R51: 0 | S51: 0 | T51: 0 | U51: 0 | V51: 0 | W51: 0 | X51: 0 | Y51: 0 | Z51: 0 | AA51: 0 | AB51: 0 | AC51: 0 | AD51: s | AE51: v | AF51: n
A52: Корпус говора деревни Пятиусово | B52: 2051 | C52: 2770090 | D52: 2775070 | E52: 20240728zes1942 | M52: Тоже как выезжаешь из ( | N52: с | O52: ) Торопы (Торопи) в низине (низина) дом стоит в низине (низина), красная крыша, по - моему, и там что - то ещё. | P52: Торопы | Q52: 1 | R52: 0 | S52: 0 | T52: 0 | U52: 0 | V52: 0 | W52: 0 | X52: 0 | Y52: 0 | Z52: 0 | AA52: 0 | AB52: 0 | AC52: 0 | AD52: s | AE52: v | AF52: n
A53: Корпус говора деревни Пятиусово | B53: 2099 | C53: 2944800 | D53: 2948090 | E53: 20240728zes1942 | M53: Сейчас скажу кто учился, | N53: с | O53: каких деревень. Так. | P53: деревень | Q53: 0 | R53: 1 | S53: 0 | T53: 0 | U53: 0 | V53: 0 | W53: 0 | X53: 0 | Y53: 0 | Z53: 0 | AA53: 0 | AB53: 0 | AC53: 0 | AD53: a | AE53: n | AF53: n
A54: Корпус говора деревни Пятиусово | B54: 2129 | C54: 3033810 | D54: 3039380 | E54: 20240728zes1942 | M54: И тогда вот дочка моя уже ходила из ( | N54: с | O54: ) Каськово, ходила в Пятиусововот в эту шк =. | P54: Каськово | Q54: 1 | R54: 0 | S54: 0 | T54: 0 | U54: 0 | V54: 0 | W54: 0 | X54: 0 | Y54: 0 | Z54: 0 | AA54: 0 | AB54: 0 | AC54: 0 | AD54: s | AE54: v | AF54: n
... A76: Корпус говора деревни Пятиусово | B76: 3889 | C76: 1511350 | D76: 1514520 | E76: 20240802zes1942 | M76: Они сами от нас, так, | N76: с | O76: Каськова. Они жили... | P76: Каськова | Q76: 1 | R76: 0 | S76: 0 | T76: 0 | U76: 0 | V76: 0 | W76: 0 | X76: 0 | Y76: 0 | Z76: 0 | AA76: 0 | AB76: 0 | AC76: 0 | AD76: a | AE76: n | AF76: n
A77: Корпус говора деревни Пятиусово | B77: 4057 | C77: 2096660 | D77: 2099150 | E77: 20240802zes1942 | N77: С | O77: Горькова? Ну вот где - то туда, где - то в хозяйства туда. | P77: Горькова | Q77: 1 | R77: 0 | S77: 0 | T77: 0 | U77: 0 | V77: 0 | W77: 0 | X77: 0 | Y77: 0 | Z77: 0 | AA77: 0 | AB77: 0 | AC77: 0 | AD77: a | AE77: n | AF77: n
A78: Корпус говора деревни Пятиусово | B78: 4134 | C78: 2333610 | D78: 2339270 | E78: 20240802zes1942 | M78: Ты, говорю, видишь? Если сверху смотреть | N78: с | O78: самолёта, то я живу в кругу борщевика. | P78: самолёта | Q78: 0 | R78: 0 | S78: 0 | T78: 0 | U78: 0 | V78: 0 | W78: 0 | X78: 1 | Y78: 0 | Z78: 0 | AA78: 0 | AB78: 0 | AC78: 0 | AD78: s | AE78: v | AF78: n
A79: Корпус говора деревни Пятиусово | B79: 4235 | C79: 2657390 | D79: 2659770 | E79: 20240802zes1942 | M79: А в = выключите | N79: с | O79: розетки! | P79: розетки | Q79: 0 | R79: 0 | S79: 0 | T79: 0 | U79: 0 | V79: 0 | W79: 0 | X79: 1 | Y79: 0 | Z79: 0 | AA79: 0 | AB79: 0 | AC79: 0 | AD79: s | AE79: v | AF79: n
A80: Корпус говора деревни Пятиусово | B80: 4408 | C80: 3175420 | D80: 3184220 | E80: 20240802zes1942 | M80: И у нас печа была большая. Я даже не знаю из (с) чего она. Мать сказала, из ( | N80: с | O80: ) камней, вроде, сделана была эта. Она сделана ещё до = до войны. | P80: камней | Q80: 0 | R80: 0 | S80: 0 | T80: 0 | U80: 0 | V80: 0 | W80: 0 | X80: 0 | Y80: 1 | Z80: 0 | AA80: 0 | AB80: 0 | AC80: 0 | AD80: o | AE80: v | AF80: n
A81: Корпус говора деревни Пятиусово | B81: 4410 | C81: 3185030 | D81: 3186490 | E81: 20240802zes1942 | N81: С | O81: хутора перевезена. | P81: хутора | Q81: 0 | R81: 0 | S81: 1 | T81: 0 | U81: 0 | V81: 0 | W81: 0 | X81: 0 | Y81: 0 | Z81: 0 | AA81: 0 | AB81: 0 | AC81: 0 | AD81: s | AE81: v | AF81: n
A82: Корпус говора деревни Пятиусово | B82: 4411 | C82: 3186850 | D82: 3190630 | E82: 20240802zes1942 | M82: Она... С = из ( | N82: с | O82: ) камней делали. Она большая была тоже. | P82: камней | Q82: 0 | R82: 0 | S82: 0 | T82: 0 | U82: 0 | V82: 0 | W82: 0 | X82: 0 | Y82: 1 | Z82: 0 | AA82: 0 | AB82: 0 | AC82: 0 | AD82: o | AE82: v | AF82: n
A83: Корпус говора деревни Пятиусово | B83: 4461 | C83: 3375580 | D83: 3379690 | E83: 20240802zes1942 | M83: А у вас там это, сделана вода | N83: с | O83: колод = колодец? | P83: колод | Q83: 0 | R83: 0 | S83: 0 | T83: 0 | U83: 0 | V83: 0 | W83: 0 | X83: 1 | Y83: 0 | Z83: 0 | AA83: 0 | AB83: 0 | AC83: 0 | AD83: s | AE83: v | AF83: n
A84: Корпус говора деревни Пятиусово | B84: 4752 | C84: 4179470 | D84: 4183450 | E84: 20240802zes1942 | M84: Кручу ведь её, чтобы она не выбивалась, | N84: с | O84: рук не в = били. | P84: рук | Q84: 0 | R84: 0 | S84: 0 | T84: 0 | U84: 0 | V84: 0 | W84: 0 | X84: 1 | Y84: 0 | Z84: 0 | AA84: 0 | AB84: 0 | AC84: 0 | AD84: s | AE84: v | AF84: n
A85: Корпус говора деревни Пятиусово | B85: 4902 | C85: 4570480 | D85: 4573260 | E85: 20240802zes1942 | M85: И | N85: с | O85: этой горы выбивает такая как скважина. | P85: горы | Q85: 0 | R85: 0 | S85: 0 | T85: 1 | U85: 0 | V85: 0 | W85: 0 | X85: 0 | Y85: 0 | Z85: 0 | AA85: 0 | AB85: 0 | AC85: 0 | AD85: s | AE85: v | AF85: n
A86: Корпус говора деревни Пятиусово | B86: 4983 | C86: 4833000 | D86: 4838210 | E86: 20240802zes1942 | M86: Он только пришёл | N86: с | O86: армии. И он курил на = на придворке. И тут мы закричали, заохали все. | P86: армии | Q86: 0 | R86: 0 | S86: 0 | T86: 0 | U86: 0 | V86: 0 | W86: 0 | X86: 0 | Y86: 0 | Z86: 1 | AA86: 0 | AB86: 0 | AC86: 0 | AD86: s | AE86: v | AF86: n
A87: Корпус говора деревни Пятиусово | B87: 5157 | C87: 180799 | D87: 191649 | E87: 20240804zes1942 | M87: Да, | N87: с | O87: Пятиусова два километра как раньше ходили напрямую, сейчас во = вокруг ходят на кладбище туда, а раньше была дорога напрямую, два километра. | P87: Пятиусова | Q87: 1 | R87: 0 | S87: 0 | T87: 0 | U87: 0 | V87: 0 | W87: 0 | X87: 0 | Y87: 0 | Z87: 0 | AA87: 0 | AB87: 0 | AC87: 0 | AD87: s | AE87: v | AF87: n
A88: Корпус говора деревни Пятиусово | B88: 5198 | C88: 1300600 | D88: 1309300 | E88: 20240804zes1942 | M88: Сразу с магазина, нет, вот | N88: с | O88: магазина по одной линии, вон мага = магазин, там тут (тута) он живёт, тут магазин, вот. | P88: магазина | Q88: 0 | R88: 0 | S88: 0 | T88: 0 | U88: 1 | V88: 0 | W88: 0 | X88: 0 | Y88: 0 | Z88: 0 | AA88: 0 | AB88: 0 | AC88: 0 | AD88: s | AE88: v | AF88: n
A89: Корпус говора деревни Пятиусово | B89: 5209 | C89: 1593900 | D89: 1611500 | E89: 20240804zes1942 | M89: А кладбище, так я сейчас вам | N89: с | O89: Торопы правильно идти, вот дорога кончается, как едете в Торопу, да, последний поворот будет на = налево, вон там там на последнем повороте живёт Елена Александровна, учительница. | P89: Торопы | Q89: 1 | R89: 0 | S89: 0 | T89: 0 | U89: 0 | V89: 0 | W89: 0 | X89: 0 | Y89: 0 | Z89: 0 | AA89: 0 | AB89: 0 | AC89: 0 | AD89: s | AE89: v | AF89: n
A90: Корпус говора деревни Пятиусово | B90: 5218 | C90: 1657639 | D90: 1659773 | E90: 20240804zes1942 | M90: Проходите, заходите, я только | N90: с | O90: бани. | P90: бани | Q90: 0 | R90: 0 | S90: 0 | T90: 0 | U90: 1 | V90: 0 | W90: 0 | X90: 0 | Y90: 0 | Z90: 0 | AA90: 0 | AB90: 0 | AC90: 0 | AD90: s | AE90: v | AF90: n
A91: Корпус говора деревни Пятиусово | B91: 5260 | C91: 2498500 | D91: 2607700 | E91: 20240804zes1942 | M91: < нрзб > пятый класс был вот, да, она в пятый класс перешла, на второй год осталась, ну и она не стала, не пошла на второй год. Ну взяли как ребёнка чистить вот эти дороги, ну тогда денег не было, колхоз денег, мы жили в колхозе, в колхозе денег не давали, денег никаких не было, были одни эти, палки назывались, ну и поэтому тогда, а там какие - то деньги платили мизерные, но всё равно платили, так оно вот постепенно и потом она вот в Кунье, она потом подросла, в Кунью, бывало, в Кунье, а бывало, сезон, наверное, там что - то на стройке что - то строили в Кунье, а потом стали вербовать н = на Украину в Ро = в Ростов, не, Ростов, я забыла, на Украину куда, она называла, но я забыла, в какой совхоз, и от нас четыре девочки ездили на Украину в совхоз и там убирали брюкву, урожай, ещё что - то, она называла, я теперь не забыла, но а осенью, когда уже нас приняли в совхоз, я написала ей, сказала, не оставайся, приезжай домой н = м = нас мы теперь зде = на деньги, за деньги (деньга) день = деньги будем получать. Вот и они осенью приехали домой, четверо девочек, они привезла два мешка песка оттуда | N91: с | O91: Украины, приезла два мешка семечек, ещё что - то, ше =, по - моему, шесть мешков, ещё, я забыла что привезла. То ли муки или что - то что - то ещё < нрзб > была дана, их в нашей деревне две было, одна моя сестра и ещё девочка их, вот так оттуда они приехали и денег привезли оттуда и питание это такое, какое давали. | P91: Украины | Q91: 1 | R91: 0 | S91: 0 | T91: 0 | U91: 0 | V91: 0 | W91: 0 | X91: 0 | Y91: 0 | Z91: 0 | AA91: 0 | AB91: 0 | AC91: 0 | AD91: s | AE91: v | AF91: y
A92: Корпус говора деревни Пятиусово | B92: 5271 | C92: 3091200 | D92: 3164300 | E92: 20240804zes1942 | M92: А так ну мно = много помню, всё из детства, я думаю, с трёх годов, с трёх лет я чу всё на свете помню, с трёх, если не раньше. Всё ка = как раньше же не было это самое во время войны мне было в сорок пятом году три года было < нрзб > четвёртый шёл, и ну я думаю, это года два мои, я думаю, мне года два было, и тогда был год ну чего - то такой голодный год был совсем, и вот я не помню только сейчас, не могу ск =, лошади то ли умерли (умёрши были) и к = погибали, наверное, и знаю, что бабушка принесла или кто - то принёс ей, она варила это мясо в печке, печи были, печи, в чугунке, чугунки были, в чугунке варила мясо, это потом | N92: с | O92: чугунка вытянула, и стол и дом тот сейчас стоит старый, поставила на стол, вытянула она такие лавки раньше были, ничего не было, одни скамейки были. Ну и она разложила меленько, она мясо такое длинное, помню это, она меленько разрезала, вот ешь потихонечку, это помню хорошо. | P92: чугунка | Q92: 0 | R92: 0 | S92: 0 | T92: 0 | U92: 0 | V92: 0 | W92: 0 | X92: 1 | Y92: 0 | Z92: 0 | AA92: 0 | AB92: 0 | AC92: 0 | AD92: s | AE92: v | AF92: n
A93: Корпус говора деревни Пятиусово | B93: 5311 | C93: 4342000 | D93: 4367000 | E93: 20240804zes1942 | M93: Ну ну если у ва = если у вас курица есть, обрежете лопатки все, я как делаю, ну я одна же у вас компания большая, я не знаю, как вы, я делаю этой самой все мякоть, кости эти варю, разрублю и кидаю, а | N93: с | O93: мякоти можете хоть котлет (котлетин) изпечь, хоть там что вы делаете, картошку в сделаете как фарш что, что захотите (захочите). | P93: мякоти | Q93: 0 | R93: 0 | S93: 0 | T93: 0 | U93: 0 | V93: 0 | W93: 0 | X93: 0 | Y93: 1 | Z93: 0 | AA93: 0 | AB93: 0 | AC93: 0 | AD93: o | AE93: v | AF93: n
A94: Корпус говора деревни Пятиусово | B94: 5347 | C94: 164260 | D94: 169000 | E94: 20231023vpm1934_1 | G94: VPM1934 | I94: 1934 | J94: техникум | K94: Ануфриево | L94: Пятиусово | M94: Ну рассказывайте, где вы были. В Каськове в своём? | N94: С | O94: Касько = | P94: Каськово | Q94: 1 | R94: 0 | S94: 0 | T94: 0 | U94: 0 | V94: 0 | W94: 0 | X94: 0 | Y94: 0 | Z94: 0 | AA94: 0 | AB94: 0 | AC94: 0 | AD94: s | AE94: v | AF94: n
A95: Корпус говора деревни Пятиусово | B95: 5387 | C95: 704120 | D95: 786800 | E95: 20231023vpm1934_1 | G95: VPM1934 | I95: 1934 | J95: техникум | K95: Ануфриево | L95: Пятиусово | M95: Семь. Раньше и было семь. Спасибо, хоть что семь по = отходила. Семь. Семь. В Фофаново училась я. Ну а с = | N95: с | O95: Ануфриево или с = с Ануфриево Фофаново, там одинаковое там расстояние, ходила на работу. Я к восьми часам... Вот видишь, у меня было... Я сюда приехала в двадцать лет, а там было восемнадцать - девятнадцать. В таком возрасте пять - шесть километров ходила пешком на работу. Ну и с работы приходишь, а потом ходили в понедельник, среду и пятницу ходили на курсы медицинских сестёр. Учились после пяти, к семи часам. В два часа приходили домой, а к восьми опять на работу. Так что придёшь... Всякое было. Хорошего не было, ну и что? Сейчас, говорят, тяжело, ну и раньше было тоже не легко. Ну с = самое страшное, девочки милые, чтобы не было войны. Жить можно, картошину постную можно есть (есь), траву есть (есь), чтобы тихо было. Не... Чтобы не было войны. Всё. Я немцев видела, знаю. | P95: Ануфриево | Q95: 1 | R95: 0 | S95: 0 | T95: 0 | U95: 0 | V95: 0 | W95: 0 | X95: 0 | Y95: 0 | Z95: 0 | AA95: 0 | AB95: 0 | AC95: 0 | AD95: s | AE95: v | AF95: n
A96: Корпус говора деревни Пятиусово | B96: 5408 | C96: 1186732 | D96: 1196165 | E96: 20231023vpm1934_1 | G96: VPM1934 | I96: 1934 | J96: техникум | K96: Ануфриево | L96: Пятиусово | M96: Нас... Нас выгнали | N96: с | O96: деревни с этой, чтобы нем = первые это... Чтобы немцам этим жить. | P96: деревни | Q96: 0 | R96: 1 | S96: 0 | T96: 0 | U96: 0 | V96: 0 | W96: 0 | X96: 0 | Y96: 0 | Z96: 0 | AA96: 0 | AB96: 0 | AC96: 0 | AD96: s | AE96: v | AF96: n
A97: Корпус говора деревни Пятиусово | B97: 5631 | C97: 2644240 | D97: 2652080 | E97: 20231023vpm1934_1 | G97: VPM1934 | I97: 1934 | J97: техникум | K97: Ануфриево | L97: Пятиусово | M97: Они же в магазин - - едят свою, а я свою. Каши готовим, правда каши я беру из ( | N97: с | O97: ) магазина, тоже под = по = добавляю. | P97: магазина | Q97: 0 | R97: 0 | S97: 0 | T97: 0 | U97: 1 | V97: 0 | W97: 0 | X97: 0 | Y97: 0 | Z97: 0 | AA97: 0 | AB97: 0 | AC97: 0 | AD97: s | AE97: v | AF97: n
A98: Корпус говора деревни Пятиусово | B98: 5633 | C98: 2657880 | D98: 2660900 | E98: 20231023vpm1934_1 | G98: VPM1934 | I98: 1934 | J98: техникум | K98: Ануфриево | L98: Пятиусово | M98: Тереп =. Питьё всё из ( | N98: с | O98: ) магазина берут. | P98: магазина | Q98: 0 | R98: 0 | S98: 0 | T98: 0 | U98: 1 | V98: 0 | W98: 0 | X98: 0 | Y98: 0 | Z98: 0 | AA98: 0 | AB98: 0 | AC98: 0 | AD98: s | AE98: v | AF98: n
A99: Корпус говора деревни Пятиусово | B99: 5700 | C99: 2965220 | D99: 2966460 | E99: 20231023vpm1934_1 | G99: VPM1934 | I99: 1934 | J99: техникум | K99: Ануфриево | L99: Пятиусово | M99: Дочка из ( | N99: с | O99: ) Москвы. | P99: Москвы | Q99: 1 | R99: 0 | S99: 0 | T99: 0 | U99: 0 | V99: 0 | W99: 0 | X99: 0 | Y99: 0 | Z99: 0 | AA99: 0 | AB99: 0 | AC99: 0 | AD99: s | AE99: v | AF99: n
A100: Корпус говора деревни Пятиусово | B100: 4408 | C100: 3175420 | D100: 3184220 | E100: 20240802zes1942 | M100: И у нас печа была большая. Я даже не знаю из (с) чего она. Мать сказала, | N100: с | O100: (с) камней, вроде, сделана была эта. Она сделана ещё до = до войны. | P100: камней | Q100: 0 | R100: 0 | S100: 0 | T100: 0 | U100: 0 | V100: 0 | W100: 0 | X100: 0 | Y100: 1 | Z100: 0 | AA100: 0 | AB100: 0 | AC100: 0 | AD100: o | AE100: v | AF100: n
A101: Корпус говора деревни Пятиусово | B101: 5294 | C101: 3765200 | D101: 3767240 | E101: 20240804zes1942 | M101: В хлев? | N101: с | O101: хлева? В поле? | P101: хлева | Q101: 0 | R101: 0 | S101: 0 | T101: 0 | U101: 0 | V101: 1 | W101: 0 | X101: 0 | Y101: 0 | Z101: 0 | AA101: 0 | AB101: 0 | AC101: 0 | AD101: s | AE101: v | AF101: n
A102: Корпус говора деревни Пятиусово | B102: 5295 | C102: 3767240 | D102: 3812000 | E102: 20240804zes1942 | N102: с | O102: хлева в поле в основном шестого мая, в Егорий. Старались в это день, но если сена не =, если травы нет в поле, один год не было травы в поле до, сейчас скажу, до девятнадцатого мая травы не было, был холод как - то один год, и вот Пятиусовские гоняли в Троицкое, есть такое туда. Первое июня, потому что не было травы, а личный скот пускали числа, наверное, пятнадцатого мая, это в зависимости, как есть трава, ну а сейчас его в деревне три коровы, они у всех на привязи, на цепях, там надо в поле и поесть (поись) и < нрзб >. | P102: хлева | Q102: 0 | R102: 0 | S102: 0 | T102: 0 | U102: 0 | V102: 1 | W102: 0 | X102: 0 | Y102: 0 | Z102: 0 | AA102: 0 | AB102: 0 | AC102: 0 | AD102: s | AE102: v | AF102: n
A103: Корпус говора деревни Пятиусово | B103: 5307 | C103: 4186800 | D103: 4277560 | E103: 20240804zes1942 | M103: Я = яйца, да, и яйца сдавали в совхоз, ну сами са = сами эти (эты) не, я думаю, ни разу, я не помню, чтобы мы сдавали мясо. А вот когда куры были, сдавали, кур было много, и каждый день возили в в ящиках (ящикам) больших (большим) по шестьсот штук в ящике были. Быва = бывало, это яйца, наверное, летом, летом, наверное, по шесть ящиков и даже в день были, ну много было кур и много яи = яиц было, и были большие расклёвы, а = курица курицу может расклевать, потому что не хватает, мяса давали, мяса, если какая - то, там < нрзб > что - то, то резали, там привозили к нам, и мы варили в котлах, в котлах вместе с картошкой с < нрзб > и давали, тогда вроде поменьше клю =, ну если расклёв был, то нас мы заста нас заставляли сразу её резать, ну в кипяток сажали, вычищали, и только голову себе оставляли, ноги потро = потроха, это себе оставляли, а если, а это сдавали. Вот это самое < нрзб > каждый день суп готовили | N103: с | O103: потрохов, вкусно были, боже мой, хорошо, сейчас в магазине возьму курицу, я даже есть её не могу, она чем - то пахнет, не понимаю я, обвариваю, обвариваю кипятком, и как - то не з = не понимаю, что такое раньше, то ли корм может (може) не такой, что, не знаю. | P103: потрохов | Q103: 0 | R103: 0 | S103: 0 | T103: 0 | U103: 0 | V103: 0 | W103: 0 | X103: 0 | Y103: 1 | Z103: 0 | AA103: 0 | AB103: 0 | AC103: 0 | AD103: o | AE103: v | AF103: n
A104: Корпус говора деревни Пятиусово | B104: 5310 | C104: 4338600 | D104: 4340440 | E104: 20240804zes1942 | N104: с | O104: курицы? Когда, сейчас? | P104: курицы | Q104: 0 | R104: 0 | S104: 0 | T104: 0 | U104: 0 | V104: 0 | W104: 0 | X104: 0 | Y104: 1 | Z104: 0 | AA104: 0 | AB104: 0 | AC104: 0 | AD104: o | AE104: v | AF104: n
A105: Корпус говора деревни Пятиусово | B105: 384 | C105: 858525 | D105: 868587 | E105: 20240729evm1937 | G105: EVM1937 | I105: 1937 | J105: техникум | K105: Коковино | L105: Пятиусово | M105: Подготовили, конечно, меня туда привез начальник медицинской службы капитан, снизу, | N105: со | O105: Сталиниси. | Q105: 1 | R105: 0 | S105: 0 | T105: 0 | U105: 0 | V105: 0 | W105: 0 | X105: 0 | Y105: 0 | Z105: 0 | AA105: 0 | AB105: 0 | AC105: 0 | AD105: s | AE105: v | AF105: n
A106: Корпус говора деревни Пятиусово | B106: 715 | C106: 2682340 | D106: 2685260 | E106: 20240729evm1937 | G106: EVM1937 | I106: 1937 | J106: техникум | K106: Коковино | L106: Пятиусово | N106: Со | O106: льна, такую культуру лён сеяли. | Q106: 0 | R106: 0 | S106: 0 | T106: 0 | U106: 0 | V106: 0 | W106: 0 | X106: 0 | Y106: 1 | Z106: 0 | AA106: 0 | AB106: 0 | AC106: 0 | AD106: o | AE106: v | AF106: n
A107: Корпус говора деревни Пятиусово | B107: 716 | C107: 2686180 | D107: 2688610 | E107: 20240729evm1937 | G107: EVM1937 | I107: 1937 | J107: техникум | K107: Коковино | L107: Пятиусово | M107: И | N107: со | O107: льна сделали с этого волокно. | Q107: 0 | R107: 0 | S107: 0 | T107: 0 | U107: 0 | V107: 0 | W107: 0 | X107: 0 | Y107: 1 | Z107: 0 | AA107: 0 | AB107: 0 | AC107: 0 | AD107: o | AE107: v | AF107: n
A108: Корпус говора деревни Пятиусово | B108: 743 | C108: 2802927 | D108: 2809144 | E108: 20240729evm1937 | G108: EVM1937 | I108: 1937 | J108: техникум | K108: Коковино | L108: Пятиусово | M108: Она строилась так, чтобы | N108: со | O108: всех деревень, с округи, был доступ одинаков. | Q108: 0 | R108: 1 | S108: 0 | T108: 0 | U108: 0 | V108: 0 | W108: 0 | X108: 0 | Y108: 0 | Z108: 0 | AA108: 0 | AB108: 0 | AC108: 0 | AD108: s | AE108: v | AF108: n
A109: Корпус говора деревни Пятиусово | B109: 2185 | C109: 3280890 | D109: 3285480 | E109: 20240728zes1942 | M109: Ну | N109: со | O109: всех деревни, ну и у = вот учительница научит там и всё у неё (ней) спросите. | Q109: 0 | R109: 1 | S109: 0 | T109: 0 | U109: 0 | V109: 0 | W109: 0 | X109: 0 | Y109: 0 | Z109: 0 | AA109: 0 | AB109: 0 | AC109: 0 | AD109: a | AE109: n | AF109: n
A110: Корпус говора деревни Пятиусово | B110: 3800 | C110: 1260440 | D110: 1264960 | E110: 20240802zes1942 | M110: А сам дед Петь =, Васька его звали, | N110: со | O110: Спиридова. | Q110: 1 | R110: 0 | S110: 0 | T110: 0 | U110: 0 | V110: 0 | W110: 0 | X110: 0 | Y110: 0 | Z110: 0 | AA110: 0 | AB110: 0 | AC110: 0 | AD110: a | AE110: n | AF110: n
A111: Корпус говора деревень Шетнево и Макеево | B111: 106 | C111: 863280 | D111: 874500 | E111: 20230427apb1940_A | G111: apb1940 | H111: f | I111: 1940 | J111: среднее | K111: Паново | L111: Макеево | M111: ... Соседка или кто, говорит: " У меня (мине), - говорит, - так было ". И принесла вот такой | N111: с | O111: холста сшитый мешок и ножки все так были враскорячку. | P111: холст | Q111: 0 | R111: 0 | S111: 0 | T111: 0 | U111: 0 | V111: 0 | W111: 0 | X111: 0 | Y111: 1 | Z111: 0 | AA111: 0 | AB111: 0 | AC111: 0 | AD111: a | AE111: n | AF111: n
A112: Корпус говора деревень Шетнево и Макеево | B112: 207 | C112: 1645300 | D112: 1657560 | E112: 20230427apb1940_A | G112: apb1940 | H112: f | I112: 1940 | J112: среднее | K112: Паново | L112: Макеево | M112: Бывает закоптишь - Господи! Слигом вот таким всё как навешивают много | N112: с | O112: деревни, вот тогда разбирают, кто где вешал в этой бане (бани). | P112: деревня | Q112: 0 | R112: 1 | S112: 0 | T112: 0 | U112: 0 | V112: 0 | W112: 0 | X112: 0 | Y112: 0 | Z112: 0 | AA112: 0 | AB112: 0 | AC112: 0 | AD112: s | AE112: v | AF112: n
A113: Корпус говора деревень Шетнево и Макеево | B113: 211 | C113: 1681140 | D113: 1688020 | E113: 20230427apb1940_A | G113: apb1940 | H113: f | I113: 1940 | J113: среднее | K113: Паново | L113: Макеево | M113: А потом вот | N113: с | O113: Панова с этой деревни, где я родилась, перевезла мамку свою. | P113: Паново | Q113: 1 | R113: 0 | S113: 0 | T113: 0 | U113: 0 | V113: 0 | W113: 0 | X113: 0 | Y113: 0 | Z113: 0 | AA113: 0 | AB113: 0 | AC113: 0 | AD113: s | AE113: v | AF113: n
A114: Корпус говора деревень Шетнево и Макеево | B114: 211 | C114: 1681140 | D114: 1688020 | E114: 20230427apb1940_A | G114: apb1940 | H114: f | I114: 1940 | J114: среднее | K114: Паново | L114: Макеево | M114: А потом вот с Панова | N114: с | O114: этой деревни, где я родилась, перевезла мамку свою. | P114: деревня | Q114: 0 | R114: 1 | S114: 0 | T114: 0 | U114: 0 | V114: 0 | W114: 0 | X114: 0 | Y114: 0 | Z114: 0 | AA114: 0 | AB114: 0 | AC114: 0 | AD114: s | AE114: v | AF114: n
A115: Корпус говора деревень Шетнево и Макеево | B115: 222 | C115: 1773560 | D115: 1782720 | E115: 20230427apb1940_A | G115: apb1940 | H115: f | I115: 1940 | J115: среднее | K115: Паново | L115: Макеево | M115: Есть этого | N115: с | O115: Москвы, где из Подмосковья приеходчи вот туда у нас и держит. | P115: Москва | Q115: 1 | R115: 0 | S115: 0 | T115: 0 | U115: 0 | V115: 0 | W115: 0 | X115: 0 | Y115: 0 | Z115: 0 | AA115: 0 | AB115: 0 | AC115: 0 | AD115: s | AE115: v | AF115: n
A116: Корпус говора деревень Шетнево и Макеево | B116: 259 | C116: 2131240 | D116: 2145500 | E116: 20230427apb1940_A | G116: apb1940 | H116: f | I116: 1940 | J116: среднее | K116: Паново | L116: Макеево | M116: Мы ж ездили втроем в Москву с рюкзаками (рюкзакам). Набираем фрукты, колбасы - всё. Колбасы возили | N116: с | O116: Москвы. Вот. Раньше ж не было этого. | P116: Москва | Q116: 1 | R116: 0 | S116: 0 | T116: 0 | U116: 0 | V116: 0 | W116: 0 | X116: 0 | Y116: 0 | Z116: 0 | AA116: 0 | AB116: 0 | AC116: 0 | AD116: s | AE116: v | AF116: n
A117: Корпус говора деревень Шетнево и Макеево | B117: 275 | C117: 2260100 | D117: 2268940 | E117: 20230427apb1940_A | G117: apb1940 | H117: f | I117: 1940 | J117: среднее | K117: Паново | L117: Макеево | M117: Это вот годов пять не стало. А так... А то бывало из Бенец, | N117: с | O117: Торопы даже приезжали сюда в клуб. | P117: Торопа | Q117: 1 | R117: 0 | S117: 0 | T117: 0 | U117: 0 | V117: 0 | W117: 0 | X117: 0 | Y117: 0 | Z117: 0 | AA117: 0 | AB117: 0 | AC117: 0 | AD117: s | AE117: v | AF117: n
A118: Корпус говора деревень Шетнево и Макеево | B118: 289 | C118: 2375300 | D118: 2392680 | E118: 20230427apb1940_A | G118: apb1940 | H118: f | I118: 1940 | J118: среднее | K118: Паново | L118: Макеево | M118: И с творогом делали, и с изюмом, и с этой... | N118: с | O118: муки (муке) делали. Бывало такое... на сковороды (сковороде) большую разрисуешь, сверху яичком сладким с песком расколотишь, с.. об... ам.. смажешь. И всё. | P118: мука | Q118: 0 | R118: 0 | S118: 0 | T118: 0 | U118: 0 | V118: 0 | W118: 0 | X118: 0 | Y118: 1 | Z118: 0 | AA118: 0 | AB118: 0 | AC118: 0 | AD118: o | AE118: v | AF118: n
A119: Корпус говора деревень Шетнево и Макеево | B119: 301 | C119: 2459020 | D119: 2463880 | E119: 20230427apb1940_A | G119: apb1940 | H119: f | I119: 1940 | J119: среднее | K119: Паново | L119: Макеево | M119: Мне даже ведра не доставалось, даже | N119: с | O119: деревни эти ведра (ведры) тащут. | P119: деревня | Q119: 0 | R119: 1 | S119: 0 | T119: 0 | U119: 0 | V119: 0 | W119: 0 | X119: 0 | Y119: 0 | Z119: 0 | AA119: 0 | AB119: 0 | AC119: 0 | AD119: s | AE119: v | AF119: n
A120: Корпус говора деревень Шетнево и Макеево | B120: 337 | C120: 2688620 | D120: 2700440 | E120: 20230427apb1940_A | G120: apb1940 | H120: f | I120: 1940 | J120: среднее | K120: Паново | L120: Макеево | M120: Да, да, да. Он уже | N120: с | O120: армии пришел. Встречались. В пятьдесят девятом году свадьба была, первого февраля. | P120: армия | Q120: 0 | R120: 0 | S120: 0 | T120: 0 | U120: 0 | V120: 0 | W120: 0 | X120: 0 | Y120: 0 | Z120: 1 | AA120: 0 | AB120: 0 | AC120: 0 | AD120: s | AE120: v | AF120: n
A121: Корпус говора деревень Шетнево и Макеево | B121: 362 | C121: 2850700 | D121: 2858760 | E121: 20230427apb1940_A | G121: apb1940 | H121: f | I121: 1940 | J121: среднее | K121: Паново | L121: Макеево | M121: Я варенья | N121: с | O121: клюквы не варила. Мы варили, у нас черники (черниц) полно было. И малины, всяких, всяких было. | P121: клюква | Q121: 0 | R121: 0 | S121: 0 | T121: 0 | U121: 0 | V121: 0 | W121: 0 | X121: 0 | Y121: 1 | Z121: 0 | AA121: 0 | AB121: 0 | AC121: 0 | AD121: o | AE121: v | AF121: n
A122: Корпус говора деревень Шетнево и Макеево | B122: 428 | C122: 346782 | D122: 348302 | E122: 20210708lxl1941 | G122: lxl1941 | H122: m | I122: 1941 | J122: неоконченное среднее | K122: Степаньково | L122: Макеево | M122: А вы сами | N122: с | O122: Москвы? | P122: Москва | Q122: 1 | R122: 0 | S122: 0 | T122: 0 | U122: 0 | V122: 0 | W122: 0 | X122: 0 | Y122: 0 | Z122: 0 | AA122: 0 | AB122: 0 | AC122: 0 | AD122: a | AE122: n | AF122: n
... A131: Корпус говора деревень Шетнево и Макеево | B131: 764 | C131: 976178 | D131: 986074 | E131: 20210716mga1932 | G131: mga1932 | H131: f | I131: 1932 | J131: начальное | K131: Пожоги | L131: Шетнево | M131: Это годы уже, я... какой, девяностые, наверно, годы, у меня были, эти, внуки, Любины, | N131: с | O131: Ленинграда, пошла в Торопу. | P131: Ленинград | Q131: 1 | R131: 0 | S131: 0 | T131: 0 | U131: 0 | V131: 0 | W131: 0 | X131: 0 | Y131: 0 | Z131: 0 | AA131: 0 | AB131: 0 | AC131: 0 | AD131: a | AE131: n | AF131: n
A132: Корпус говора деревень Шетнево и Макеево | B132: 995 | C132: 2268611 | D132: 2271372 | E132: 20210716mga1932 | G132: mga1932 | H132: f | I132: 1932 | J132: начальное | K132: Пожоги | L132: Шетнево | N132: С | O132: Торопы ходит разве? ходит? | P132: Торопа | Q132: 1 | R132: 0 | S132: 0 | T132: 0 | U132: 0 | V132: 0 | W132: 0 | X132: 0 | Y132: 0 | Z132: 0 | AA132: 0 | AB132: 0 | AC132: 0 | AD132: s | AE132: v | AF132: n
A133: Корпус говора деревень Шетнево и Макеево | B133: 996 | C133: 2284700 | D133: 2288297 | E133: 20210716mga1932 | G133: mga1932 | H133: f | I133: 1932 | J133: начальное | K133: Пожоги | L133: Шетнево | M133: А | N133: с | O133: Торопы по сколько, три дня? | P133: Торопа | Q133: 1 | R133: 0 | S133: 0 | T133: 0 | U133: 0 | V133: 0 | W133: 0 | X133: 0 | Y133: 0 | Z133: 0 | AA133: 0 | AB133: 0 | AC133: 0 | AD133: s | AE133: v | AF133: n
A134: Корпус говора деревень Шетнево и Макеево | B134: 999 | C134: 2298405 | D134: 2319759 | E134: 20210716mga1932 | G134: mga1932 | H134: f | I134: 1932 | J134: начальное | K134: Пожоги | L134: Шетнево | M134: Раньше в Ленинград ходил сквозной | N134: с | O134: Торопы и до Ленинграда ездила, прицепной вагон было, сядешь спокойно, приедешь, и я ездила оттуда к дочке, в Торопе сяду, едешь и домой, и они потом они стали так ходить. | P134: Торопа | Q134: 1 | R134: 0 | S134: 0 | T134: 0 | U134: 0 | V134: 0 | W134: 0 | X134: 0 | Y134: 0 | Z134: 0 | AA134: 0 | AB134: 0 | AC134: 0 | AD134: s | AE134: v | AF134: n
A135: Корпус говора деревень Шетнево и Макеево | B135: 1010 | C135: 2401046 | D135: 2406827 | E135: 20210716mga1932 | G135: mga1932 | H135: f | I135: 1932 | J135: начальное | K135: Пожоги | L135: Шетнево | M135: Деревню не видать, бывало | N135: с | O135: Макеево вся видать деревня, а сейчас пока к Сомову придёшь, всё заросло. | P135: Макеево | Q135: 1 | R135: 0 | S135: 0 | T135: 0 | U135: 0 | V135: 0 | W135: 0 | X135: 0 | Y135: 0 | Z135: 0 | AA135: 0 | AB135: 0 | AC135: 0 | AD135: s | AE135: v | AF135: n
A136: Корпус говора деревень Шетнево и Макеево | B136: 1127 | C136: 3163359 | D136: 3172140 | E136: 20210716mga1932 | G136: mga1932 | H136: f | I136: 1932 | J136: начальное | K136: Пожоги | L136: Шетнево | M136: Колхоз, тогда | N136: с | O136: колхоза не давали паспорт, стандартную справку не давали, паспорт, а без паспорта не брали ж. | P136: колхоз | Q136: 0 | R136: 1 | S136: 0 | T136: 0 | U136: 0 | V136: 0 | W136: 0 | X136: 0 | Y136: 0 | Z136: 0 | AA136: 0 | AB136: 0 | AC136: 0 | AD136: a | AE136: n | AF136: n
A137: Корпус говора деревень Шетнево и Макеево | B137: 1144 | C137: 3263890 | D137: 3276140 | E137: 20210716mga1932 | G137: mga1932 | H137: f | I137: 1932 | J137: начальное | K137: Пожоги | L137: Шетнево | M137: Раньше присылали вот на тракториста, в колхозы разных, учились где - то на трактор, и присылали - вот сестра моя (у сестры моей) тоже был приехадчи с этой, с этой, | N137: с | O137: Осетии. | P137: Осетия | Q137: 1 | R137: 0 | S137: 0 | T137: 0 | U137: 0 | V137: 0 | W137: 0 | X137: 0 | Y137: 0 | Z137: 0 | AA137: 0 | AB137: 0 | AC137: 0 | AD137: s | AE137: v | AF137: n
A138: Корпус говора деревень Шетнево и Макеево | B138: 1400 | C138: 5041097 | D138: 5050392 | E138: 20210716mga1932 | G138: mga1932 | H138: f | I138: 1932 | J138: начальное | K138: Пожоги | L138: Шетнево | M138: Соби = собираем мы это в мешки, в эти пакеты | N138: с | O138: целлофана у нас, и брат отвозит, сын отвозит, в Макеево там свалка. | P138: целлофан | Q138: 0 | R138: 0 | S138: 0 | T138: 0 | U138: 0 | V138: 0 | W138: 0 | X138: 0 | Y138: 1 | Z138: 0 | AA138: 0 | AB138: 0 | AC138: 0 | AD138: a | AE138: n | AF138: n
A139: Корпус говора деревень Шетнево и Макеево | B139: 1500 | C139: 363883 | D139: 369400 | E139: 20220715gip1953 | G139: gip1953 | H139: f | I139: 1953 | J139: среднее | K139: Макеево | L139: Макеево | M139: Техничка топила печку, как она топила.. Наверно... Может обронила уголь какой | N139: с | O139: печки. Ну и... | P139: печка | Q139: 0 | R139: 0 | S139: 0 | T139: 0 | U139: 0 | V139: 0 | W139: 0 | X139: 1 | Y139: 0 | Z139: 0 | AA139: 0 | AB139: 0 | AC139: 0 | AD139: a | AE139: n | AF139: n
A140: Корпус говора деревень Шетнево и Макеево | B140: 1527 | C140: 505171 | D140: 511833 | E140: 20220715gip1953 | G140: gip1953 | H140: f | I140: 1953 | J140: среднее | K140: Макеево | L140: Макеево | N140: С | O140: дому санки брали. И такая была там гора большая, крутая, трамплины такие... Высокая. | P140: дом | Q140: 0 | R140: 0 | S140: 1 | T140: 0 | U140: 0 | V140: 0 | W140: 0 | X140: 0 | Y140: 0 | Z140: 0 | AA140: 0 | AB140: 0 | AC140: 0 | AD140: s | AE140: v | AF140: n
A141: Корпус говора деревень Шетнево и Макеево | B141: 1543 | C141: 597653 | D141: 605144 | E141: 20220715gip1953 | G141: gip1953 | H141: f | I141: 1953 | J141: среднее | K141: Макеево | L141: Макеево | M141: И... В семь уже и шли | N141: с | O141: дому. А то = зима была тёмная. Снег большой. И вот ходили в Степаньково. | P141: дом | Q141: 0 | R141: 0 | S141: 1 | T141: 0 | U141: 0 | V141: 0 | W141: 0 | X141: 0 | Y141: 0 | Z141: 0 | AA141: 0 | AB141: 0 | AC141: 0 | AD141: s | AE141: v | AF141: n
A142: Корпус говора деревень Шетнево и Макеево | B142: 1587 | C142: 865187 | D142: 877511 | E142: 20220715gip1953 | G142: gip1953 | H142: f | I142: 1953 | J142: среднее | K142: Макеево | L142: Макеево | M142: Вот то магазин мы и ходили. и | N142: с | O142: Панова люди шли, с Осташково, вот со Щелкиной... И со Степаньково шли в это один магазин. Вот. Это потом построили вот этот кирпичный... Вот. | P142: Паново | Q142: 1 | R142: 0 | S142: 0 | T142: 0 | U142: 0 | V142: 0 | W142: 0 | X142: 0 | Y142: 0 | Z142: 0 | AA142: 0 | AB142: 0 | AC142: 0 | AD142: s | AE142: v | AF142: n
A143: Корпус говора деревень Шетнево и Макеево | B143: 1587 | C143: 865187 | D143: 877511 | E143: 20220715gip1953 | G143: gip1953 | H143: f | I143: 1953 | J143: среднее | K143: Макеево | L143: Макеево | M143: Вот то магазин мы и ходили. и с Панова люди шли, | N143: с | O143: Осташково, вот со Щелкиной... И со Степаньково шли в это один магазин. Вот. Это потом построили вот этот кирпичный... Вот. | P143: Осташково | Q143: 1 | R143: 0 | S143: 0 | T143: 0 | U143: 0 | V143: 0 | W143: 0 | X143: 0 | Y143: 0 | Z143: 0 | AA143: 0 | AB143: 0 | AC143: 0 | AD143: s | AE143: v | AF143: n
A144: Корпус говора деревень Шетнево и Макеево | B144: 1651 | C144: 1180290 | D144: 1188200 | E144: 20220715gip1953 | G144: gip1953 | H144: f | I144: 1953 | J144: среднее | K144: Макеево | L144: Макеево | M144: Ну а вот сестра моя | N144: с | O144: Ленинграда, а её (еёный) муж - то военный, он прапорщик. И он ему посоветовал поваром. | P144: Ленинград | Q144: 1 | R144: 0 | S144: 0 | T144: 0 | U144: 0 | V144: 0 | W144: 0 | X144: 0 | Y144: 0 | Z144: 0 | AA144: 0 | AB144: 0 | AC144: 0 | AD144: a | AE144: n | AF144: n
A145: Корпус говора деревень Шетнево и Макеево | B145: 1667 | C145: 1277780 | D145: 1280680 | E145: 20220715gip1953 | G145: gip1953 | H145: f | I145: 1953 | J145: среднее | K145: Макеево | L145: Макеево | M145: Ты | N145: с | O145: Москвы сама - то? А ты, доча, откуда? | P145: Москва | Q145: 1 | R145: 0 | S145: 0 | T145: 0 | U145: 0 | V145: 0 | W145: 0 | X145: 0 | Y145: 0 | Z145: 0 | AA145: 0 | AB145: 0 | AC145: 0 | AD145: a | AE145: n | AF145: n
A146: Корпус говора деревень Шетнево и Макеево | B146: 1668 | C146: 1282220 | D146: 1283840 | E146: 20220715gip1953 | G146: gip1953 | H146: f | I146: 1953 | J146: среднее | K146: Макеево | L146: Макеево | M146: А, ты | N146: с | O146: Калужской области... | P146: Калужская область | Q146: 1 | R146: 0 | S146: 0 | T146: 0 | U146: 0 | V146: 0 | W146: 0 | X146: 0 | Y146: 0 | Z146: 0 | AA146: 0 | AB146: 0 | AC146: 0 | AD146: a | AE146: n | AF146: n
A147: Корпус говора деревень Шетнево и Макеево | B147: 1707 | C147: 1498041 | D147: 1507025 | E147: 20220715gip1953 | G147: gip1953 | H147: f | I147: 1953 | J147: среднее | K147: Макеево | L147: Макеево | M147: А сейчас мать моя умерла, сестра живёт в том доме... там такая большая икона. Такая большая икона... | N147: С | O147: церкви она, эта икона, наверное. | P147: церковь | Q147: 0 | R147: 0 | S147: 0 | T147: 0 | U147: 1 | V147: 0 | W147: 0 | X147: 0 | Y147: 0 | Z147: 0 | AA147: 0 | AB147: 0 | AC147: 0 | AD147: a | AE147: n | AF147: n
A148: Корпус говора деревень Шетнево и Макеево | B148: 1853 | C148: 310420 | D148: 313270 | E148: 20210713mga1932 | M148: Был старшина = староста выбранный | N148: с | O148: деревни. | P148: деревня | Q148: 0 | R148: 1 | S148: 0 | T148: 0 | U148: 0 | V148: 0 | W148: 0 | X148: 0 | Y148: 0 | Z148: 0 | AA148: 0 | AB148: 0 | AC148: 0 | AD148: s | AE148: v | AF148: n
A149: Корпус говора деревень Шетнево и Макеево | B149: 1868 | C149: 383720 | D149: 388060 | E149: 20210713mga1932 | M149: Говорит, - работали один | N149: с | O149: Орловской области и еще какой - то с ним были в немцах там. | P149: Орловская область | Q149: 1 | R149: 0 | S149: 0 | T149: 0 | U149: 0 | V149: 0 | W149: 0 | X149: 0 | Y149: 0 | Z149: 0 | AA149: 0 | AB149: 0 | AC149: 0 | AD149: a | AE149: n | AF149: n
...

Sheet предлог_из
A1: Корпус | B1: utterance_id | C1: From | D1: To | E1: File | F1: Id | G1: String id | H1: Gender | I1: Year of birth | J1: Education | K1: Place of birth | L1: Place of living | M1: Left Context | N1: DMatch | O1: Right Context | P1: имя в предложной группе | Q1: Топоним | R1: деревня, город, область, страна и пр. | S1: жилище | T1: природные пространственные локации | U1: учреждения | V1: пространственные локации | W1: остальные употребления | X1: выход из контейнера | Y1: материал | Z1: армия, тюрьма, школа, детский сад, институт , универ, служба(?) фазы жизни | AA1: коллектив, группа | AB1: деньги, заработок, зарплата | AC1: Прайминг | AD1: пространственная/объектная/определительная | AE1: глагольная/именная | AF1: соответствует/не соответствует литературной норме
A2: корпус говора деревни Пятиусово | B2: 329 | C2: 525500 | D2: 529400 | E2: 20240729evm1937 | G2: EVM1937 | I2: 1937 | J2: техникум | K2: Коковино | L2: Пятиусово | N2: Из | O2: Твери там эшелон нас вёз, полный состав. | P2: Твери | Q2: 1 | R2: 0 | S2: 0 | T2: 0 | U2: 0 | V2: 0 | W2: 0 | X2: 0 | Y2: 0 | Z2: 0 | AA2: 0 | AB2: 0 | AC2: 0 | AD2: s | AE2: v | AF2: y
A3: корпус говора деревни Пятиусово | B3: 618 | C3: 2143520 | D3: 2145180 | E3: 20240729evm1937 | G3: EVM1937 | I3: 1937 | J3: техникум | K3: Коковино | L3: Пятиусово | N3: Из | O3: Торопы пешком пришли? | P3: Торопы | Q3: 1 | R3: 0 | S3: 0 | T3: 0 | U3: 0 | V3: 0 | W3: 0 | X3: 0 | Y3: 0 | Z3: 0 | AA3: 0 | AB3: 0 | AC3: 0 | AD3: s | AE3: v | AF3: y
A4: корпус говора деревни Пятиусово | B4: 732 | C4: 2758059 | D4: 2762881 | E4: 20240729evm1937 | G4: EVM1937 | I4: 1937 | J4: техникум | K4: Коковино | L4: Пятиусово | M4: Варежки все вязали шерстяные, | N4: из | O4: овец = из овечей шерсти. | P4: овец (овечей шерсти) | Q4: 0 | R4: 0 | S4: 0 | T4: 0 | U4: 0 | V4: 0 | W4: 0 | X4: 0 | Y4: 1 | Z4: 0 | AA4: 0 | AB4: 0 | AC4: 0 | AD4: o | AE4: v | AF4: y
A5: корпус говора деревни Пятиусово | B5: 801 | C5: 3054494 | D5: 3058020 | E5: 20240729evm1937 | G5: EVM1937 | I5: 1937 | J5: техникум | K5: Коковино | L5: Пятиусово | M5: Так говорят, | N5: из | O5: поля в поле два раза ходит. | P5: поля | Q5: 0 | R5: 0 | S5: 0 | T5: 1 | U5: 0 | V5: 0 | W5: 0 | X5: 0 | Y5: 0 | Z5: 0 | AA5: 0 | AB5: 0 | AC5: 0 | AD5: s | AE5: v | AF5: y
A6: корпус говора деревни Пятиусово | B6: 822 | C6: 3133206 | D6: 3138618 | E6: 20240729evm1937 | G6: EVM1937 | I6: 1937 | J6: техникум | K6: Коковино | L6: Пятиусово | N6: Из | O6: этого волокна потом пряли, из этого льна. | P6: волокна | Q6: 0 | R6: 0 | S6: 0 | T6: 0 | U6: 0 | V6: 0 | W6: 0 | X6: 0 | Y6: 1 | Z6: 0 | AA6: 0 | AB6: 0 | AC6: 0 | AD6: o | AE6: v | AF6: y
A7: корпус говора деревни Пятиусово | B7: 822 | C7: 3133206 | D7: 3138618 | E7: 20240729evm1937 | G7: EVM1937 | I7: 1937 | J7: техникум | K7: Коковино | L7: Пятиусово | M7: Из этого волокна потом пряли, | N7: из | O7: этого льна. | P7: льна | Q7: 0 | R7: 0 | S7: 0 | T7: 0 | U7: 0 | V7: 0 | W7: 0 | X7: 0 | Y7: 1 | Z7: 0 | AA7: 0 | AB7: 0 | AC7: 0 | AD7: o | AE7: v | AF7: y
A8: корпус говора деревни Пятиусово | B8: 930 | C8: 47119 | D8: 53919 | E8: 20231026lng1954 | G8: LNG1954 | I8: 1954 | J8: среднее (10 классов) | K8: Пятиусово | L8: Пятиусово | M8: Ну может на этой основе я | N8: из | O8: своего жизненного опыта взял, что восемьдесят процентов женщин они фригидные. | P8: жизненного опыта | Q8: 0 | R8: 0 | S8: 0 | T8: 0 | U8: 0 | V8: 0 | W8: 1 | X8: 0 | Y8: 0 | Z8: 0 | AA8: 0 | AB8: 0 | AC8: 0 | AD8: o | AE8: v | AF8: y
A9: корпус говора деревни Пятиусово | B9: 1017 | C9: 636012 | D9: 640652 | E9: 20231026lng1954 | G9: LNG1954 | I9: 1954 | J9: среднее (10 классов) | K9: Пятиусово | L9: Пятиусово | M9: Я и = т = | N9: из | O9: породы таких людей: дал слово - - я его сдержу. | P9: порода | Q9: 0 | R9: 0 | S9: 0 | T9: 0 | U9: 0 | V9: 0 | W9: 0 | X9: 0 | Y9: 0 | Z9: 0 | AA9: 1 | AB9: 0 | AC9: 0 | AD9: a | AE9: n | AF9: y
A10: корпус говора деревни Пятиусово | B10: 1199 | C10: 68627 | D10: 72812 | E10: 20231023pvv1935 | G10: PVV1935 | I10: 1935 | J10: техникум | K10: Пятиусово | L10: Пятиусово | M10: Ну вот и поменьше народу теперь | N10: из | O10: местных. | P10: местных | Q10: 0 | R10: 0 | S10: 0 | T10: 0 | U10: 0 | V10: 0 | W10: 0 | X10: 0 | Y10: 0 | Z10: 0 | AA10: 1 | AB10: 0 | AC10: 0 | AD10: a | AE10: n | AF10: y
A11: корпус говора деревни Пятиусово | B11: 1417 | C11: 1998214 | D11: 2006294 | E11: 20231023pvv1935 | G11: PVV1935 | I11: 1935 | J11: техникум | K11: Пятиусово | L11: Пятиусово | M11: Сразу поехал в Торопу – там весной уже привозят, это, | N11: из | O11: питомника саженцы – купил пять яблонь. | P11: питомник | Q11: 0 | R11: 0 | S11: 0 | T11: 0 | U11: 1 | V11: 0 | W11: 0 | X11: 0 | Y11: 0 | Z11: 0 | AA11: 0 | AB11: 0 | AC11: 0 | AD11: s | AE11: v | AF11: y
A12: корпус говора деревни Пятиусово | B12: 1647 | C12: 939680 | D12: 942160 | E12: 20240728zes1942 | N12: Из | O12: шести сыновей все были на войне (войны). | P12: сыновья | Q12: 0 | R12: 0 | S12: 0 | T12: 0 | U12: 0 | V12: 0 | W12: 0 | X12: 0 | Y12: 0 | Z12: 0 | AA12: 1 | AB12: 0 | AC12: 0 | AD12: o | AE12: n | AF12: y
A13: корпус говора деревни Пятиусово | B13: 1673 | C13: 1071510 | D13: 1077040 | E13: 20240728zes1942 | M13: Ну у нас все | N13: из | O13: родителей... Мы из детей все живы были. | P13: родители | Q13: 0 | R13: 0 | S13: 0 | T13: 0 | U13: 0 | V13: 0 | W13: 0 | X13: 0 | Y13: 0 | Z13: 0 | AA13: 1 | AB13: 0 | AC13: 0 | AD13: a | AE13: n | AF13: n
A14: корпус говора деревни Пятиусово | B14: 1673 | C14: 1071510 | D14: 1077040 | E14: 20240728zes1942 | M14: Ну у нас все из родителей... Мы | N14: из | O14: детей все живы были. | P14: дети | Q14: 0 | R14: 0 | S14: 0 | T14: 0 | U14: 0 | V14: 0 | W14: 0 | X14: 0 | Y14: 0 | Z14: 0 | AA14: 1 | AB14: 0 | AC14: 0 | AD14: a | AE14: n | AF14: n
A15: корпус говора деревни Пятиусово | B15: 1755 | C15: 1478630 | D15: 1484530 | E15: 20240728zes1942 | M15: Раньше специально носили, | N15: из | O15: Бенец были, был дед и баба. | P15: Бенец | Q15: 1 | R15: 0 | S15: 0 | T15: 0 | U15: 0 | V15: 0 | W15: 0 | X15: 0 | Y15: 0 | Z15: 0 | AA15: 0 | AB15: 0 | AC15: 0 | AD15: a | AE15: n | AF15: y
A16: корпус говора деревни Пятиусово | B16: 2004 | C16: 2564470 | D16: 2568880 | E16: 20240728zes1942 | M16: Ну кор = | N16: из | O16: кормовых для коров сажали брюкву. | P16: кормовые | Q16: 0 | R16: 0 | S16: 0 | T16: 0 | U16: 0 | V16: 0 | W16: 0 | X16: 0 | Y16: 0 | Z16: 0 | AA16: 1 | AB16: 0 | AC16: 0 | AD16: o | AE16: v | AF16: y
A17: корпус говора деревни Пятиусово | B17: 2373 | C17: 4066084 | D17: 4072863 | E17: 20240728zes1942 | M17: В деревне нету никого теперь и = | N17: из | O17: жителей оставши. Сколько жили там - вот одна я оставши теперь, нет никого. | P17: жителей | Q17: 0 | R17: 0 | S17: 0 | T17: 0 | U17: 0 | V17: 0 | W17: 0 | X17: 0 | Y17: 0 | Z17: 0 | AA17: 1 | AB17: 0 | AC17: 0 | AD17: o | AE17: n | AF17: y
A18: корпус говора деревни Пятиусово | B18: 2377 | C18: 4090069 | D18: 4093879 | E18: 20240728zes1942 | M18: И они вот переехали из = | N18: из | O18: этих домов в один из них. | P18: домов | Q18: 0 | R18: 0 | S18: 1 | T18: 0 | U18: 0 | V18: 0 | W18: 0 | X18: 0 | Y18: 0 | Z18: 0 | AA18: 0 | AB18: 0 | AC18: 0 | AD18: s | AE18: v | AF18: y
A19: корпус говора деревни Пятиусово | B19: 2496 | C19: 343620 | D19: 351360 | E19: 20240727zes1942 | M19: Да, теперь вы не узнаешь никого | N19: из | O19: ребят, все взрослые. Где узнаешь, а я уже старая и слепая, зрение плохое у () меня (мне), я плохо вижу. | P19: ребят | Q19: 0 | R19: 0 | S19: 0 | T19: 0 | U19: 0 | V19: 0 | W19: 0 | X19: 0 | Y19: 0 | Z19: 0 | AA19: 1 | AB19: 0 | AC19: 0 | AD19: o | AE19: v | AF19: y
A20: корпус говора деревни Пятиусово | B20: 2788 | C20: 1590666 | D20: 1597152 | E20: 20240727zes1942 | M20: Мои родители, у него (его) отца нету, мать была, мать, по - моему, ещё кто - то был | N20: из | O20: родственников. | P20: родственников | Q20: 0 | R20: 0 | S20: 0 | T20: 0 | U20: 0 | V20: 0 | W20: 0 | X20: 0 | Y20: 0 | Z20: 0 | AA20: 1 | AB20: 0 | AC20: 0 | AD20: a | AE20: n | AF20: y
A21: корпус говора деревни Пятиусово | B21: 2896 | C21: 2024652 | D21: 2033130 | E21: 20240727zes1942 | M21: А там (тама) на гормошке играли, была площадка сделаная из = это по = просто нацгак = как танцплощадка такая | N21: из | O21: дерева, из досок сложена. | P21: дерева | Q21: 0 | R21: 0 | S21: 0 | T21: 0 | U21: 0 | V21: 0 | W21: 0 | X21: 0 | Y21: 1 | Z21: 0 | AA21: 0 | AB21: 0 | AC21: 0 | AD21: a | AE21: n | AF21: y
A22: корпус говора деревни Пятиусово | B22: 2896 | C22: 2024652 | D22: 2033130 | E22: 20240727zes1942 | M22: А там (тама) на гормошке играли, была площадка сделаная из = это по = просто нацгак = как танцплощадка такая из дерева, | N22: из | O22: досок сложена. | P22: досок | Q22: 0 | R22: 0 | S22: 0 | T22: 0 | U22: 0 | V22: 0 | W22: 0 | X22: 0 | Y22: 1 | Z22: 0 | AA22: 0 | AB22: 0 | AC22: 0 | AD22: o | AE22: v | AF22: y
A23: корпус говора деревни Пятиусово | B23: 3133 | C23: 3278776 | D23: 3281644 | E23: 20240727zes1942 | N23: Из | O23: тринадцати деревень оставши вот только вот эта. | P23: деревень | Q23: 0 | R23: 1 | S23: 0 | T23: 0 | U23: 0 | V23: 0 | W23: 0 | X23: 0 | Y23: 0 | Z23: 0 | AA23: 0 | AB23: 0 | AC23: 0 | AD23: o | AE23: n | AF23: y
A24: корпус говора деревни Пятиусово | B24: 3299 | C24: 4384932 | D24: 4391489 | E24: 20240727zes1942 | M24: Де = де = держа = держали. Я держала, даже кто - то | N24: из | O24: ребят из ваших приходил, я давала, помню, сало. | P24: ребят | Q24: 0 | R24: 0 | S24: 0 | T24: 0 | U24: 0 | V24: 0 | W24: 0 | X24: 0 | Y24: 0 | Z24: 0 | AA24: 1 | AB24: 0 | AC24: 0 | AD24: o | AE24: n | AF24: y
A25: корпус говора деревни Пятиусово | B25: 3869 | C25: 1466970 | D25: 1474310 | E25: 20240802zes1942 | M25: Их в совхозе много было, их не оставши почти никого и = и = | N25: из | O25: моих ровесников. У Рыжиковой Любы не были вы? | P25: ровесники | Q25: 0 | R25: 0 | S25: 0 | T25: 0 | U25: 0 | V25: 0 | W25: 0 | X25: 0 | Y25: 0 | Z25: 0 | AA25: 1 | AB25: 0 | AC25: 0 | AD25: a | AE25: n | AF25: y
A26: корпус говора деревни Пятиусово | B26: 3885 | C26: 1498310 | D26: 1501090 | E26: 20240802zes1942 | M26: Да, она родом | N26: из | O26: Каськова, да. | P26: Каськово | Q26: 1 | R26: 0 | S26: 0 | T26: 0 | U26: 0 | V26: 0 | W26: 0 | X26: 0 | Y26: 0 | Z26: 0 | AA26: 0 | AB26: 0 | AC26: 1 | AD26: a | AE26: n | AF26: y
A27: корпус говора деревни Пятиусово | B27: 732 | C27: 2758059 | D27: 2762881 | E27: 20240729evm1937 | G27: EVM1937 | I27: 1937 | J27: техникум | K27: Коковино | L27: Пятиусово | M27: Варежки все вязали шерстяные, из овец = | N27: из | O27: овечей шерсти. | P27: шерсть | Q27: 0 | R27: 0 | S27: 0 | T27: 0 | U27: 0 | V27: 0 | W27: 0 | X27: 0 | Y27: 1 | Z27: 0 | AA27: 0 | AB27: 0 | AC27: 0 | AD27: o | AE27: v | AF27: y
A28: корпус говора деревни Пятиусово | B28: 3869 | C28: 1466970 | D28: 1474310 | E28: 20240802zes1942 | M28: Их в совхозе много было, их не оставши почти никого и = и = | N28: из | O28: моих ровесников. У Рыжиковой Любы не были вы? | P28: ровесник | Q28: 0 | R28: 0 | S28: 0 | T28: 0 | U28: 0 | V28: 0 | W28: 0 | X28: 0 | Y28: 0 | Z28: 0 | AA28: 1 | AB28: 0 | AC28: 0 | AD28: a | AE28: n | AF28: y
A29: корпус говора деревни Пятиусово | B29: 3976 | C29: 1802650 | D29: 1808240 | E29: 20240802zes1942 | M29: Фляги эти в = вых = выносили на улицу. На улице было щит сделано | N29: из | O29: досок. | P29: досок | Q29: 0 | R29: 0 | S29: 0 | T29: 0 | U29: 0 | V29: 0 | W29: 0 | X29: 0 | Y29: 1 | Z29: 0 | AA29: 0 | AB29: 0 | AC29: 0 | AD29: o | AE29: v | AF29: y
A30: корпус говора деревни Пятиусово | B30: 3978 | C30: 1808950 | D30: 1814380 | E30: 20240802zes1942 | M30: И там была сделана яма | N30: из | O30: цемента. Пускали туда воду и ставили фляги туда. | P30: цемента | Q30: 0 | R30: 0 | S30: 0 | T30: 0 | U30: 0 | V30: 0 | W30: 0 | X30: 0 | Y30: 1 | Z30: 0 | AA30: 0 | AB30: 0 | AC30: 0 | AD30: o | AE30: v | AF30: y
A31: корпус говора деревни Пятиусово | B31: 4351 | C31: 3002840 | D31: 3009670 | E31: 20240802zes1942 | M31: В подполье сразу сыпали, а сейчас в подполье не сыпят (сыплют). Сейчас сыпят (сыплют) в сарай или у кого оббито, такие, сделано | N31: из | O31: досок... | P31: досок | Q31: 0 | R31: 0 | S31: 0 | T31: 0 | U31: 0 | V31: 0 | W31: 0 | X31: 0 | Y31: 1 | Z31: 0 | AA31: 0 | AB31: 0 | AC31: 0 | AD31: o | AE31: v | AF31: y
A32: корпус говора деревни Пятиусово | B32: 4371 | C32: 3068330 | D32: 3075760 | E32: 20240802zes1942 | M32: Сделанный | N32: из | O32: фундамента. Там (тама) не у (в) одних у них, на их (ихней) улице, наверное во = кто желал, все делали тогда, она сказала. | P32: фундамента | Q32: 0 | R32: 0 | S32: 0 | T32: 0 | U32: 0 | V32: 0 | W32: 0 | X32: 0 | Y32: 1 | Z32: 0 | AA32: 0 | AB32: 0 | AC32: 0 | AD32: o | AE32: v | AF32: y
A33: корпус говора деревни Пятиусово | B33: 4412 | C33: 3191170 | D33: 3198320 | E33: 20240802zes1942 | M33: И была сделана лежанка | N33: из | O33: дереве = из = из досок, из досок. | P33: дерева | Q33: 0 | R33: 0 | S33: 0 | T33: 0 | U33: 0 | V33: 0 | W33: 0 | X33: 0 | Y33: 1 | Z33: 0 | AA33: 0 | AB33: 0 | AC33: 0 | AD33: o | AE33: v | AF33: y
A34: корпус говора деревни Пятиусово | B34: 4412 | C34: 3191170 | D34: 3198320 | E34: 20240802zes1942 | M34: И была сделана лежанка из дереве = из = | N34: из | O34: досок, из досок. | P34: досок | Q34: 0 | R34: 0 | S34: 0 | T34: 0 | U34: 0 | V34: 0 | W34: 0 | X34: 0 | Y34: 1 | Z34: 0 | AA34: 0 | AB34: 0 | AC34: 0 | AD34: o | AE34: v | AF34: y
A35: корпус говора деревни Пятиусово | B35: 4412 | C35: 3191170 | D35: 3198320 | E35: 20240802zes1942 | M35: И была сделана лежанка из дереве = из = из досок, | N35: из | O35: досок. | P35: досок | Q35: 0 | R35: 0 | S35: 0 | T35: 0 | U35: 0 | V35: 0 | W35: 0 | X35: 0 | Y35: 1 | Z35: 0 | AA35: 0 | AB35: 0 | AC35: 0 | AD35: o | AE35: v | AF35: y
A36: корпус говора деревни Пятиусово | B36: 4784 | C36: 4274800 | D36: 4285570 | E36: 20240802zes1942 | M36: Его делают. Вот руками (рукам) держатся вот так. Ну теперь (теперя) я видела у Бориса Николаевича какой - то вообще на палках, которым там. У нас специально делают | N36: из | O36: брёда такую. | P36: брёда | Q36: 0 | R36: 0 | S36: 0 | T36: 0 | U36: 0 | V36: 0 | W36: 0 | X36: 0 | Y36: 1 | Z36: 0 | AA36: 0 | AB36: 0 | AC36: 0 | AD36: o | AE36: v | AF36: y
A37: корпус говора деревни Пятиусово | B37: 5180 | C37: 739190 | D37: 764381 | E37: 20240804zes1942 | M37: Ну покупаю эти корма, покупаю корма в магазине, ну и иногда если только свежого супа, если | N37: из | O37: куры, курятину и так, если чуть - чуть, а так не особо. Ну рыбу любит, бывало, мойва была. Сейчас мойвы нет, бывала мойва. То супа сварю из мойвы, чтобы покушать, то так, а так он сейчас, он молоко любит, молоко когда дают.. | P37: куры | Q37: 0 | R37: 0 | S37: 0 | T37: 0 | U37: 0 | V37: 0 | W37: 0 | X37: 0 | Y37: 1 | Z37: 0 | AA37: 0 | AB37: 0 | AC37: 0 | AD37: a | AE37: n | AF37: y
A38: корпус говора деревни Пятиусово | B38: 5180 | C38: 739190 | D38: 764381 | E38: 20240804zes1942 | M38: Ну покупаю эти корма, покупаю корма в магазине, ну и иногда если только свежого супа, если из куры, курятину и так, если чуть - чуть, а так не особо. Ну рыбу любит, бывало, мойва была. Сейчас мойвы нет, бывала мойва. То супа сварю | N38: из | O38: мойвы, чтобы покушать, то так, а так он сейчас, он молоко любит, молоко когда дают.. | P38: мойвы | Q38: 0 | R38: 0 | S38: 0 | T38: 0 | U38: 0 | V38: 0 | W38: 0 | X38: 0 | Y38: 1 | Z38: 0 | AA38: 0 | AB38: 0 | AC38: 0 | AD38: o | AE38: v | AF38: y
A39: корпус говора деревни Пятиусово | B39: 5189 | C39: 915667 | D39: 951571 | E39: 20240804zes1942 | N39: Из | O39: молока, которое в хозяйствве, во все времена и даже в пятьдесят восьмом году у нас уже был сепаратор, ещё не замужем была, а нас только приняли в совхоз, совхоз был на деньгах, поэтому нас соединили. И перегоняли, перегон, хочешь на творог перегон, хочешь, держали поросёнка, поросё = поросятам давали и белили, а ну, а молоко, делали масло, творог, ой ели ну такое, своё, ну. | P39: молока | Q39: 0 | R39: 0 | S39: 0 | T39: 0 | U39: 0 | V39: 0 | W39: 0 | X39: 0 | Y39: 1 | Z39: 0 | AA39: 0 | AB39: 0 | AC39: 1 | AD39: o | AE39: v | AF39: y
A40: корпус говора деревни Пятиусово | B40: 5202 | C40: 1384500 | D40: 1402500 | E40: 20240804zes1942 | M40: В Каськове, да, рожала девушка одна молодая, невестка принимала моя роды там, она как бы вызвала скорую там (тама) они, ещё какая - то медичка была, вдвоём принимали роды | N40: из | O40: дома. | P40: дома | Q40: 0 | R40: 0 | S40: 1 | T40: 0 | U40: 0 | V40: 0 | W40: 0 | X40: 0 | Y40: 0 | Z40: 0 | AA40: 0 | AB40: 0 | AC40: 0 | AD40: s | AE40: v | AF40: y
A41: корпус говора деревни Пятиусово | B41: 5254 | C41: 1988900 | D41: 2130100 | E41: 20240804zes1942 | M41: В де = в детстве какие вам истории надо, я вам расскажу историю, могу рассказать одну, у нас же дружили, ну я думаю, может кто и рассказывал вам | N41: из | O41: деревни. Дружил парень с девушкой, уже хотели жениться, ну это это на самом деле такое есть, было, и они, значит, на =, свадьба назначена, точно не могу, по - моему, как на Троицу. Они за два дня Троицы пошли в этом, говорит (говорить) мужик её (еёный), теперь ну парень, назовём его. Говорит (говорить), пойдём искупаемся, пошли к речке купаться напротив кладбища где - то туда, он как разделся, как нырнул, так и не вынырнул, вот такой случай это вот был. И вот она осталась на берегу, и потом она вышла за другого замуж, она сама позже умерла (умёрши), ну а дети в Ленинграде, одна дочка вроде умерла (умерши) уже. Так вот такой сулчай был, но из ма = из материного рассказа, ну она рассказывала, что - то, она сказала < нрзб > значит (значить), правильнро как сказать, сейчас скажу. Ну как бы в жизни всяко бывает, и не складывается жизнь. Ну приходит дочка к матери и говорит, говорит (говорить), я не хочу жить, я ну что там (тама) не ладится жизнь то ли < нрзб >, но я не спрашивала, точно не могу сказать, она ей говорит, знаешь, детка, дочь, говорит, вот, если тебе накакают на голову, ты скинь с головы, извините за выражение, и опять живи. Ну что, то это жизнь, говорит, не что - нибудь, вот такое. Ну и потом рассказывала, мужик, значит, ходит к женщине ходит (ходить) и ходит (ходить), она, значит, как лето приходит, так ему надо спать на сеновале, но эта жёнка, она понимает что - то, что да нет, она раз послушала, два послушала людей, говорит, надо мне пос = самой покараулить. Она пошла караулить, караулит (караулить), значит, они полезли на черда = на = на = на хлё = на сарай. Она помокнула в жижу, раньше жижесборники такие за хлёвом были, метлу, и туда на это самое, на хлёв их метлой этой с жижей. Говорит (говорить), вот такой случай был. Но драться никто не дрался, она сказала, не дрались, а вот такой случай был. | P41: деревни | Q41: 0 | R41: 1 | S41: 0 | T41: 0 | U41: 0 | V41: 0 | W41: 0 | X41: 0 | Y41: 0 | Z41: 0 | AA41: 0 | AB41: 0 | AC41: 0 | AD41: o | AE41: v | AF41: y
A42: корпус говора деревни Пятиусово | B42: 5254 | C42: 1988900 | D42: 2130100 | E42: 20240804zes1942 | M42: В де = в детстве какие вам истории надо, я вам расскажу историю, могу рассказать одну, у нас же дружили, ну я думаю, может кто и рассказывал вам из деревни. Дружил парень с девушкой, уже хотели жениться, ну это это на самом деле такое есть, было, и они, значит, на =, свадьба назначена, точно не могу, по - моему, как на Троицу. Они за два дня Троицы пошли в этом, говорит (говорить) мужик её (еёный), теперь ну парень, назовём его. Говорит (говорить), пойдём искупаемся, пошли к речке купаться напротив кладбища где - то туда, он как разделся, как нырнул, так и не вынырнул, вот такой случай это вот был. И вот она осталась на берегу, и потом она вышла за другого замуж, она сама позже умерла (умёрши), ну а дети в Ленинграде, одна дочка вроде умерла (умерши) уже. Так вот такой сулчай был, но из ма = | N42: из | O42: материного рассказа, ну она рассказывала, что - то, она сказала < нрзб > значит (значить), правильнро как сказать, сейчас скажу. Ну как бы в жизни всяко бывает, и не складывается жизнь. Ну приходит дочка к матери и говорит, говорит (говорить), я не хочу жить, я ну что там (тама) не ладится жизнь то ли < нрзб >, но я не спрашивала, точно не могу сказать, она ей говорит, знаешь, детка, дочь, говорит, вот, если тебе накакают на голову, ты скинь с головы, извините за выражение, и опять живи. Ну что, то это жизнь, говорит, не что - нибудь, вот такое. Ну и потом рассказывала, мужик, значит, ходит к женщине ходит (ходить) и ходит (ходить), она, значит, как лето приходит, так ему надо спать на сеновале, но эта жёнка, она понимает что - то, что да нет, она раз послушала, два послушала людей, говорит, надо мне пос = самой покараулить. Она пошла караулить, караулит (караулить), значит, они полезли на черда = на = на = на хлё = на сарай. Она помокнула в жижу, раньше жижесборники такие за хлёвом были, метлу, и туда на это самое, на хлёв их метлой этой с жижей. Говорит (говорить), вот такой случай был. Но драться никто не дрался, она сказала, не дрались, а вот такой случай был. | P42: рассказ | Q42: 0 | R42: 0 | S42: 0 | T42: 0 | U42: 0 | V42: 0 | W42: 1 | X42: 0 | Y42: 0 | Z42: 0 | AA42: 0 | AB42: 0 | AC42: 0 | AD42: a | AE42: n | AF42: y
A43: корпус говора деревни Пятиусово | B43: 5255 | C43: 2130900 | D43: 2138000 | E43: 20240804zes1942 | M43: Вот, это | N43: из | O43: жизни, это всё жизненное, это не придуманное, придумать я ничего не могу. | P43: жизни | Q43: 0 | R43: 0 | S43: 0 | T43: 0 | U43: 0 | V43: 0 | W43: 1 | X43: 0 | Y43: 0 | Z43: 0 | AA43: 0 | AB43: 0 | AC43: 0 | AD43: a | AE43: n | AF43: y
A44: корпус говора деревни Пятиусово | B44: 5283 | C44: 3389940 | D44: 3405940 | E44: 20240804zes1942 | M44: Это я имею в виду, если для колхозного с = скота для совхозного, а для личного, а для личного у них сараи есть во многих < нрзб > сделано | N44: из | O44: досок, а может (може) сарай пустой сарай сыплют картошку. | P44: доски | Q44: 0 | R44: 0 | S44: 0 | T44: 0 | U44: 0 | V44: 0 | W44: 0 | X44: 0 | Y44: 1 | Z44: 0 | AA44: 0 | AB44: 0 | AC44: 0 | AD44: o | AE44: v | AF44: y
A45: корпус говора деревни Пятиусово | B45: 5294 | C45: 3765200 | D45: 3767240 | E45: 20240804zes1942 | M45: В хлев? | N45: Из | O45: хлева? В поле? | P45: хлев | Q45: 0 | R45: 0 | S45: 0 | T45: 0 | U45: 0 | V45: 1 | W45: 0 | X45: 0 | Y45: 0 | Z45: 0 | AA45: 0 | AB45: 0 | AC45: 0 | AD45: s | AE45: v | AF45: y
A46: корпус говора деревни Пятиусово | B46: 5295 | C46: 3767240 | D46: 3812000 | E46: 20240804zes1942 | N46: Из | O46: хлева в поле в основном шестого мая, в Егорий. Старались в это день, но если сена не =, если травы нет в поле, один год не было травы в поле до, сейчас скажу, до девятнадцатого мая травы не было, был холод как - то один год, и вот Пятиусовские гоняли в Троицкое, есть такое туда. Первое июня, потому что не было травы, а личный скот пускали числа, наверное, пятнадцатого мая, это в зависимости, как есть трава, ну а сейчас его в деревне три коровы, они у всех на привязи, на цепях, там надо в поле и поесть (поись) и < нрзб >. | P46: хлев | Q46: 0 | R46: 0 | S46: 0 | T46: 0 | U46: 0 | V46: 1 | W46: 0 | X46: 0 | Y46: 0 | Z46: 0 | AA46: 0 | AB46: 0 | AC46: 0 | AD46: s | AE46: v | AF46: y
A47: корпус говора деревни Пятиусово | B47: 5307 | C47: 4186800 | D47: 4277560 | E47: 20240804zes1942 | M47: Я = яйца, да, и яйца сдавали в совхоз, ну сами са = сами эти (эты) не, я думаю, ни разу, я не помню, чтобы мы сдавали мясо. А вот когда куры были, сдавали, кур было много, и каждый день возили в в ящиках (ящикам) больших (большим) по шестьсот штук в ящике были. Быва = бывало, это яйца, наверное, летом, летом, наверное, по шесть ящиков и даже в день были, ну много было кур и много яи = яиц было, и были большие расклёвы, а = курица курицу может расклевать, потому что не хватает, мяса давали, мяса, если какая - то, там < нрзб > что - то, то резали, там привозили к нам, и мы варили в котлах, в котлах вместе с картошкой с < нрзб > и давали, тогда вроде поменьше клю =, ну если расклёв был, то нас мы заста нас заставляли сразу её резать, ну в кипяток сажали, вычищали, и только голову себе оставляли, ноги потро = потроха, это себе оставляли, а если, а это сдавали. Вот это самое < нрзб > каждый день суп готовили | N47: из | O47: потрохов, вкусно были, боже мой, хорошо, сейчас в магазине возьму курицу, я даже есть её не могу, она чем - то пахнет, не понимаю я, обвариваю, обвариваю кипятком, и как - то не з = не понимаю, что такое раньше, то ли корм может (може) не такой, что, не знаю. | P47: потрохи | Q47: 0 | R47: 0 | S47: 0 | T47: 0 | U47: 0 | V47: 0 | W47: 0 | X47: 0 | Y47: 1 | Z47: 0 | AA47: 0 | AB47: 0 | AC47: 0 | AD47: o | AE47: v | AF47: y
A48: корпус говора деревни Пятиусово | B48: 5310 | C48: 4338600 | D48: 4340440 | E48: 20240804zes1942 | N48: Из | O48: курицы? Когда, сейчас? | P48: курица | Q48: 0 | R48: 0 | S48: 0 | T48: 0 | U48: 0 | V48: 0 | W48: 0 | X48: 0 | Y48: 1 | Z48: 0 | AA48: 0 | AB48: 0 | AC48: 0 | AD48: o | AE48: v | AF48: y
A49: корпус говора деревни Пятиусово | B49: 5386 | C49: 632250 | D49: 702900 | E49: 20231023vpm1934_1 | G49: VPM1934 | I49: 1934 | J49: техникум | K49: Ануфриево | L49: Пятиусово | M49: Да, Фо = в этом Фофаново ходила в школу. В школу я ходила в Фофаново. А теперь после, как я уехала, даже хочется сходить туда, посмотреть, что там творится. Говорят, всё москвичи построились, застроились теперь. Не была ни разу. Прое = Когда бываешь, церковь проедешь мимо на автобусе. Автобус же ходил | N49: из | O49: Западной до Пятиусова. Проедешь, и всё. Так что в тех краях я даже и не была что - то. Конечно, говорят, там школы уже нет с... Это в каком году, Господи?! Уже столько лет прошло. Там и постройки большие, говорят, у москвичей (w москвичах) построены. Везде москвичи застроились, что они (оны)? А теперь дома не хотят покупать. Что там они покупают? Ну теперь хотят покупать со всеми удобствами, чтоб было всё, удобства... Не хотят же теперь молодые так, чтобы... И вода, чтобы проно = выте = пропротекала и вытекала, а у нас этого нет. Вот. | P49: Западная | Q49: 1 | R49: 0 | S49: 0 | T49: 0 | U49: 0 | V49: 0 | W49: 0 | X49: 0 | Y49: 0 | Z49: 0 | AA49: 0 | AB49: 0 | AC49: 0 | AD49: s | AE49: v | AF49: y
A50: Корпус говора деревень Шетнево и Макеево | B50: 6 | C50: 30040 | D50: 35970 | E50: 20230427apb1940_A | G50: apb1940 | H50: f | I50: 1940 | J50: среднее | K50: Паново | L50: Макеево | M50: На одиннадцатый день меня (мине) выписали | N50: из | O50: больницы во Ржеве отсюда. | P50: больница | Q50: 0 | R50: 0 | S50: 0 | T50: 0 | U50: 1 | V50: 0 | W50: 0 | X50: 0 | Y50: 0 | Z50: 0 | AA50: 0 | AB50: 0 | AC50: 0 | AD50: s | AE50: v | AF50: y
A51: Корпус говора деревень Шетнево и Макеево | B51: 171 | C51: 1369620 | D51: 1373280 | E51: 20230427apb1940_A | G51: apb1940 | H51: f | I51: 1940 | J51: среднее | K51: Паново | L51: Макеево | M51: Ходили | N51: из | O51: Панова сюда в клуб гулять. | P51: Панов | Q51: 1 | R51: 0 | S51: 0 | T51: 0 | U51: 0 | V51: 0 | W51: 0 | X51: 0 | Y51: 0 | Z51: 0 | AA51: 0 | AB51: 0 | AC51: 0 | AD51: s | AE51: v | AF51: y
A52: Корпус говора деревень Шетнево и Макеево | B52: 222 | C52: 1773560 | D52: 1782720 | E52: 20230427apb1940_A | G52: apb1940 | H52: f | I52: 1940 | J52: среднее | K52: Паново | L52: Макеево | M52: Есть этого с Москвы, где | N52: из | O52: Подмосковья приеходчи вот туда у нас и держит. | P52: Подмосквье | Q52: 1 | R52: 0 | S52: 0 | T52: 0 | U52: 0 | V52: 0 | W52: 0 | X52: 0 | Y52: 0 | Z52: 0 | AA52: 0 | AB52: 0 | AC52: 0 | AD52: s | AE52: v | AF52: y
A53: Корпус говора деревень Шетнево и Макеево | B53: 275 | C53: 2260100 | D53: 2268940 | E53: 20230427apb1940_A | G53: apb1940 | H53: f | I53: 1940 | J53: среднее | K53: Паново | L53: Макеево | M53: Это вот годов пять не стало. А так... А то бывало | N53: из | O53: Бенец, с Торопы даже приезжали сюда в клуб. | P53: Бенцы | Q53: 1 | R53: 0 | S53: 0 | T53: 0 | U53: 0 | V53: 0 | W53: 0 | X53: 0 | Y53: 0 | Z53: 0 | AA53: 0 | AB53: 0 | AC53: 0 | AD53: s | AE53: v | AF53: y
A54: Корпус говора деревень Шетнево и Макеево | B54: 755 | C54: 899432 | D54: 904103 | E54: 20210716mga1932 | G54: mga1932 | H54: f | I54: 1932 | J54: начальное | K54: Пожоги | L54: Шетнево | M54: Выгнали | N54: из | O54: дому... вот жили у соседа. | P54: дом | Q54: 0 | R54: 0 | S54: 1 | T54: 0 | U54: 0 | V54: 0 | W54: 0 | X54: 0 | Y54: 0 | Z54: 0 | AA54: 0 | AB54: 0 | AC54: 0 | AD54: s | AE54: v | AF54: y
A55: Корпус говора деревень Шетнево и Макеево | B55: 1666 | C55: 1273980 | D55: 1274760 | E55: 20220715gip1953 | G55: gip1953 | H55: f | I55: 1953 | J55: среднее | K55: Макеево | L55: Макеево | N55: Из | O55: Питера... | P55: Питер | Q55: 1 | R55: 0 | S55: 0 | T55: 0 | U55: 0 | V55: 0 | W55: 0 | X55: 0 | Y55: 0 | Z55: 0 | AA55: 0 | AB55: 0 | AC55: 1 | AD55: a | AE55: n | AF55: y
A56: Корпус говора деревень Шетнево и Макеево | B56: 1933 | C56: 587925 | D56: 589295 | E56: 20210713mga1932 | M56: С избы выгнали, | N56: из | O56: дому. | P56: дом | Q56: 0 | R56: 0 | S56: 1 | T56: 0 | U56: 0 | V56: 0 | W56: 0 | X56: 0 | Y56: 0 | Z56: 0 | AA56: 0 | AB56: 0 | AC56: 0 | AD56: s | AE56: v | AF56: y
A57: Корпус говора деревень Шетнево и Макеево | B57: 2167 | C57: 1416741 | D57: 1417963 | E57: 20210713mga1932 | N57: Из | O57: досок сбитый. | P57: доски | Q57: 0 | R57: 0 | S57: 0 | T57: 0 | U57: 0 | V57: 0 | W57: 0 | X57: 0 | Y57: 1 | Z57: 0 | AA57: 0 | AB57: 0 | AC57: 0 | AD57: a | AE57: n | AF57: y
A58: Корпус говора деревень Шетнево и Макеево | B58: 2643 | C58: 3033047 | D58: 3034147 | E58: 20210713mga1932 | N58: Из | O58: садика вон. | P58: садик | Q58: 0 | R58: 0 | S58: 0 | T58: 0 | U58: 1 | V58: 0 | W58: 0 | X58: 0 | Y58: 0 | Z58: 0 | AA58: 0 | AB58: 0 | AC58: 0 | AD58: s | AE58: v | AF58: y
A59: Корпус говора деревень Шетнево и Макеево | B59: 2930 | C59: 3027400 | D59: 3037066 | E59: 20230427apb1940_B | G59: apb1940 | H59: f | I59: 1940 | J59: среднее | K59: Паново | L59: Макеево | M59: Теперь | N59: из | O59: магазина берём одно, другое, третье. Что у меня, клубника посажена, так я всё этой правнучке. | P59: магазин | Q59: 0 | R59: 0 | S59: 0 | T59: 0 | U59: 1 | V59: 0 | W59: 0 | X59: 0 | Y59: 0 | Z59: 0 | AA59: 0 | AB59: 0 | AC59: 0 | AD59: s | AE59: v | AF59: y
A60: Корпус говора деревень Шетнево и Макеево | B60: 3720 | C60: 6752607 | D60: 6753272 | E60: 20230427gip1953 | G60: gip1953 | H60: f | I60: 1953 | J60: среднее | K60: Макеево | L60: Макеево | N60: Из | O60: Стевии ? | P60: стевия | Q60: 0 | R60: 0 | S60: 0 | T60: 0 | U60: 0 | V60: 0 | W60: 0 | X60: 0 | Y60: 1 | Z60: 0 | AA60: 0 | AB60: 0 | AC60: 0 | AD60: a | AE60: n | AF60: y
A61: Корпус говора деревень Шетнево и Макеево | B61: 4048 | C61: 1368360 | D61: 1369157 | E61: 20220710zns1939_A | G61: zns1939 | H61: f | I61: 1939 | J61: среднее | K61: Макеево | L61: Макеево | N61: Из | O61: Москвы? | P61: Москва | Q61: 1 | R61: 0 | S61: 0 | T61: 0 | U61: 0 | V61: 0 | W61: 0 | X61: 0 | Y61: 0 | Z61: 0 | AA61: 0 | AB61: 0 | AC61: 1 | AD61: a | AE61: n | AF61: y
A62: Корпус говора деревень Шетнево и Макеево | B62: 4125 | C62: 3821240 | D62: 3823272 | E62: 20210706lnt1950 | G62: lnt1950 | H62: f | I62: 1950 | J62: среднее | K62: Шетнево | L62: Шетнево | M62: А | N62: из | O62: фруктов ничего, ни с каких не делала. | P62: фрукты | Q62: 0 | R62: 0 | S62: 0 | T62: 0 | U62: 0 | V62: 0 | W62: 0 | X62: 0 | Y62: 1 | Z62: 0 | AA62: 0 | AB62: 0 | AC62: 1 | AD62: o | AE62: v | AF62: y
A63: Корпус говора деревень Шетнево и Макеево | B63: 5089 | C63: 831978 | D63: 835034 | E63: 20210712ivs1954 | G63: ivs1954 | H63: m | I63: 1954 | J63: среднее | K63: Макеево | L63: Макеево | M63: молодой, Пашка такой, | N63: из | O63: Москвы тоже. | P63: Москва | Q63: 1 | R63: 0 | S63: 0 | T63: 0 | U63: 0 | V63: 0 | W63: 0 | X63: 0 | Y63: 0 | Z63: 0 | AA63: 0 | AB63: 0 | AC63: 0 | AD63: a | AE63: n | AF63: y
A64: Корпус говора деревень Шетнево и Макеево | B64: 5464 | C64: 49645 | D64: 54600 | E64: 20220710mga1932 | G64: mga1932 | H64: f | I64: 1932 | J64: начальное | K64: Пожоги | L64: Шетнево | M64: Сколько? Три дня, как приехала ( | N64: из | O64: ) больницы, лежала в больнице. | P64: больница | Q64: 0 | R64: 0 | S64: 0 | T64: 0 | U64: 1 | V64: 0 | W64: 0 | X64: 0 | Y64: 0 | Z64: 0 | AA64: 0 | AB64: 0 | AC64: 0 | AD64: s | AE64: v | AF64: y
A65: Корпус говора деревень Шетнево и Макеево | B65: 6442 | C65: 2591456 | D65: 2594956 | E65: 20220711zns1939 | G65: zns1939 | H65: f | I65: 1939 | J65: среднее | K65: Макеево | L65: Макеево | M65: Да и = | N65: из | O65: шерсти, исподки эти. | P65: шерсть | Q65: 0 | R65: 0 | S65: 0 | T65: 0 | U65: 0 | V65: 0 | W65: 0 | X65: 0 | Y65: 1 | Z65: 0 | AA65: 0 | AB65: 0 | AC65: 1 | AD65: a | AE65: n | AF65: y
A66: Корпус говора деревень Шетнево и Макеево | B66: 6651 | C66: 327790 | D66: 332530 | E66: 20210707gip1953 | G66: gip1953 | H66: f | I66: 1953 | J66: среднее | K66: Макеево | L66: Макеево | M66: А вы все сами с города все или с деревни? | N66: Из | O66: города? Ага | P66: город | Q66: 0 | R66: 1 | S66: 0 | T66: 0 | U66: 0 | V66: 0 | W66: 0 | X66: 0 | Y66: 0 | Z66: 0 | AA66: 0 | AB66: 0 | AC66: 0 | AD66: a | AE66: n | AF66: y
A67: Корпус говора деревень Шетнево и Макеево | B67: 6741 | C67: 1336449 | D67: 1339315 | E67: 20210707gip1953 | G67: gip1953 | H67: f | I67: 1953 | J67: среднее | K67: Макеево | L67: Макеево | M67: Не, они что - то | N67: из | O67: дерева там делали. | P67: дерево | Q67: 0 | R67: 0 | S67: 0 | T67: 0 | U67: 0 | V67: 0 | W67: 0 | X67: 0 | Y67: 1 | Z67: 0 | AA67: 0 | AB67: 0 | AC67: 0 | AD67: o | AE67: v | AF67: y
A68: Корпус говора деревень Шетнево и Макеево | B68: 7103 | C68: 3754835 | D68: 3759305 | E68: 20210707gip1953 | G68: gip1953 | H68: f | I68: 1953 | J68: среднее | K68: Макеево | L68: Макеево | M68: Не, | N68: из | O68: льна мы не делали, увозили куда - то его на машина увозила, наверное, специально на эти... | P68: лен | Q68: 0 | R68: 0 | S68: 0 | T68: 0 | U68: 0 | V68: 0 | W68: 0 | X68: 0 | Y68: 1 | Z68: 0 | AA68: 0 | AB68: 0 | AC68: 1 | AD68: o | AE68: v | AF68: y
A69: Корпус говора деревень Шетнево и Макеево | B69: 7453 | C69: 5467692 | D69: 5472259 | E69: 20210707gip1953 | G69: gip1953 | H69: f | I69: 1953 | J69: среднее | K69: Макеево | L69: Макеево | M69: Крятки такие, два колеса | N69: из | O69: дерева, вырезанные с этого... | P69: дерево | Q69: 0 | R69: 0 | S69: 0 | T69: 0 | U69: 0 | V69: 0 | W69: 0 | X69: 0 | Y69: 1 | Z69: 0 | AA69: 0 | AB69: 0 | AC69: 0 | AD69: a | AE69: n | AF69: y
A70: Корпус говора деревень Шетнево и Макеево | B70: 7943 | C70: 7712901 | D70: 7718402 | E70: 20210707gip1953 | G70: gip1953 | H70: f | I70: 1953 | J70: среднее | K70: Макеево | L70: Макеево | N70: Из | O70: Щелкино, сынок. С той деревни. Она в магазин ходила, потом уже в последнее время она старая, не стала ходить. | P70: Щелкино | Q70: 1 | R70: 0 | S70: 0 | T70: 0 | U70: 0 | V70: 0 | W70: 0 | X70: 0 | Y70: 0 | Z70: 0 | AA70: 0 | AB70: 0 | AC70: 1 | AD70: a | AE70: n | AF70: y
A71: Корпус говора деревень Шетнево и Макеево | B71: 7660 | C71: 6334623 | D71: 6343773 | E71: 20210707gip1953 | G71: gip1953 | H71: f | I71: 1953 | J71: среднее | K71: Макеево | L71: Макеево | M71: Я | N71: изо | O71: старых простыней рвала, где ты наберёшь пелёнок столько, рвала старые простыни, разрывала, делала пелёнки. | P71: простыни | Q71: 0 | R71: 0 | S71: 0 | T71: 0 | U71: 0 | V71: 0 | W71: 0 | X71: 0 | Y71: 1 | Z71: 0 | AA71: 0 | AB71: 0 | AC71: 0 | AD71: o | AE71: v | AF71: n
A72: Корпус Опочецких говоров | B72: 591 | C72: 613422 | D72: 620730 | E72: 20180620_nae1958 | G72: нае1958 | I72: 1958 | J72: среднее специальное | M72: Нет, он со = да, вообще они родом | N72: из | O72: Питера, потом сюда вся семья переехала, а ездят они... | P72: Питер | Q72: 1 | R72: 0 | S72: 0 | T72: 0 | U72: 0 | V72: 0 | W72: 0 | X72: 0 | Y72: 0 | Z72: 0 | AA72: 0 | AB72: 0 | AC72: 0 | AD72: a | AE72: n | AF72: y
A73: Корпус Опочецких говоров | B73: 656 | C73: 979914 | D73: 987276 | E73: 20180620_nae1958 | G73: нае1958 | I73: 1958 | J73: среднее специальное | M73: Это, солнце... Вот это у него сделано | N73: из | O73: щуки из большой, двенадцать с половиной килограмм или двенадцать шестьсот... | P73: щука | Q73: 0 | R73: 0 | S73: 0 | T73: 0 | U73: 0 | V73: 0 | W73: 0 | X73: 0 | Y73: 1 | Z73: 0 | AA73: 0 | AB73: 0 | AC73: 0 | AD73: o | AE73: v | AF73: y
A74: Корпус Опочецких говоров | B74: 717 | C74: 1307897 | D74: 1313463 | E74: 20180620_nae1958 | G74: нае1958 | I74: 1958 | J74: среднее специальное | M74: Ну всех пугал, змея | N74: из | O74: кармана вытащит, ну, что ж... | P74: карман | Q74: 0 | R74: 0 | S74: 0 | T74: 0 | U74: 0 | V74: 0 | W74: 0 | X74: 1 | Y74: 0 | Z74: 0 | AA74: 0 | AB74: 0 | AC74: 0 | AD74: s | AE74: v | AF74: y
A75: Корпус Опочецких говоров | B75: 779 | C75: 1628120 | D75: 1629866 | E75: 20180620_nae1958 | G75: нае1958 | I75: 1958 | J75: среднее специальное | M75: Это я | N75: из | O75: архива знаю. | P75: архив | Q75: 0 | R75: 0 | S75: 0 | T75: 0 | U75: 1 | V75: 0 | W75: 0 | X75: 0 | Y75: 0 | Z75: 0 | AA75: 0 | AB75: 0 | AC75: 0 | AD75: s | AE75: v | AF75: y
A76: Корпус Опочецких говоров | B76: 1427 | C76: 1117491 | D76: 1121492 | E76: 20180619_vav1949 | G76: вав1949 | I76: 1949 | J76: unknown | M76: Тоже | N76: из | O76: больницы ему... Ну что - то не, не знаю, что он не едет. | P76: больница | Q76: 0 | R76: 0 | S76: 0 | T76: 0 | U76: 1 | V76: 0 | W76: 0 | X76: 0 | Y76: 0 | Z76: 0 | AA76: 0 | AB76: 0 | AC76: 0 | AD76: s | AE76: v | AF76: y
A77: Корпус Опочецких говоров | B77: 1941 | C77: 742600 | D77: 747430 | E77: 20180621_avv1933 | M77: как новенькая, ну уже в Питера, | N77: из | O77: Питера приезжаю, вот, мама сюда переехала, поэтому я тоже не всех знаю как - то. | P77: Питер | Q77: 1 | R77: 0 | S77: 0 | T77: 0 | U77: 0 | V77: 0 | W77: 0 | X77: 0 | Y77: 0 | Z77: 0 | AA77: 0 | AB77: 0 | AC77: 0 | AD77: s | AE77: v | AF77: y
A78: Корпус Опочецких говоров | B78: 3255 | C78: 55623 | D78: 63946 | E78: 20190701_saf1973 | G78: саф1973 | I78: 1973 | J78: высшее | M78: Ну а что раньше? Раньше интересно... Раньше было так, что выпихивали | N78: из | O78: колхоза – паспортов - то не было. | P78: колхоз | Q78: 0 | R78: 0 | S78: 0 | T78: 0 | U78: 1 | V78: 0 | W78: 0 | X78: 0 | Y78: 0 | Z78: 0 | AA78: 0 | AB78: 0 | AC78: 0 | AD78: s | AE78: v | AF78: y
A79: Корпус Опочецких говоров | B79: 3555 | C79: 2070788 | D79: 2081110 | E79: 20190701_saf1973 | G79: саф1973 | I79: 1973 | J79: высшее | M79: А памятник в виде надгробной плиты. Он - то | N79: из | O79: гранита сделан, [говорю, говорят], все говорят, сравнивают с надгробной плитой, ну, я говорю: " Ну что, Днепропетровске и в этом похоронили ". | P79: гранит | Q79: 0 | R79: 0 | S79: 0 | T79: 0 | U79: 0 | V79: 0 | W79: 0 | X79: 0 | Y79: 1 | Z79: 0 | AA79: 0 | AB79: 0 | AC79: 0 | AD79: o | AE79: v | AF79: y
A80: Корпус Опочецких говоров | B80: 3671 | C80: 2899698 | D80: 2905242 | E80: 20190701_saf1973 | G80: саф1973 | I80: 1973 | J80: высшее | M80: О! [Из] она | N80: из | O80: Анчинок, вот, вспомнил, Анчинки. Анчинкский мост, анчинкский мост. | P80: Анчинки | Q80: 1 | R80: 0 | S80: 0 | T80: 0 | U80: 0 | V80: 0 | W80: 0 | X80: 0 | Y80: 0 | Z80: 0 | AA80: 0 | AB80: 0 | AC80: 0 | AD80: a | AE80: n | AF80: y
A81: Корпус Опочецких говоров | B81: 4679 | C81: 2122999 | D81: 2126307 | E81: 20180618_zii1932_a | G81: зии1932 | I81: 1932 | J81: начальное | M81: я было даже | N81: из | O81: мебели что - то куплю, | P81: мебель | Q81: 0 | R81: 0 | S81: 0 | T81: 0 | U81: 0 | V81: 0 | W81: 0 | X81: 0 | Y81: 0 | Z81: 0 | AA81: 1 | AB81: 0 | AC81: 0 | AD81: o | AE81: v | AF81: y
A82: Корпус Опочецких говоров | B82: 5229 | C82: 4646183 | D82: 4653647 | E82: 20180618_zii1932_a | G82: зии1932 | I82: 1932 | J82: начальное | M82: Даже многие | N82: из | O82: Ленинграда привозят сюда родств = (родственников), которые отсюда, | P82: Ленинград | Q82: 1 | R82: 0 | S82: 0 | T82: 0 | U82: 0 | V82: 0 | W82: 0 | X82: 0 | Y82: 0 | Z82: 0 | AA82: 0 | AB82: 0 | AC82: 0 | AD82: s | AE82: v | AF82: y
A83: Корпус Опочецких говоров | B83: 6507 | C83: 210398 | D83: 217718 | E83: 20180621a_nae1958 | G83: нае1958 | I83: 1958 | J83: среднее специальное | M83: Три деревни вот списали тогда вот я | N83: из | O83: архива это знаю, и всё, больше не списывались. | P83: архив | Q83: 0 | R83: 0 | S83: 0 | T83: 0 | U83: 1 | V83: 0 | W83: 0 | X83: 0 | Y83: 0 | Z83: 0 | AA83: 0 | AB83: 0 | AC83: 0 | AD83: s | AE83: v | AF83: y

Sheet удалено_с
A1: корпус | B1: utterance_id | C1: From | D1: To | E1: File | F1: Id | G1: String id | H1: Gender | I1: Year of birth | J1: Education | K1: Place of birth | L1: Place of living | M1: Left Context | N1: DMatch | O1: Right Context | P1: причина удаления | R1: =IFERROR(__xludf.DUMMYFUNCTION("QUERY(P2:P10000, ""SELECT P, COUNT(P) WHERE P IS NOT NULL AND P != '' GROUP BY P ORDER BY COUNT(P) DESC LABEL COUNT(P) 'Количество'"")"),"") | S1: =IFERROR(__xludf.DUMMYFUNCTION("""COMPUTED_VALUE"""),"Количество") -> Количество
A2: Корпус говора деревни Пятиусово | B2: 55 | C2: 1116181 | D2: 1121630 | E2: 20231028zes1942 | M2: Ну, а мы на улице со ( | N2: с | O2: ) своим дедом, хозяином дрова резали, вот так... | P2: другой падеж | R2: =IFERROR(__xludf.DUMMYFUNCTION("""COMPUTED_VALUE"""),"другой падеж") -> другой падеж | S2: =IFERROR(__xludf.DUMMYFUNCTION("""COMPUTED_VALUE"""),829.0) -> 829
A3: Корпус говора деревни Пятиусово | B3: 62 | C3: 1147370 | D3: 1151750 | E3: 20231028zes1942 | N3: С | O3: неё (ней) не снять это, рукавицы... Варежки раньше были шерстяные. | P3: отсутствует существительное в предложной группе | R3: =IFERROR(__xludf.DUMMYFUNCTION("""COMPUTED_VALUE"""),"нет вариативности") -> нет вариативности | S3: =IFERROR(__xludf.DUMMYFUNCTION("""COMPUTED_VALUE"""),254.0) -> 254
A4: Корпус говора деревни Пятиусово | B4: 77 | C4: 1212489 | D4: 1215709 | E4: 20231028zes1942 | M4: После какой | N4: с | O4: #NAME? | P4: неполные данные | R4: =IFERROR(__xludf.DUMMYFUNCTION("""COMPUTED_VALUE"""),"неполные данные") -> неполные данные | S4: =IFERROR(__xludf.DUMMYFUNCTION("""COMPUTED_VALUE"""),148.0) -> 148
A5: Корпус говора деревни Пятиусово | B5: 91 | C5: 1283884 | D5: 1289084 | E5: 20231028zes1942 | M5: Мы не пускали как - бы... Ночлег, это | N5: с | O5: собой никто не носит, это сейчас у вас машины... | P5: другой падеж | R5: =IFERROR(__xludf.DUMMYFUNCTION("""COMPUTED_VALUE"""),"отсутствует существительное в предложной группе") -> отсутствует существительное в предложной группе | S5: =IFERROR(__xludf.DUMMYFUNCTION("""COMPUTED_VALUE"""),91.0) -> 91
A6: Корпус говора деревни Пятиусово | B6: 113 | C6: 1395162 | D6: 1400395 | E6: 20231028zes1942 | M6: Её называть... Она сама... Я разговаривала | N6: с | O6: ней, тоже, так, когда в автобусе еду... | P6: другой падеж | R6: =IFERROR(__xludf.DUMMYFUNCTION("""COMPUTED_VALUE"""),"временное значение") -> временное значение | S6: =IFERROR(__xludf.DUMMYFUNCTION("""COMPUTED_VALUE"""),33.0) -> 33
A7: Корпус говора деревни Пятиусово | B7: 114 | C7: 1400856 | D7: 1407011 | E7: 20231028zes1942 | M7: Когда в автобусе еду, то люблю поговорить, встретиться | N7: с | O7: кем - то и поговорить... Ну, и спросила у неё (ней)... | P7: другой падеж | R7: =IFERROR(__xludf.DUMMYFUNCTION("""COMPUTED_VALUE"""),"самоповтор") -> самоповтор | S7: =IFERROR(__xludf.DUMMYFUNCTION("""COMPUTED_VALUE"""),26.0) -> 26
A8: Корпус говора деревни Пятиусово | B8: 155 | C8: 1607049 | D8: 1618583 | E8: 20231028zes1942 | M8: На правительство обижаться нельзя, живёт хорошо во главе | N8: с | O8: президентом, живут все хорошо. В нашей деревне, я не знаю, как в других, в нашей все живут хорошо. Кто работал, пенсию заработал, он пенсию... На пенсию живёт. | P8: другой падеж | R8: =IFERROR(__xludf.DUMMYFUNCTION("""COMPUTED_VALUE"""),"идиома/фразеологизм") -> идиома/фразеологизм | S8: =IFERROR(__xludf.DUMMYFUNCTION("""COMPUTED_VALUE"""),22.0) -> 22
A9: Корпус говора деревни Пятиусово | B9: 193 | C9: 1877298 | D9: 1881498 | E9: 20231028zes1942 | M9: Ну и, так вкусны (укусны) были | N9: с | O9: молоком, но держали корову. | P9: другой падеж | R9: =IFERROR(__xludf.DUMMYFUNCTION("""COMPUTED_VALUE"""),"мера/сопоставление") -> мера/сопоставление | S9: =IFERROR(__xludf.DUMMYFUNCTION("""COMPUTED_VALUE"""),6.0) -> 6
A10: Корпус говора деревни Пятиусово | B10: 216 | C10: 2007902 | D10: 2014883 | E10: 20231028zes1942 | M10: Всё было, и хлеб было тогда, и все... Стали кровати все | N10: с | O10: клопами выносить вон, раньше клопов было много. | P10: другой падеж | R10: =IFERROR(__xludf.DUMMYFUNCTION("""COMPUTED_VALUE"""),"мера") -> мера | S10: =IFERROR(__xludf.DUMMYFUNCTION("""COMPUTED_VALUE"""),5.0) -> 5
A11: Корпус говора деревни Пятиусово | B11: 218 | C11: 2020393 | D11: 2027793 | E11: 20231028zes1942 | M11: В субботу до обеда, полный день воскресенье, ну, жизнь совсем уже другоая стала конечно, | N11: с | O11: пятьдесят восьмого года она... | R11: =IFERROR(__xludf.DUMMYFUNCTION("""COMPUTED_VALUE"""),"составной предлог") -> составной предлог | S11: =IFERROR(__xludf.DUMMYFUNCTION("""COMPUTED_VALUE"""),5.0) -> 5
A12: Корпус говора деревни Пятиусово | B12: 219 | C12: 2028059 | D12: 2034483 | E12: 20231028zes1942 | N12: С | O12: двадцатого мая... Взяли в это = эту самую... В совхоз соединили. Но совхоз жил хорошо. | P12: нет вариативности | R12: =IFERROR(__xludf.DUMMYFUNCTION("""COMPUTED_VALUE"""),"мера/приблизительно") -> мера/приблизительно | S12: =IFERROR(__xludf.DUMMYFUNCTION("""COMPUTED_VALUE"""),2.0) -> 2
A13: Корпус говора деревни Пятиусово | B13: 221 | C13: 2041377 | D13: 2047516 | E13: 20231028zes1942 | M13: А я старая, никуда, без зуб теперь уже, | N13: с | O13: пятьдесят лет зубов нет, стерялись все... Растерялись все зубы. | P13: нет вариативности
A14: Корпус говора деревни Пятиусово | B14: 240 | C14: 2195910 | D14: 2202667 | E14: 20231028zes1942 | M14: Это вот... А они как - то были приехадчи, а я на улице была, по - моему... Не, в (у) доме была. А Артём был приехадчи | N14: с | O14: ним. | P14: другой падеж
A15: Корпус говора деревни Пятиусово | B15: 261 | C15: 2274410 | D15: 2278840 | E15: 20231028zes1942 | N15: С | O15: друзьями (друзьям) где - то были на охоте, вот он тоже, тоже на охоте, да, вот этот сын. | P15: другой падеж
A16: Корпус говора деревни Пятиусово | B16: 263 | C16: 2282310 | D16: 2285860 | E16: 20231028zes1942 | N16: С | O16: доски почёта... На доске почёта. Ну, у меня, бывало, свои < нрзб > были. | P16: нет вариативности
A17: Корпус говора деревни Пятиусово | B17: 287 | C17: 338700 | D17: 342270 | E17: 20240729evm1937 | G17: EVM1937 | I17: 1937 | J17: техникум | K17: Коковино | L17: Пятиусово | M17: А вы, наверное, там я плохо | N17: с | O17: вами разговаривал, наверное. | P17: другой падеж
A18: Корпус говора деревни Пятиусово | B18: 290 | C18: 349530 | D18: 349973 | E18: 20240729evm1937 | G18: EVM1937 | I18: 1937 | J18: техникум | K18: Коковино | L18: Пятиусово | M18: Я | N18: с | O18: =... -> #ERROR! | P18: неполные данные
A19: Корпус говора деревни Пятиусово | B19: 299 | C19: 388786 | D19: 392800 | E19: 20240729evm1937 | G19: EVM1937 | I19: 1937 | J19: техникум | K19: Коковино | L19: Пятиусово | N19: С | O19: () шестьдесят второго года. | P19: нет вариативности
A20: Корпус говора деревни Пятиусово | B20: 307 | C20: 427810 | D20: 428990 | E20: 20240729evm1937 | G20: EVM1937 | I20: 1937 | J20: техникум | K20: Коковино | L20: Пятиусово | N20: С | O20: шестьдесят второго года. | P20: нет вариативности
A21: Корпус говора деревни Пятиусово | B21: 324 | C21: 498040 | D21: 502290 | E21: 20240729evm1937 | G21: EVM1937 | I21: 1937 | J21: техникум | K21: Коковино | L21: Пятиусово | M21: Это так у меня лейтенант называл, когда я | N21: с | O21: ним еду в машине. | P21: другой падеж
A22: Корпус говора деревни Пятиусово | B22: 375 | C22: 797525 | D22: 802525 | E22: 20240729evm1937 | G22: EVM1937 | I22: 1937 | J22: техникум | K22: Коковино | L22: Пятиусово | M22: Был на Бакуриани - - три тысячи | N22: с | O22: половиной, тысячи над уровнем моря. | P22: другой падеж
A23: Корпус говора деревни Пятиусово | B23: 376 | C23: 802725 | D23: 813830 | E23: 20240729evm1937 | G23: EVM1937 | I23: 1937 | J23: техникум | K23: Коковино | L23: Пятиусово | M23: Я спускал оттуда станцию, с Бакуриани, | N23: с | O23: тягачом АТС, а сзади приёмо - передающая кабина, 20 тонн. | P23: другой падеж
A24: Корпус говора деревни Пятиусово | B24: 381 | C24: 844250 | D24: 850425 | E24: 20240729evm1937 | G24: EVM1937 | I24: 1937 | J24: техникум | K24: Коковино | L24: Пятиусово | M24: А как посмотришь они | N24: с | O24: такой вроде, панамы поднимаются, волосы кверху, не захочешь смотреть | P24: другой падеж
A25: Корпус говора деревни Пятиусово | B25: 390 | C25: 902287 | D25: 913162 | E25: 20240729evm1937 | G25: EVM1937 | I25: 1937 | J25: техникум | K25: Коковино | L25: Пятиусово | M25: На третьи сутки товарищ у нас один говорит: " Мы пойдем, Муравьёв, | N25: с | O25: тобой на метеостаницию. " | P25: другой падеж
A26: Корпус говора деревни Пятиусово | B26: 399 | C26: 953412 | D26: 955500 | E26: 20240729evm1937 | G26: EVM1937 | I26: 1937 | J26: техникум | K26: Коковино | L26: Пятиусово | M26: И там мы | N26: с | O26: ним (им) пробыли до отбоя. | P26: другой падеж
A27: Корпус говора деревни Пятиусово | B27: 437 | C27: 1155510 | D27: 1165021 | E27: 20240729evm1937 | G27: EVM1937 | I27: 1937 | J27: техникум | K27: Коковино | L27: Пятиусово | M27: И здесь я создал семью, познакомился | N27: с | O27: дамой или с девочкой назовем, дамой (дамом) тогда не называли. | P27: другой падеж
A28: Корпус говора деревни Пятиусово | B28: 437 | C28: 1155510 | D28: 1165021 | E28: 20240729evm1937 | G28: EVM1937 | I28: 1937 | J28: техникум | K28: Коковино | L28: Пятиусово | M28: И здесь я создал семью, познакомился с дамой или | N28: с | O28: девочкой назовем, дамой (дамом) тогда не называли. | P28: другой падеж
A29: Корпус говора деревни Пятиусово | B29: 465 | C29: 1319573 | D29: 1328935 | E29: 20240729evm1937 | G29: EVM1937 | I29: 1937 | J29: техникум | K29: Коковино | L29: Пятиусово | M29: Я говорю: " Ну как я буду работать? Я среднетехнического образования, агрономы | N29: с | O29: высшим, приду, зоотехники с высшим, мне как - то неудобно. " | P29: другой падеж
A30: Корпус говора деревни Пятиусово | B30: 465 | C30: 1319573 | D30: 1328935 | E30: 20240729evm1937 | G30: EVM1937 | I30: 1937 | J30: техникум | K30: Коковино | L30: Пятиусово | M30: Я говорю: " Ну как я буду работать? Я среднетехнического образования, агрономы с высшим, приду, зоотехники | N30: с | O30: высшим, мне как - то неудобно. " | P30: другой падеж
A31: Корпус говора деревни Пятиусово | B31: 480 | C31: 1425550 | D31: 1440820 | E31: 20240729evm1937 | G31: EVM1937 | I31: 1937 | J31: техникум | K31: Коковино | L31: Пятиусово | M31: Она тяжело болела, не так что тяжело, но болела, пользовалась ингалятором, у неё плохо | N31: с | O31: сердцем было, с дыханием, ушла из жизни. | P31: другой падеж
A32: Корпус говора деревни Пятиусово | B32: 480 | C32: 1425550 | D32: 1440820 | E32: 20240729evm1937 | G32: EVM1937 | I32: 1937 | J32: техникум | K32: Коковино | L32: Пятиусово | M32: Она тяжело болела, не так что тяжело, но болела, пользовалась ингалятором, у неё плохо с сердцем было, | N32: с | O32: дыханием, ушла из жизни. | P32: другой падеж
... A66: Корпус говора деревни Пятиусово | B66: 1113 | C66: 1209120 | D66: 1217220 | E66: 20231026lng1954 | G66: LNG1954 | I66: 1954 | J66: среднее (10 классов) | K66: Пятиусово | L66: Пятиусово | M66: А краски не было, а ехать в городо, туда в (у) Западную, | N66: с | O66: большим количеством - объёмом краски, а у меня (мне) было вот такой... | P66: другой падеж
A67: Корпус говора деревни Пятиусово | B67: 1122 | C67: 1274400 | D67: 1293080 | E67: 20231026lng1954 | G67: LNG1954 | I67: 1954 | J67: среднее (10 классов) | K67: Пятиусово | L67: Пятиусово | M67: Ну в современном (совремённом) Красногорске. | N67: С | O67: =по - моему, сорок три или сорок восемь квадратов там, раздельно что. Вот дочка на выданье будет, куда, чего, что. А потом раз у человека на генетическом уровне забит это, они же вот эта ностальгия, деревенские они всё равно, к земле их тянет, вот. -> #ERROR! | P67: неполные данные
A68: Корпус говора деревни Пятиусово | B68: 1136 | C68: 1387020 | D68: 1396786 | E68: 20231026lng1954 | G68: LNG1954 | I68: 1954 | J68: среднее (10 классов) | K68: Пятиусово | L68: Пятиусово | M68: Без.. Короче, я на Новый год бросил работать, а | N68: с | O68: двадцатого февраля девяностого года я там служил. И вот начальником караула, в охране был. | P68: нет вариативности
A69: Корпус говора деревни Пятиусово | B69: 1139 | C69: 1404866 | D69: 1412720 | E69: 20231026lng1954 | G69: LNG1954 | I69: 1954 | J69: среднее (10 классов) | K69: Пятиусово | L69: Пятиусово | M69: Это | N69: с | O69: тридцать третьего года организовано. Это ну Кубышка, это государственное, допустим, на случай войны что - то, такое это вот это. | P69: нет вариативности
A70: Корпус говора деревни Пятиусово | B70: 1142 | C70: 1422079 | D70: 1428866 | E70: 20231026lng1954 | G70: LNG1954 | I70: 1954 | J70: среднее (10 классов) | K70: Пятиусово | L70: Пятиусово | M70: Сейчас я уже не знаю. Информация я обладаю ту, которую в мою бытость это было - - я | N70: с | O70: четырнадцатого года на пенсии. | P70: нет вариативности
A71: Корпус говора деревни Пятиусово | B71: 1146 | C71: 1446293 | D71: 1456266 | E71: 20231026lng1954 | G71: LNG1954 | I71: 1954 | J71: среднее (10 классов) | K71: Пятиусово | L71: Пятиусово | M71: А начинал вот тут в совхозе, вот. До судимости я трактористом работал на тракторе. Ну там я мало, это | N71: с | O71: семьдесят первого года с октября по апрель. | P71: нет вариативности
A72: Корпус говора деревни Пятиусово | B72: 1146 | C72: 1446293 | D72: 1456266 | E72: 20231026lng1954 | G72: LNG1954 | I72: 1954 | J72: среднее (10 классов) | K72: Пятиусово | L72: Пятиусово | M72: А начинал вот тут в совхозе, вот. До судимости я трактористом работал на тракторе. Ну там я мало, это с семьдесят первого года | N72: с | O72: октября по апрель. | P72: нет вариативности
A73: Корпус говора деревни Пятиусово | B73: 1160 | C73: 1540706 | D73: 1546773 | E73: 20231026lng1954 | G73: LNG1954 | I73: 1954 | J73: среднее (10 классов) | K73: Пятиусово | L73: Пятиусово | M73: Вот пять месяцев я закончил школу и поступил | N73: с | O73: нового года сюда, шофёром работал. | P73: нет вариативности
A74: Корпус говора деревни Пятиусово | B74: 1161 | C74: 1547213 | D74: 1552599 | E74: 20231026lng1954 | G74: LNG1954 | I74: 1954 | J74: среднее (10 классов) | K74: Пятиусово | L74: Пятиусово | M74: Вот. Восемь (восем) лет, не семь (сем) - - | N74: с | O74: восьмидесятого по восемьдесят седьмой - - я шофёром отработал. | P74: нет вариативности
A75: Корпус говора деревни Пятиусово | B75: 1167 | C75: 1583373 | D75: 1589360 | E75: 20231026lng1954 | G75: LNG1954 | I75: 1954 | J75: среднее (10 классов) | K75: Пятиусово | L75: Пятиусово | M75: Потому | N75: с | O75: ней встал - - я говорю, вот Галя как. Я тогда согласен был и на = на переезд в Западную уехать. | P75: другой падеж
A76: Корпус говора деревни Пятиусово | B76: 1178 | C76: 1643719 | D76: 1657852 | E76: 20231026lng1954 | G76: LNG1954 | I76: 1954 | J76: среднее (10 классов) | K76: Пятиусово | L76: Пятиусово | M76: Я потом договорился уже, | N76: с | O76: осени (осеню) отсюда делал товаро - трасп = накладные там, я... Мы как бы десять рейсов, это... на пятнадцать километров... | P76: нет вариативности
A77: Корпус говора деревни Пятиусово | B77: 1185 | C77: 1700652 | D77: 1706386 | E77: 20231026lng1954 | G77: LNG1954 | I77: 1954 | J77: среднее (10 классов) | K77: Пятиусово | L77: Пятиусово | M77: А я же говорил, что со мной | N77: с | O77: позиции силы нельзя разговаривать, со мной можно договориться, вот. | P77: идиома/фразеологизм
A78: Корпус говора деревни Пятиусово | B78: 1220 | C78: 246957 | D78: 266057 | E78: 20231023pvv1935 | G78: PVV1935 | I78: 1935 | J78: техникум | K78: Пятиусово | L78: Пятиусово | M78: И стричься, и бриться, и пуговицы чистить... А что, едем на канун Нового Года, так... Четыре солдата было с нашей части... Вместе, и мы вдвоем, | N78: с | O78: =один с Юровских друг, призвались вместе, это нашего района. -> #ERROR! | P78: другой падеж
A79: Корпус говора деревни Пятиусово | B79: 1221 | C79: 266884 | D79: 280900 | E79: 20231023pvv1935 | G79: PVV1935 | I79: 1935 | J79: техникум | K79: Пятиусово | L79: Пятиусово | M79: И вместе мы | N79: с | O79: ним ехали, и вместе учились, он во взвод связи попал, а я в (у) роту, с какой роты ну, поступал в эту... Школа была при части. На младших командиров. | P79: другой падеж
A80: Корпус говора деревни Пятиусово | B80: 1245 | C80: 465822 | D80: 471922 | E80: 20231023pvv1935 | G80: PVV1935 | I80: 1935 | J80: техникум | K80: Пятиусово | L80: Пятиусово | M80: И как... | N80: С | O80: =... Как, известянк, или как, на, говорит, даже за границу на экспорт идёт. -> #ERROR! | P80: неполные данные
A81: Корпус говора деревни Пятиусово | B81: 1247 | C81: 487125 | D81: 509450 | E81: 20231023pvv1935 | G81: PVV1935 | I81: 1935 | J81: техникум | K81: Пятиусово | L81: Пятиусово | M81: А там | N81: с | O81: каждого (кажного) корабля по тридцать человек офицерам квартиры строили. Ну, прямо... Так они там микрорайон такой сделали, там... Как поглядишь, где только они (оны) размещаются. Как ночью, как тревога... Посмотришь, все бухты... Пустые... Куда они (оны) такой... | P81: отсутствует существительное в предложной группе
A82: Корпус говора деревни Пятиусово | B82: 1257 | C82: 580686 | D82: 591450 | E82: 20231023pvv1935 | G82: PVV1935 | I82: 1935 | J82: техникум | K82: Пятиусово | L82: Пятиусово | M82: Ну там как... Так у нас он говорит, расценок нет, кому как, наряды посмотрит | N82: с | O82: потолка, и что поставит... | P82: нет вариативности
A83: Корпус говора деревни Пятиусово | B83: 1262 | C83: 608497 | D83: 610847 | E83: 20231023pvv1935 | G83: PVV1935 | I83: 1935 | J83: техникум | K83: Пятиусово | L83: Пятиусово | N83: С | O83: этого, получить паспорт. | P83: отсутствует существительное в предложной группе
A84: Корпус говора деревни Пятиусово | B84: 1275 | C84: 768069 | D84: 783625 | E84: 20231023pvv1935 | G84: PVV1935 | I84: 1935 | J84: техникум | K84: Пятиусово | L84: Пятиусово | M84: А называ = говорит, сделаем тебе перерыв, он подходит к брату. Скажи ты этому, пусть он... Один не проголосовал, а их четыре члена правления было. И всё. Поговори | N84: с | O84: ним (jим), чтобы он бы... | P84: другой падеж
A85: Корпус говора деревни Пятиусово | B85: 1285 | C85: 860074 | D85: 884875 | E85: 20231023pvv1935 | G85: PVV1935 | I85: 1935 | J85: техникум | K85: Пятиусово | L85: Пятиусово | M85: Там как уборка, так... Ну да рубильник сделан был от генератора же, движок был | N85: с | O85: генератором. Можно свой, и оттуда, когда сверху раз, вниз. Лампочка висит, когда оттуда есть. Я ходил ходил, думаю, а что делать. К мастеру подхожу, говорю, давай буду котёл топить, раз свет есть. Деньги же платят (плотят), надо что - то делать | P85: другой падеж
A86: Корпус говора деревни Пятиусово | B86: 1294 | C86: 944426 | D86: 966100 | E86: 20231023pvv1935 | G86: PVV1935 | I86: 1935 | J86: техникум | K86: Пятиусово | L86: Пятиусово | M86: Ну я на этих (этых), на сельский. Отработал четырнадцать лет на запарке кормов. У нас... Пять | N86: с | O86: половиной тысяч свиней было в совхозе. Был совхоз, а теперь... Ни =... Теперь сократили совхозы, колхозы, и промышленности сорок прцентов, или не больше. | P86: другой падеж
A87: Корпус говора деревни Пятиусово | B87: 1299 | C87: 1016364 | D87: 1034250 | E87: 20231023pvv1935 | G87: PVV1935 | I87: 1935 | J87: техникум | K87: Пятиусово | L87: Пятиусово | M87: Так они у нас уже, наверное, двенадцать лет. И до какие сейчас... Бывало сзади телега ещё прицеплена, а теперь сплошной. В два ряда по длине (длины). Это двенадцать метров, говорили по шесть, а шесть | N87: с | O87: половиной был раньше стандарт лес. | P87: другой падеж
A88: Корпус говора деревни Пятиусово | B88: 1304 | C88: 1087248 | D88: 1102450 | E88: 20231023pvv1935 | G88: PVV1935 | I88: 1935 | J88: техникум | K88: Пятиусово | L88: Пятиусово | M88: Часть, наверное, было отсюда. | N88: С | O88: =как у... Не на фронте, на Ржев. А часть на Витебск, Ильинская зона, там бои сильные тоже были. А призывали двадцать четвёртый год... -> #ERROR! | P88: неполные данные
A89: Корпус говора деревни Пятиусово | B89: 1319 | C89: 1222021 | D89: 1236196 | E89: 20231023pvv1935 | G89: PVV1935 | I89: 1935 | J89: техникум | K89: Пятиусово | L89: Пятиусово | M89: Да как бывало приходят (приходют)... Резаное мясо вот, допустим, как раньше, деревянные кадушки, или бочки были. | N89: С | O89: крышкой. Мясо зарезано, они (оны) поглядят, сами ничего не сыпят (сыплют), и не трогали резан. | P89: другой падеж
A90: Корпус говора деревни Пятиусово | B90: 1331 | C90: 1332318 | D90: 1359625 | E90: 20231023pvv1935 | G90: PVV1935 | I90: 1935 | J90: техникум | K90: Пятиусово | L90: Пятиусово | M90: А за семь километров ходили чистить вот как Шишово дорога есть, там. Кроты ещё проезжаешь, Дубняги есть. Наши стояли там, | N90: с | O90: одной (одный) стороны окопы. Офицеры жили, а с левой стороны мелкокалиберные склады были. Ну там, я представляю, что... Винтовочные, автоматные, потом какой - то динамит был. То вот я видел, а динамит не видел. | P90: нет вариативности
A91: Корпус говора деревни Пятиусово | B91: 1331 | C91: 1332318 | D91: 1359625 | E91: 20231023pvv1935 | G91: PVV1935 | I91: 1935 | J91: техникум | K91: Пятиусово | L91: Пятиусово | M91: А за семь километров ходили чистить вот как Шишово дорога есть, там. Кроты ещё проезжаешь, Дубняги есть. Наши стояли там, с одной (одный) стороны окопы. Офицеры жили, а | N91: с | O91: левой стороны мелкокалиберные склады были. Ну там, я представляю, что... Винтовочные, автоматные, потом какой - то динамит был. То вот я видел, а динамит не видел. | P91: нет вариативности
A92: Корпус говора деревни Пятиусово | B92: 1337 | C92: 1424224 | D92: 1437500 | E92: 20231023pvv1935 | G92: PVV1935 | I92: 1935 | J92: техникум | K92: Пятиусово | L92: Пятиусово | M92: Я | N92: с | O92: тридцать пятого года... Как мне сейчас восемьдесят восемь, уже восемьдесят девятый пошёл, с этого = с этого месяца. С июня... | P92: нет вариативности
A93: Корпус говора деревни Пятиусово | B93: 1337 | C93: 1424224 | D93: 1437500 | E93: 20231023pvv1935 | G93: PVV1935 | I93: 1935 | J93: техникум | K93: Пятиусово | L93: Пятиусово | M93: Я с тридцать пятого года... Как мне сейчас восемьдесят восемь, уже восемьдесят девятый пошёл, | N93: с | O93: этого = с этого месяца. С июня... | P93: отсутствует существительное в предложной группе
A94: Корпус говора деревни Пятиусово | B94: 1337 | C94: 1424224 | D94: 1437500 | E94: 20231023pvv1935 | G94: PVV1935 | I94: 1935 | J94: техникум | K94: Пятиусово | L94: Пятиусово | M94: Я с тридцать пятого года... Как мне сейчас восемьдесят восемь, уже восемьдесят девятый пошёл, с этого = | N94: с | O94: этого месяца. С июня... | P94: отсутствует существительное в предложной группе
A95: Корпус говора деревни Пятиусово | B95: 1337 | C95: 1424224 | D95: 1437500 | E95: 20231023pvv1935 | G95: PVV1935 | I95: 1935 | J95: техникум | K95: Пятиусово | L95: Пятиусово | M95: Я с тридцать пятого года... Как мне сейчас восемьдесят восемь, уже восемьдесят девятый пошёл, с этого = с этого месяца. | N95: С | O95: июня... | P95: отсутствует существительное в предложной группе
A96: Корпус говора деревни Пятиусово | B96: 1372 | C96: 1697835 | D96: 1705625 | E96: 20231023pvv1935 | G96: PVV1935 | I96: 1935 | J96: техникум | K96: Пятиусово | L96: Пятиусово | M96: А думаю, как бы это где... Вот, | N96: с | O96: =крыши нет, кирпичное здание стоит... Каменное. -> #ERROR! | P96: нет вариативности
A97: Корпус говора деревни Пятиусово | B97: 1374 | C97: 1713723 | D97: 1725050 | E97: 20231023pvv1935 | G97: PVV1935 | I97: 1935 | J97: техникум | K97: Пятиусово | L97: Пятиусово | M97: Надо... Самим (самым) кровати, им, а там и поставить некуда, и коридорчик общий, ну и... Печек нет, и... У () меня (мне) русская печка | N97: с | O97: плитой сейчас. | P97: другой падеж
A98: Корпус говора деревни Пятиусово | B98: 1403 | C98: 1912557 | D98: 1917980 | E98: 20231023pvv1935 | G98: PVV1935 | I98: 1935 | J98: техникум | K98: Пятиусово | L98: Пятиусово | M98: На дизельной возил, сколько она, четыре | N98: с | O98: половиной тонны берёт. | P98: другой падеж
A99: Корпус говора деревни Пятиусово | B99: 1434 | C99: 2101081 | D99: 2111260 | E99: 20231023pvv1935 | G99: PVV1935 | I99: 1935 | J99: техникум | K99: Пятиусово | L99: Пятиусово | M99: И последний сорок шесть. Там каждый (кажный) батон по - своему, потому что они (оны) | N99: с | O99: маком, потом... Как это, забыл, как называе = (называется). | P99: другой падеж
A100: Корпус говора деревни Пятиусово | B100: 1450 | C100: 2181249 | D100: 2189120 | E100: 20231023pvv1935 | G100: PVV1935 | I100: 1935 | J100: техникум | K100: Пятиусово | L100: Пятиусово | M100: Вот, та (тая), говорит, надоело, а это | N100: с | O100: аппетитом, как в обед, ну, хорошо, да, там первое, второе дают, а утром... | P100: другой падеж
A101: Корпус говора деревни Пятиусово | B101: 1463 | C101: 57480 | D101: 65630 | E101: 20240728zes1942 | M101: Она живёт в своём доме. Это как и = | N101: с | O101: =из(с) Каськово идёте прямо, так сразу первый дом, а на правую руку голубой. -> #ERROR! | P101: неполные данные
A102: Корпус говора деревни Пятиусово | B102: 1466 | C102: 82260 | D102: 84430 | E102: 20240728zes1942 | M102: Ну вот, а и = она | N102: с | O102: сорокового года. | P102: нет вариативности
A103: Корпус говора деревни Пятиусово | B103: 1469 | C103: 91270 | D103: 95640 | E103: 20240728zes1942 | M103: Она тоже | N103: с | O103: сорок первого года. Она тоже много чего расскажет, так. | P103: нет вариативности
A104: Корпус говора деревни Пятиусово | B104: 1487 | C104: 163360 | D104: 170190 | E104: 20240728zes1942 | M104: Вы | N104: с | O104: =куда заходите, вы ничего, если случай что. Там, сейчас же телефоны эти, не броса = звонят. -> #ERROR! | P104: неполные данные
A105: Корпус говора деревни Пятиусово | B105: 1488 | C105: 170480 | D105: 175630 | E105: 20240728zes1942 | M105: Вы скажите: " Возможно, мы поможем вашей деревне ". Они вам | N105: с | O105: удовольствием сразу откроют. | P105: другой падеж
A106: Корпус говора деревни Пятиусово | B106: 1512 | C106: 289990 | D106: 293680 | E106: 20240728zes1942 | M106: И | N106: с | O106: тех пор я х = не хожу. Это прошло, наверное... А, телефон. | P106: нет вариативности
A107: Корпус говора деревни Пятиусово | B107: 1547 | C107: 453610 | D107: 456940 | E107: 20240728zes1942 | M107: Ходит. Невестка, по - моему, в прошлом году тоже не ходила. Что - то у неё (ней) | N107: с | O107: ногой. | P107: другой падеж
A108: Корпус говора деревни Пятиусово | B108: 1549 | C108: 465560 | D108: 470430 | E108: 20240728zes1942 | M108: Вот. И нынче Лена ходила, и | N108: с | O108: маленьким со своим ходили в лес - - Сашка водил. | P108: другой падеж
A109: Корпус говора деревни Пятиусово | B109: 1597 | C109: 677710 | D109: 682220 | E109: 20240728zes1942 | M109: Она учитель уже... Всю жизнь (жизь). Ей уже тоже пятьдесят, наверное, | N109: с | O109: лишним лет. | P109: другой падеж
A110: Корпус говора деревни Пятиусово | B110: 1614 | C110: 766980 | D110: 772770 | E110: 20240728zes1942 | N110: С | O110: первого... Четыре класса: первый, второй, третий, четвёртый. Четыре класса было. | P110: нет вариативности
A111: Корпус говора деревни Пятиусово | B111: 1620 | C111: 790810 | D111: 797980 | E111: 20240728zes1942 | M111: Был двухвартирный дом. В (у) этом доме вот | N111: с | O111: одной стороны жил директор школы - - Здоровенко Василий Александрович его звали. | P111: нет вариативности
A112: Корпус говора деревни Пятиусово | B112: 1635 | C112: 880370 | D112: 886300 | E112: 20240728zes1942 | M112: И я и шла... Да у нас все, по - моему, сейчас. В семь | N112: с | O112: половиной лет я и шла в школу. В семь с половиной лет я и шла. | P112: другой падеж
A113: Корпус говора деревни Пятиусово | B113: 1635 | C113: 880370 | D113: 886300 | E113: 20240728zes1942 | M113: И я и шла... Да у нас все, по - моему, сейчас. В семь с половиной лет я и шла в школу. В семь | N113: с | O113: половиной лет я и шла. | P113: другой падеж
A114: Корпус говора деревни Пятиусово | B114: 1648 | C114: 942980 | D114: 946930 | E114: 20240728zes1942 | M114: Но и двое не пришло, | N114: с | O114: войны двое. | P114: нет вариативности
A115: Корпус говора деревни Пятиусово | B115: 1651 | C115: 958970 | D115: 963280 | E115: 20240728zes1942 | M115: Сорок пятый, да? Значит, выходит, мне три | N115: с | O115: половиной года было, наверное. | P115: другой падеж
A116: Корпус говора деревни Пятиусово | B116: 1656 | C116: 975920 | D116: 979150 | E116: 20240728zes1942 | M116: Значит, три | N116: с | O116: половиной года мне было, я помню, приходил военный. | P116: другой падеж
A117: Корпус говора деревни Пятиусово | B117: 1657 | C117: 980150 | D117: 984430 | E117: 20240728zes1942 | M117: И а так как бабушка жила вместе | N117: с | O117: нами (нам). | P117: другой падеж
A118: Корпус говора деревни Пятиусово | B118: 1695 | C118: 1188405 | D118: 1190550 | E118: 20240728zes1942 | N118: С | O118: рождения, как его?... | P118: нет вариативности
A119: Корпус говора деревни Пятиусово | B119: 1696 | C119: 1192600 | D119: 1195360 | E119: 20240728zes1942 | M119: Гипноз. | N119: С | O119: рождения может какой гипноз и был. | P119: нет вариативности
A120: Корпус говора деревни Пятиусово | B120: 1704 | C120: 1227150 | D120: 1229320 | E120: 20240728zes1942 | M120: А этот, поговорит | N120: с | O120: ней, солдат. | P120: другой падеж
A121: Корпус говора деревни Пятиусово | B121: 1739 | C121: 1386000 | D121: 1394070 | E121: 20240728zes1942 | M121: А пчёлы... Он разводил... Сразу после, как | N121: с | O121: войны пришёл, стал разводить. Раньше были, сейчас домики. | P121: нет вариативности
A122: Корпус говора деревни Пятиусово | B122: 1745 | C122: 1420760 | D122: 1424300 | E122: 20240728zes1942 | M122: И спрячет от нас на чердак. А мы | N122: с | O122: сестрой ещё в школу ходили. | P122: другой падеж
A123: Корпус говора деревни Пятиусово | B123: 1785 | C123: 1597830 | D123: 1602890 | E123: 20240728zes1942 | M123: У сына моего, например, так сделано, | N123: с | O123: огорода сделано и ставит там у них (их). | P123: нет вариативности
A124: Корпус говора деревни Пятиусово | B124: 1837 | C124: 1838120 | D124: 1844660 | E124: 20240728zes1942 | M124: Звонит. Ну а я как думаю, может (може) по делу надо, всегда беру телефон. Ну, пока у меня (мне) | N124: с | O124: мозгами (мозгам) всё в порядке. | P124: другой падеж
A125: Корпус говора деревни Пятиусово | B125: 1912 | C125: 2206990 | D125: 2213100 | E125: 20240728zes1942 | M125: Если мало, допустим | N125: с | O125: =со св = за огородом мало площади(площадь), они где - то на поле разработают и берут. -> #ERROR! | P125: неполные данные
A126: Корпус говора деревни Пятиусово | B126: 2007 | C126: 2578550 | D126: 2582480 | E126: 20240728zes1942 | M126: Сначала сеяли горох | N126: с | O126: овсом, викой там (тама). | P126: другой падеж
A127: Корпус говора деревни Пятиусово | B127: 2021 | C127: 2640440 | D127: 2643510 | E127: 20240728zes1942 | M127: Горох сеяли, да, скоту. Вместе | N127: с | O127: овсом. | P127: другой падеж
A128: Корпус говора деревни Пятиусово | B128: 2024 | C128: 2654960 | D128: 2657090 | E128: 20240728zes1942 | M128: Бывало привозят со струками (струкам) | N128: с | O128: этим. | P128: другой падеж
A129: Корпус говора деревни Пятиусово | B129: 2042 | C129: 2734320 | D129: 2739200 | E129: 20240728zes1942 | M129: Не в = не высокий ростом. Ну, | N129: с | O129: бородой такой, старше, старик. | P129: другой падеж
A130: Корпус говора деревни Пятиусово | B130: 2053 | C130: 2778350 | D130: 2781200 | E130: 20240728zes1942 | M130: Ну а потом (потома) а | N130: с | O130: #VALUE! | P130: неполные данные
A131: Корпус говора деревни Пятиусово | B131: 2143 | C131: 3101290 | D131: 3104280 | E131: 20240728zes1942 | M131: Ме = медведя. Юля приехадчи | N131: с | O131: Иваном, да? | P131: другой падеж
A132: Корпус говора деревни Пятиусово | B132: 2156 | C132: 3157690 | D132: 3162560 | E132: 20240728zes1942 | M132: Он | N132: с | O132: Гапанчуком. Может (може) помните Петра Гапанчука. Ну вот он ходил с ним (им). | P132: другой падеж
A133: Корпус говора деревни Пятиусово | B133: 2156 | C133: 3157690 | D133: 3162560 | E133: 20240728zes1942 | M133: Он с Гапанчуком. Может (може) помните Петра Гапанчука. Ну вот он ходил | N133: с | O133: ним (им). | P133: другой падеж
...

Sheet удалено_из
A1: Корпус | B1: utterance_id | C1: From | D1: To | E1: File | F1: Id | G1: String id | H1: Gender | I1: Year of birth | J1: Education | K1: Place of birth | L1: Place of living | M1: Left Context | N1: DMatch | O1: Right Context | P1: причина удаления | S1: =IFERROR(__xludf.DUMMYFUNCTION("QUERY(P2:P10000, ""SELECT P, COUNT(P) WHERE P IS NOT NULL AND P != '' GROUP BY P ORDER BY COUNT(P) DESC LABEL COUNT(P) 'Количество'"")"),"") | T1: =IFERROR(__xludf.DUMMYFUNCTION("""COMPUTED_VALUE"""),"Количество") -> Количество
A2: Корпус говора деревни Пятиусово | B2: 150 | C2: 1585412 | D2: 1589895 | E2: 20231028zes1942 | M2: А они, бывало, тихонечко | N2: из | O2: - под (спод) парты пряничек, конфетку... | P2: составной предлог | S2: =IFERROR(__xludf.DUMMYFUNCTION("""COMPUTED_VALUE"""),"составной предлог") -> составной предлог | T2: =IFERROR(__xludf.DUMMYFUNCTION("""COMPUTED_VALUE"""),13.0) -> 13
A3: Корпус говора деревни Пятиусово | B3: 264 | C3: 2286430 | D3: 2294940 | E3: 20231028zes1942 | M3: Вот... На = на вид красива =, ну она - то худая, а мне было двадцать девять лет тут (тута), я была всё время зудая, это сейчас я разъелась | N3: из | O3: ... Разъелась как корова... | P3: неполные данные | S3: =IFERROR(__xludf.DUMMYFUNCTION("""COMPUTED_VALUE"""),"неполные данные") -> неполные данные | T3: =IFERROR(__xludf.DUMMYFUNCTION("""COMPUTED_VALUE"""),8.0) -> 8
A4: Корпус говора деревни Пятиусово | B4: 479 | C4: 1413700 | D4: 1423570 | E4: 20240729evm1937 | G4: EVM1937 | I4: 1937 | J4: техникум | K4: Коковино | L4: Пятиусово | M4: Первая жена умерла, где - то двадцать пять лет уже, как ушла | N4: из | O4: жизни. | P4: идиома/фразеологизм | S4: =IFERROR(__xludf.DUMMYFUNCTION("""COMPUTED_VALUE"""),"вопрос интервьюера") -> вопрос интервьюера | T4: =IFERROR(__xludf.DUMMYFUNCTION("""COMPUTED_VALUE"""),6.0) -> 6
A5: Корпус говора деревни Пятиусово | B5: 480 | C5: 1425550 | D5: 1440820 | E5: 20240729evm1937 | G5: EVM1937 | I5: 1937 | J5: техникум | K5: Коковино | L5: Пятиусово | M5: Она тяжело болела, не так что тяжело, но болела, пользовалась ингалятором, у неё плохо с сердцем было, с дыханием, ушла | N5: из | O5: жизни. | P5: идиома/фразеологизм | S5: =IFERROR(__xludf.DUMMYFUNCTION("""COMPUTED_VALUE"""),"отсутствие существительного в предложной группе") -> отсутствие существительного в предложной группе | T5: =IFERROR(__xludf.DUMMYFUNCTION("""COMPUTED_VALUE"""),5.0) -> 5
A6: Корпус говора деревни Пятиусово | B6: 482 | C6: 1449000 | D6: 1457420 | E6: 20240729evm1937 | G6: EVM1937 | I6: 1937 | J6: техникум | K6: Коковино | L6: Пятиусово | M6: Тоже с сердцем, два или три, инфаркт или инсульт, ушла | N6: из | O6: жизни. | P6: идиома/фразеологизм | S6: =IFERROR(__xludf.DUMMYFUNCTION("""COMPUTED_VALUE"""),"самоповтор") -> самоповтор | T6: =IFERROR(__xludf.DUMMYFUNCTION("""COMPUTED_VALUE"""),5.0) -> 5
A7: Корпус говора деревни Пятиусово | B7: 973 | C7: 359492 | D7: 366199 | E7: 20231026lng1954 | G7: LNG1954 | I7: 1954 | J7: среднее (10 классов) | K7: Пятиусово | L7: Пятиусово | M7: Дальше - - больше. Там уже такие проблемы, знаешь, | N7: из | O7: - за пустяка может это всё. | P7: составной предлог | S7: =IFERROR(__xludf.DUMMYFUNCTION("""COMPUTED_VALUE"""),"идиома/фразеологизм") -> идиома/фразеологизм | T7: =IFERROR(__xludf.DUMMYFUNCTION("""COMPUTED_VALUE"""),4.0) -> 4
A8: Корпус говора деревни Пятиусово | B8: 988 | C8: 447600 | D8: 459493 | E8: 20231026lng1954 | G8: LNG1954 | I8: 1954 | J8: среднее (10 классов) | K8: Пятиусово | L8: Пятиусово | M8: И разругались, понимаешь? Вот | N8: из | O8: - за чего разругались? Ещё и как говорят... Да, и билета нету, а они вот деньги деливши разругались. Понимаешь? Так вот жизнь устроен. | P8: составной предлог | S8: =IFERROR(__xludf.DUMMYFUNCTION("""COMPUTED_VALUE"""),"Предлог с") -> Предлог с | T8: =IFERROR(__xludf.DUMMYFUNCTION("""COMPUTED_VALUE"""),3.0) -> 3
A9: Корпус говора деревни Пятиусово | B9: 1055 | C9: 870426 | D9: 874039 | E9: 20231026lng1954 | G9: LNG1954 | I9: 1954 | J9: среднее (10 классов) | K9: Пятиусово | L9: Пятиусово | M9: И вот я семь лет от звонка до звонка отсидел, вот. | N9: Из | O9: неё... | P9: отсутствие существительного в предложной группе | S9: =IFERROR(__xludf.DUMMYFUNCTION("""COMPUTED_VALUE"""),"отсутствие лексически выраженного существительного") -> отсутствие лексически выраженного существительного | T9: =IFERROR(__xludf.DUMMYFUNCTION("""COMPUTED_VALUE"""),3.0) -> 3
A10: Корпус говора деревни Пятиусово | B10: 2134 | C10: 3052780 | D10: 3054740 | E10: 20240728zes1942 | M10: Они теперь ушли уже | N10: из | O10: жизни. | P10: идиома/фразеологизм | S10: =IFERROR(__xludf.DUMMYFUNCTION("""COMPUTED_VALUE"""),"временное значение") -> временное значение | T10: =IFERROR(__xludf.DUMMYFUNCTION("""COMPUTED_VALUE"""),2.0) -> 2
A11: Корпус говора деревни Пятиусово | B11: 2377 | C11: 4090069 | D11: 4093879 | E11: 20240728zes1942 | M11: И они вот переехали | N11: из | O11: #NAME? | P11: неполные данные | S11: =IFERROR(__xludf.DUMMYFUNCTION("""COMPUTED_VALUE"""),"идиомы/фразеологизмы") -> идиомы/фразеологизмы | T11: =IFERROR(__xludf.DUMMYFUNCTION("""COMPUTED_VALUE"""),2.0) -> 2
A12: Корпус говора деревни Пятиусово | B12: 2377 | C12: 4090069 | D12: 4093879 | E12: 20240728zes1942 | M12: И они вот переехали из = из этих домов в один | N12: из | O12: них. | P12: отсутствие существительного в предложной группе | S12: =IFERROR(__xludf.DUMMYFUNCTION("""COMPUTED_VALUE"""),"неподходяший контекст") -> неподходяший контекст | T12: =IFERROR(__xludf.DUMMYFUNCTION("""COMPUTED_VALUE"""),2.0) -> 2
A13: Корпус говора деревни Пятиусово | B13: 2896 | C13: 2024652 | D13: 2033130 | E13: 20240727zes1942 | M13: А там (тама) на гормошке играли, была площадка сделаная | N13: из | O13: =это по = просто нацгак = как танцплощадка такая из дерева, из досок сложена. -> #ERROR! | P13: неполные данные | S13: =IFERROR(__xludf.DUMMYFUNCTION("""COMPUTED_VALUE"""),"колодец") -> колодец | T13: =IFERROR(__xludf.DUMMYFUNCTION("""COMPUTED_VALUE"""),1.0) -> 1
A14: Корпус говора деревни Пятиусово | B14: 3299 | C14: 4384932 | D14: 4391489 | E14: 20240727zes1942 | M14: Де = де = держа = держали. Я держала, даже кто - то из ребят | N14: из | O14: ваших приходил, я давала, помню, сало. | P14: отсутствие существительного в предложной группе | S14: =IFERROR(__xludf.DUMMYFUNCTION("""COMPUTED_VALUE"""),"повтор") -> повтор | T14: =IFERROR(__xludf.DUMMYFUNCTION("""COMPUTED_VALUE"""),1.0) -> 1
A15: Корпус говора деревни Пятиусово | B15: 3682 | C15: 870030 | D15: 872770 | E15: 20240802zes1942 | M15: А она с = ваша родная? | N15: Из | O15: Спиридово тоже? | P15: вопрос интервьюера | S15: =IFERROR(__xludf.DUMMYFUNCTION("""COMPUTED_VALUE"""),"предлог с") -> предлог с | T15: =IFERROR(__xludf.DUMMYFUNCTION("""COMPUTED_VALUE"""),1.0) -> 1
A16: Корпус говора деревни Пятиусово | B16: 3717 | C16: 997840 | D16: 1004450 | E16: 20240802zes1942 | M16: И она в одном | N16: из | O16: , в двухквартирном доме жила в одной стороне (стороны) она жила, во второй другие соседи жили. Потом... | P16: неполные данные | S16: =IFERROR(__xludf.DUMMYFUNCTION("""COMPUTED_VALUE"""),"предлог со") -> предлог со | T16: =IFERROR(__xludf.DUMMYFUNCTION("""COMPUTED_VALUE"""),1.0) -> 1
A17: Корпус говора деревни Пятиусово | B17: 3796 | C17: 1243670 | D17: 1248490 | E17: 20240802zes1942 | M17: А все ваши бабушки, дедушки, они тоже | N17: из | O17: Спиридово? Или ещё откуда - то отсюда? | P17: вопрос интервьюера
A18: Корпус говора деревни Пятиусово | B18: 3884 | C18: 1496215 | D18: 1498285 | E18: 20240802zes1942 | M18: Она тоже | N18: из | O18: Каськ =. Она говорит, что она из Каськова. | P18: самоповтор
A19: Корпус говора деревни Пятиусово | B19: 4408 | C19: 3175420 | D19: 3184220 | E19: 20240802zes1942 | M19: И у нас печа была большая. Я даже не знаю | N19: из | O19: (с) чего она. Мать сказала, из (с) камней, вроде, сделана была эта. Она сделана ещё до = до войны. | P19: отсутствие существительного в предложной группе
A20: Корпус говора деревни Пятиусово | B20: 4411 | C20: 3186850 | D20: 3190630 | E20: 20240802zes1942 | M20: Она... С = | N20: из | O20: (с) камней делали. Она большая была тоже. | P20: предлог с
A21: Корпус говора деревни Пятиусово | B21: 4412 | C21: 3191170 | D21: 3198320 | E21: 20240802zes1942 | M21: И была сделана лежанка из дереве = | N21: из | O21: =из досок, из досок. -> #ERROR! | P21: самоповтор
A22: Корпус говора деревни Пятиусово | B22: 5080 | C22: 5080620 | D22: 5082920 | E22: 20240802zes1942 | M22: Скажите, а вы сами когда - нибудь | N22: из | O22: деревни уезжали? | P22: вопрос интервьюера
A23: Корпус говора деревни Пятиусово | B23: 5116 | C23: 5174460 | D23: 5176500 | E23: 20240802zes1942 | M23: А в Луки автобус ходит | N23: из | O23: Торопы? | P23: вопрос интервьюера
A24: Корпус говора деревни Пятиусово | B24: 5254 | C24: 1988900 | D24: 2130100 | E24: 20240804zes1942 | M24: В де = в детстве какие вам истории надо, я вам расскажу историю, могу рассказать одну, у нас же дружили, ну я думаю, может кто и рассказывал вам из деревни. Дружил парень с девушкой, уже хотели жениться, ну это это на самом деле такое есть, было, и они, значит, на =, свадьба назначена, точно не могу, по - моему, как на Троицу. Они за два дня Троицы пошли в этом, говорит (говорить) мужик её (еёный), теперь ну парень, назовём его. Говорит (говорить), пойдём искупаемся, пошли к речке купаться напротив кладбища где - то туда, он как разделся, как нырнул, так и не вынырнул, вот такой случай это вот был. И вот она осталась на берегу, и потом она вышла за другого замуж, она сама позже умерла (умёрши), ну а дети в Ленинграде, одна дочка вроде умерла (умерши) уже. Так вот такой сулчай был, но | N24: из | O24: ма = из материного рассказа, ну она рассказывала, что - то, она сказала < нрзб > значит (значить), правильнро как сказать, сейчас скажу. Ну как бы в жизни всяко бывает, и не складывается жизнь. Ну приходит дочка к матери и говорит, говорит (говорить), я не хочу жить, я ну что там (тама) не ладится жизнь то ли < нрзб >, но я не спрашивала, точно не могу сказать, она ей говорит, знаешь, детка, дочь, говорит, вот, если тебе накакают на голову, ты скинь с головы, извините за выражение, и опять живи. Ну что, то это жизнь, говорит, не что - нибудь, вот такое. Ну и потом рассказывала, мужик, значит, ходит к женщине ходит (ходить) и ходит (ходить), она, значит, как лето приходит, так ему надо спать на сеновале, но эта жёнка, она понимает что - то, что да нет, она раз послушала, два послушала людей, говорит, надо мне пос = самой покараулить. Она пошла караулить, караулит (караулить), значит, они полезли на черда = на = на = на хлё = на сарай. Она помокнула в жижу, раньше жижесборники такие за хлёвом были, метлу, и туда на это самое, на хлёв их метлой этой с жижей. Говорит (говорить), вот такой случай был. Но драться никто не дрался, она сказала, не дрались, а вот такой случай был. | P24: самоповтор
A25: Корпус говора деревни Пятиусово | B25: 5271 | C25: 3091200 | D25: 3164300 | E25: 20240804zes1942 | M25: А так ну мно = много помню, всё | N25: из | O25: детства, я думаю, с трёх годов, с трёх лет я чу всё на свете помню, с трёх, если не раньше. Всё ка = как раньше же не было это самое во время войны мне было в сорок пятом году три года было < нрзб > четвёртый шёл, и ну я думаю, это года два мои, я думаю, мне года два было, и тогда был год ну чего - то такой голодный год был совсем, и вот я не помню только сейчас, не могу ск =, лошади то ли умерли (умёрши были) и к = погибали, наверное, и знаю, что бабушка принесла или кто - то принёс ей, она варила это мясо в печке, печи были, печи, в чугунке, чугунки были, в чугунке варила мясо, это потом с чугунка вытянула, и стол и дом тот сейчас стоит старый, поставила на стол, вытянула она такие лавки раньше были, ничего не было, одни скамейки были. Ну и она разложила меленько, она мясо такое длинное, помню это, она меленько разрезала, вот ешь потихонечку, это помню хорошо. | P25: временное значение
A26: Корпус говора деревни Пятиусово | B26: 5688 | C26: 2918110 | D26: 2923440 | E26: 20231023vpm1934_1 | G26: VPM1934 | I26: 1934 | J26: техникум | K26: Ануфриево | L26: Пятиусово | M26: Банку колотишь - колотишь - колотишь ну или кто - то | N26: из | O26: м = з = моих кто - то здесь, вот. | P26: неполные данные
A27: Корпус говора деревни Пятиусово | B27: 1729 | C27: 93015 | D27: 94385 | E27: 20180621_avv1933 | I27: 1933 | K27: неоконченное начальное | L27: авв1933 | M27: Ну а что ж | N27: из | O27: детства? | P27: временное значение
A28: Корпус говора деревни Пятиусово | B28: 3884 | C28: 1496215 | D28: 1498285 | E28: 20240802zes1942 | M28: Она тоже из Каськ =. Она говорит, что она | N28: из | O28: Каськова. | P28: вопрос интервьюера
A29: Корпус говора деревни Пятиусово | B29: 4056 | C29: 2095080 | D29: 2096330 | E29: 20240802zes1942 | M29: Аня | N29: из | O29: Горькова. | P29: вопрос интервьюера
A30: Корпус говора деревни Пятиусово | B30: 4462 | C30: 3379720 | D30: 3381540 | E30: 20240802zes1942 | M30: Ну у нас | N30: из | O30: колодца насос. | P30: колодец
A31: Корпус говора деревень Шетнево и Макеево | B31: 678 | C31: 478270 | D31: 481720 | E31: 20210716mga1932 | G31: mga1932 | H31: f | I31: 1932 | J31: начальное | K31: Пожоги | L31: Шетнево | M31: К нам тоже сколько раз приходили < | N31: из | O31: =-за>папки. -> #NAME? | P31: составной предлог
A32: Корпус говора деревень Шетнево и Макеево | B32: 1540 | C32: 574165 | D32: 584544 | E32: 20220715gip1953 | G32: gip1953 | H32: f | I32: 1953 | J32: среднее | K32: Макеево | L32: Макеево | M32: Зимой факел. Делали. Факел | N32: из | O32: такая... Негожая одежда. Её так... В комок делали, связывали. Потом на проволочину, или на палку. | P32: неполные данные
A33: Корпус говора деревень Шетнево и Макеево | B33: 2948 | C33: 3201308 | D33: 3221980 | E33: 20230427apb1940_B | G33: apb1940 | H33: f | I33: 1940 | J33: среднее | K33: Паново | L33: Макеево | M33: Там даже челны делали, это лодку такую самое, и бочечки делал, а то под капусту вот их, селёдка раньше была в бочках, вот была | N33: из | O33: - под селёдки, бочку эту в магазине караулят, кто купит, когда осталась | P33: составной предлог
A34: Корпус говора деревень Шетнево и Макеево | B34: 3263 | C34: 4388041 | D34: 4394437 | E34: 20230427gip1953 | G34: gip1953 | H34: f | I34: 1953 | J34: среднее | K34: Макеево | L34: Макеево | M34: Ну, а у неё сын был, наверное. Вот | N34: из | O34: - за сына, её, я думаю, не посадили. Это уже давно было - теперь же плохо помню. | P34: составной предлог
A35: Корпус говора деревень Шетнево и Макеево | B35: 4606 | C35: 6125030 | D35: 6128468 | E35: 20210706lnt1950 | G35: lnt1950 | H35: f | I35: 1950 | J35: среднее | K35: Шетнево | L35: Шетнево | M35: В это, отдыхать тоже на это на море. Ну я поехала, | N35: из | O35: - за ног. | P35: составной предлог
A36: Корпус говора деревень Шетнево и Макеево | B36: 3469 | C36: 5342643 | D36: 5345230 | E36: 20230427gip1953 | G36: gip1953 | H36: f | I36: 1953 | J36: среднее | K36: Макеево | L36: Макеево | M36: Я в то время уже | N36: из | O36: лаптей вышла. | P36: неподходяший контекст
A37: Корпус говора деревень Шетнево и Макеево | B37: 4153 | C37: 3945831 | D37: 3955013 | E37: 20210706lnt1950 | G37: lnt1950 | H37: f | I37: 1950 | J37: среднее | K37: Шетнево | L37: Шетнево | M37: Конечно. А сейчас | N37: из | O37: торговых – пожалуйста. Раньше эту самогонку как было прятали эту самогонку - господи, не давали ж гнать. Ой, было поймают – сразу штрафу. | P37: неподходяший контекст
A38: Корпус говора деревень Шетнево и Макеево | B38: 5877 | C38: 713150 | D38: 715040 | E38: 20230505anv1941 | G38: anv1941 | H38: m | I38: 1941 | J38: среднее | K38: Макеево | L38: Макеево | M38: Да, нитки делали ( | N38: из | O38: ) со льна. | P38: предлог со
A39: Корпус говора деревень Шетнево и Макеево | B39: 5877 | C39: 713150 | D39: 715040 | E39: 20230505anv1941 | G39: anv1941 | H39: m | I39: 1941 | J39: среднее | K39: Макеево | L39: Макеево | M39: Да, нитки делали ( | N39: из | O39: ) со льна. | P39: повтор
A40: Корпус говора деревень Шетнево и Макеево | B40: 7253 | C40: 4552847 | D40: 4556621 | E40: 20210707gip1953 | G40: gip1953 | H40: f | I40: 1953 | J40: среднее | K40: Макеево | L40: Макеево | M40: И он поехал, там с каким - то с нашим, кто - то | N40: из | O40: наших был. | P40: отсутствие существительного в предложной группе
A41: Корпус говора деревень Шетнево и Макеево | B41: 2939 | C41: 3119385 | D41: 3122754 | E41: 20230427apb1940_B | G41: apb1940 | H41: f | I41: 1940 | J41: среднее | K41: Паново | L41: Макеево | N41: Из | O41: глины (с гнилы) делали чашки, жбанки | P41: Предлог с
A42: Корпус говора деревень Шетнево и Макеево | B42: 2941 | C42: 3133261 | D42: 3145692 | E42: 20230427apb1940_B | G42: apb1940 | H42: f | I42: 1940 | J42: среднее | K42: Паново | L42: Макеево | M42: Ну | N42: из | O42: глины (с глины) сделанные моло = ну такие по два литра этого, молоко раньше же, всё равно банок так не было, вот это жбанки, бывало, молоко цедили | P42: Предлог с
A43: Корпус говора деревень Шетнево и Макеево | B43: 2944 | C43: 3162015 | D43: 3166261 | E43: 20230427apb1940_B | G43: apb1940 | H43: f | I43: 1940 | J43: среднее | K43: Паново | L43: Макеево | M43: Жбанки ну всякую посуду делала | N43: из | O43: глины (с глины), делают | P43: Предлог с
A44: Корпус Опочецких говоров | B44: 954 | C44: 2650909 | D44: 2657892 | E44: 20180620_nae1958 | G44: нае1958 | I44: 1958 | J44: среднее специальное | M44: Ну вот тут, как говорили, молитву читают перед киселём. Когда вот кисель поели, | N44: из | O44: - за стола тогда готовь, с поминок. | P44: составной предлог
A45: Корпус Опочецких говоров | B45: 2105 | C45: 1205175 | D45: 1208640 | E45: 20180621_avv1933 | G45: авв1933 | I45: 1933 | J45: неоконченное начальное | N45: из | O45: - под низа, который я проехала, назад зерно. | P45: составной предлог
A46: Корпус Опочецких говоров | B46: 3276 | C46: 171915 | D46: 177557 | E46: 20190701_saf1973 | G46: саф1973 | I46: 1973 | J46: высшее | M46: Дед воевал. Дед Саня. Он | N46: из | O46: - под оккупации, когда их тут пришли | P46: составной предлог
A47: Корпус Опочецких говоров | B47: 3733 | C47: 398419 | D47: 416069 | E47: 20190706_tai1955 | G47: таи1955 | I47: 1955 | J47: неоконченное начальное | M47: И вот потом они вот вот этот купили. И квартира у них вот в новом в этом доме, когда пере =, когда воинскую часть от нас убрали, а перевели с Эстонии, вот они - то вот построили этот дом последний на Раи Гавриловой три. И вот ей там дали тоже квартиру | N47: из | O47: - за этого дома. | P47: составной предлог
A48: Корпус Опочецких говоров | B48: 4462 | C48: 1429312 | D48: 1431853 | E48: 20180618_zii1932_a | G48: зии1932 | I48: 1932 | J48: начальное | M48: Та (тая) деревня страдала | N48: из | O48: - за партизан | P48: составной предлог
A49: Корпус Опочецких говоров | B49: 6490 | C49: 88708 | D49: 90710 | E49: 20180621a_nae1958 | G49: нае1958 | I49: 1958 | J49: среднее специальное | M49: только что | N49: из | O49: - за этого так. | P49: составной предлог
A50: Корпус Опочецких говоров | B50: 3341 | C50: 576493 | D50: 580629 | E50: 20190701_saf1973 | G50: саф1973 | I50: 1973 | J50: высшее | M50: Погоди, как же деревня... всё на языке у меня крутится, и что, вылетело | N50: из | O50: головы... | P50: идиомы/фразеологизмы
A51: Корпус Опочецких говоров | B51: 3342 | C51: 581479 | D51: 583771 | E51: 20190701_saf1973 | G51: саф1973 | I51: 1973 | J51: высшее | M51: Вылетела | N51: из | O51: головы Макушинская... | P51: идиомы/фразеологизмы
A52: Корпус Опочецких говоров | B52: 656 | C52: 979914 | D52: 987276 | E52: 20180620_nae1958 | G52: нае1958 | I52: 1958 | J52: среднее специальное | M52: Это, солнце... Вот это у него сделано из щуки | N52: из | O52: большой, двенадцать с половиной килограмм или двенадцать шестьсот... | P52: самоповтор
A53: Корпус Опочецких говоров | B53: 3586 | C53: 2355866 | D53: 2360755 | E53: 20190701_saf1973 | G53: саф1973 | I53: 1973 | J53: высшее | M53: Сделали... | N53: из | O53: того было, из того и лепили, грубо говоря, то есть... | P53: отсутствие лексически выраженного существительного
A54: Корпус Опочецких говоров | B54: 3586 | C54: 2355866 | D54: 2360755 | E54: 20190701_saf1973 | G54: саф1973 | I54: 1973 | J54: высшее | M54: Сделали... из того было, | N54: из | O54: того и лепили, грубо говоря, то есть... | P54: отсутствие лексически выраженного существительного
A55: Корпус Опочецких говоров | B55: 3671 | C55: 2899698 | D55: 2905242 | E55: 20190701_saf1973 | G55: саф1973 | I55: 1973 | J55: высшее | M55: О! [ | N55: Из | O55: ] она из Анчинок, вот, вспомнил, Анчинки. Анчинкский мост, анчинкский мост. | P55: самоповтор
A56: Корпус Опочецких говоров | B56: 6296 | C56: 7374112 | D56: 7376250 | E56: 20190702_tve1955 | G56: тве1955 | I56: 1955 | J56: unknown | M56: Как | N56: из | O56: < нрзб >. | P56: неполные данные
A57: Корпус Опочецких говоров | B57: 6486 | C57: 60040 | D57: 66376 | E57: 20180621a_nae1958 | G57: нае1958 | I57: 1958 | J57: среднее специальное | M57: Да, только баба Зина вот | N57: из | O57: тех, к = которая там проживала, она одна. | P57: отсутствие лексически выраженного существительного
A58: Корпус Опочецких говоров | B58: 2430 | C58: 2200915 | D58: 2209855 | E58: 20180621_avv1933 | G58: авв1933 | I58: 1933 | J58: неоконченное начальное | M58: А получилось, вот, сказала раньше, вот, красный был, < нрзб > у нас тут такие молоденькие, тоже идут, дерутся, | N58: из | O58: подола поднимают | P58: неполные данные

Sheet респонденты
A2: =IFERROR(__xludf.DUMMYFUNCTION("QUERY('предлог_с'!I2:I10000, ""SELECT I, COUNT(I) WHERE I IS NOT NULL GROUP BY I LABEL COUNT(I) ''"")")," ") | B2: =IFERROR(__xludf.DUMMYFUNCTION("""COMPUTED_VALUE"""),"") | E2: Образование у информантов "предлог с" | I2: Образование у информантов "предлог с"
A3: =IFERROR(__xludf.DUMMYFUNCTION("""COMPUTED_VALUE"""),1930.0) -> 1930 | B3: =IFERROR(__xludf.DUMMYFUNCTION("""COMPUTED_VALUE"""),12.0) -> 12 | E3: =IFERROR(__xludf.DUMMYFUNCTION("QUERY('предлог_с'!J2:J10000, ""SELECT J, COUNT(J) WHERE J IS NOT NULL AND J != 'unknown' GROUP BY J LABEL COUNT(J) ''"")"),"высшее") -> высшее | F3: =IFERROR(__xludf.DUMMYFUNCTION("""COMPUTED_VALUE"""),8.0) -> 8 | G3: =F3/F11 -> 0.02507837 | I3: высшее | J3: 0.02507837 | N3: =IFERROR(__xludf.DUMMYFUNCTION("QUERY('предлог_из'!I2:I10000, ""SELECT I, COUNT(I) WHERE I IS NOT NULL GROUP BY I LABEL COUNT(I) ''"")"),1932.0) -> 1932 | O3: =IFERROR(__xludf.DUMMYFUNCTION("""COMPUTED_VALUE"""),4.0) -> 4 | Q3: Образование у информантов предлог "из" | T3: Образование у информантов предлог "из"
A4: =IFERROR(__xludf.DUMMYFUNCTION("""COMPUTED_VALUE"""),1932.0) -> 1932 | B4: =IFERROR(__xludf.DUMMYFUNCTION("""COMPUTED_VALUE"""),41.0) -> 41 | E4: =IFERROR(__xludf.DUMMYFUNCTION("""COMPUTED_VALUE"""),"начальное") -> начальное | F4: =IFERROR(__xludf.DUMMYFUNCTION("""COMPUTED_VALUE"""),41.0) -> 41 | G4: =F4/F11 -> 0.12852665 | I4: начальное | J4: 0.12852665 | N4: =IFERROR(__xludf.DUMMYFUNCTION("""COMPUTED_VALUE"""),1934.0) -> 1934 | O4: =IFERROR(__xludf.DUMMYFUNCTION("""COMPUTED_VALUE"""),1.0) -> 1 | Q4: =IFERROR(__xludf.DUMMYFUNCTION("QUERY('предлог_из'!J2:J10000, ""SELECT J, COUNT(J) WHERE J IS NOT NULL AND J != 'unknown' GROUP BY J LABEL COUNT(J) ''"")"),"высшее") -> высшее | R4: =IFERROR(__xludf.DUMMYFUNCTION("""COMPUTED_VALUE"""),3.0) -> 3 | T4: высшее | U4: =R4/R10 -> 0.073170732
A5: =IFERROR(__xludf.DUMMYFUNCTION("""COMPUTED_VALUE"""),1933.0) -> 1933 | B5: =IFERROR(__xludf.DUMMYFUNCTION("""COMPUTED_VALUE"""),12.0) -> 12 | E5: =IFERROR(__xludf.DUMMYFUNCTION("""COMPUTED_VALUE"""),"неоконченное начальное") -> неоконченное начальное | F5: =IFERROR(__xludf.DUMMYFUNCTION("""COMPUTED_VALUE"""),30.0) -> 30 | G5: =F5/F11 -> 0.094043887 | I5: неоконченное начальное | J5: 0.094043887 | N5: =IFERROR(__xludf.DUMMYFUNCTION("""COMPUTED_VALUE"""),1935.0) -> 1935 | O5: =IFERROR(__xludf.DUMMYFUNCTION("""COMPUTED_VALUE"""),2.0) -> 2 | Q5: =IFERROR(__xludf.DUMMYFUNCTION("""COMPUTED_VALUE"""),"начальное") -> начальное | R5: =IFERROR(__xludf.DUMMYFUNCTION("""COMPUTED_VALUE"""),4.0) -> 4 | T5: начальное | U5: =R5/R10 -> 0.097560976
A6: =IFERROR(__xludf.DUMMYFUNCTION("""COMPUTED_VALUE"""),1934.0) -> 1934 | B6: =IFERROR(__xludf.DUMMYFUNCTION("""COMPUTED_VALUE"""),6.0) -> 6 | E6: =IFERROR(__xludf.DUMMYFUNCTION("""COMPUTED_VALUE"""),"неоконченное среднее") -> неоконченное среднее | F6: =IFERROR(__xludf.DUMMYFUNCTION("""COMPUTED_VALUE"""),3.0) -> 3 | G6: =F6/F11 -> 0.0094043887 | I6: неоконченное среднее | J6: 0.0094043887 | N6: =IFERROR(__xludf.DUMMYFUNCTION("""COMPUTED_VALUE"""),1937.0) -> 1937 | O6: =IFERROR(__xludf.DUMMYFUNCTION("""COMPUTED_VALUE"""),7.0) -> 7 | Q6: =IFERROR(__xludf.DUMMYFUNCTION("""COMPUTED_VALUE"""),"среднее") -> среднее | R6: =IFERROR(__xludf.DUMMYFUNCTION("""COMPUTED_VALUE"""),17.0) -> 17 | T6: среднее | U6: =R6/R10 -> 0.41463415
A7: =IFERROR(__xludf.DUMMYFUNCTION("""COMPUTED_VALUE"""),1935.0) -> 1935 | B7: =IFERROR(__xludf.DUMMYFUNCTION("""COMPUTED_VALUE"""),13.0) -> 13 | E7: =IFERROR(__xludf.DUMMYFUNCTION("""COMPUTED_VALUE"""),"среднее") -> среднее | F7: =IFERROR(__xludf.DUMMYFUNCTION("""COMPUTED_VALUE"""),169.0) -> 169 | G7: =F7/F11 -> 0.52978056 | I7: среднее | J7: 0.52978056 | N7: =IFERROR(__xludf.DUMMYFUNCTION("""COMPUTED_VALUE"""),1939.0) -> 1939 | O7: =IFERROR(__xludf.DUMMYFUNCTION("""COMPUTED_VALUE"""),2.0) -> 2 | Q7: =IFERROR(__xludf.DUMMYFUNCTION("""COMPUTED_VALUE"""),"среднее (10 классов)") -> среднее (10 классов) | R7: =IFERROR(__xludf.DUMMYFUNCTION("""COMPUTED_VALUE"""),2.0) -> 2 | T7: среднее (10 классов) | U7: =R7/R10 -> 0.048780488
A8: =IFERROR(__xludf.DUMMYFUNCTION("""COMPUTED_VALUE"""),1937.0) -> 1937 | B8: =IFERROR(__xludf.DUMMYFUNCTION("""COMPUTED_VALUE"""),20.0) -> 20 | E8: =IFERROR(__xludf.DUMMYFUNCTION("""COMPUTED_VALUE"""),"среднее (10 классов)") -> среднее (10 классов) | F8: =IFERROR(__xludf.DUMMYFUNCTION("""COMPUTED_VALUE"""),4.0) -> 4 | G8: =F8/F11 -> 0.012539185 | I8: среднее (10 классов) | J8: 0.012539185 | N8: =IFERROR(__xludf.DUMMYFUNCTION("""COMPUTED_VALUE"""),1940.0) -> 1940 | O8: =IFERROR(__xludf.DUMMYFUNCTION("""COMPUTED_VALUE"""),5.0) -> 5 | Q8: =IFERROR(__xludf.DUMMYFUNCTION("""COMPUTED_VALUE"""),"среднее специальное") -> среднее специальное | R8: =IFERROR(__xludf.DUMMYFUNCTION("""COMPUTED_VALUE"""),5.0) -> 5 | T8: среднее специальное | U8: =R8/R10 -> 0.12195122
A9: =IFERROR(__xludf.DUMMYFUNCTION("""COMPUTED_VALUE"""),1939.0) -> 1939 | B9: =IFERROR(__xludf.DUMMYFUNCTION("""COMPUTED_VALUE"""),8.0) -> 8 | E9: =IFERROR(__xludf.DUMMYFUNCTION("""COMPUTED_VALUE"""),"среднее специальное") -> среднее специальное | F9: =IFERROR(__xludf.DUMMYFUNCTION("""COMPUTED_VALUE"""),25.0) -> 25 | G9: =F9/F11 -> 0.078369906 | I9: среднее специальное | J9: 0.078369906 | N9: =IFERROR(__xludf.DUMMYFUNCTION("""COMPUTED_VALUE"""),1949.0) -> 1949 | O9: =IFERROR(__xludf.DUMMYFUNCTION("""COMPUTED_VALUE"""),1.0) -> 1 | Q9: =IFERROR(__xludf.DUMMYFUNCTION("""COMPUTED_VALUE"""),"техникум") -> техникум | R9: =IFERROR(__xludf.DUMMYFUNCTION("""COMPUTED_VALUE"""),10.0) -> 10 | T9: техникум | U9: =R9/R10 -> 0.24390244
A10: =IFERROR(__xludf.DUMMYFUNCTION("""COMPUTED_VALUE"""),1940.0) -> 1940 | B10: =IFERROR(__xludf.DUMMYFUNCTION("""COMPUTED_VALUE"""),17.0) -> 17 | E10: =IFERROR(__xludf.DUMMYFUNCTION("""COMPUTED_VALUE"""),"техникум") -> техникум | F10: =IFERROR(__xludf.DUMMYFUNCTION("""COMPUTED_VALUE"""),39.0) -> 39 | G10: =F10/F11 -> 0.12225705 | I10: техникум | J10: 0.12225705 | N10: =IFERROR(__xludf.DUMMYFUNCTION("""COMPUTED_VALUE"""),1950.0) -> 1950 | O10: =IFERROR(__xludf.DUMMYFUNCTION("""COMPUTED_VALUE"""),1.0) -> 1 | Q10: итого | R10: =SUM(R4:R9) -> 41
A11: =IFERROR(__xludf.DUMMYFUNCTION("""COMPUTED_VALUE"""),1941.0) -> 1941 | B11: =IFERROR(__xludf.DUMMYFUNCTION("""COMPUTED_VALUE"""),9.0) -> 9 | E11: итого | F11: =SUM(F3:F10) -> 319 | N11: =IFERROR(__xludf.DUMMYFUNCTION("""COMPUTED_VALUE"""),1953.0) -> 1953 | O11: =IFERROR(__xludf.DUMMYFUNCTION("""COMPUTED_VALUE"""),8.0) -> 8 | Q11: всего | R11: =ROWS('предлог_из'!I2:I83) -> 82
A12: =IFERROR(__xludf.DUMMYFUNCTION("""COMPUTED_VALUE"""),1949.0) -> 1949 | B12: =IFERROR(__xludf.DUMMYFUNCTION("""COMPUTED_VALUE"""),7.0) -> 7 | E12: всего | F12: =ROWS('предлог_с'!J2:J414) -> 413 | N12: =IFERROR(__xludf.DUMMYFUNCTION("""COMPUTED_VALUE"""),1954.0) -> 1954 | O12: =IFERROR(__xludf.DUMMYFUNCTION("""COMPUTED_VALUE"""),3.0) -> 3 | Q12: заполнено | R12: =R10/R11 -> 0.5
A13: =IFERROR(__xludf.DUMMYFUNCTION("""COMPUTED_VALUE"""),1950.0) -> 1950 | B13: =IFERROR(__xludf.DUMMYFUNCTION("""COMPUTED_VALUE"""),32.0) -> 32 | E13: заполнено | F13: =F11/F12 -> 0.77239709 | N13: =IFERROR(__xludf.DUMMYFUNCTION("""COMPUTED_VALUE"""),1958.0) -> 1958 | O13: =IFERROR(__xludf.DUMMYFUNCTION("""COMPUTED_VALUE"""),5.0) -> 5
A14: =IFERROR(__xludf.DUMMYFUNCTION("""COMPUTED_VALUE"""),1953.0) -> 1953 | B14: =IFERROR(__xludf.DUMMYFUNCTION("""COMPUTED_VALUE"""),79.0) -> 79 | N14: =IFERROR(__xludf.DUMMYFUNCTION("""COMPUTED_VALUE"""),1973.0) -> 1973 | O14: =IFERROR(__xludf.DUMMYFUNCTION("""COMPUTED_VALUE"""),3.0) -> 3
A15: =IFERROR(__xludf.DUMMYFUNCTION("""COMPUTED_VALUE"""),1954.0) -> 1954 | B15: =IFERROR(__xludf.DUMMYFUNCTION("""COMPUTED_VALUE"""),9.0) -> 9 | N15: итого | O15: =SUM(O3:O14) -> 42
A16: =IFERROR(__xludf.DUMMYFUNCTION("""COMPUTED_VALUE"""),1955.0) -> 1955 | B16: =IFERROR(__xludf.DUMMYFUNCTION("""COMPUTED_VALUE"""),10.0) -> 10 | N16: всего | O16: =ROWS('предлог_из'!I2:I83) -> 82
A17: =IFERROR(__xludf.DUMMYFUNCTION("""COMPUTED_VALUE"""),1956.0) -> 1956 | B17: =IFERROR(__xludf.DUMMYFUNCTION("""COMPUTED_VALUE"""),8.0) -> 8 | N17: заполнено | O17: =O15/O16 -> 0.51219512
A18: =IFERROR(__xludf.DUMMYFUNCTION("""COMPUTED_VALUE"""),1958.0) -> 1958 | B18: =IFERROR(__xludf.DUMMYFUNCTION("""COMPUTED_VALUE"""),25.0) -> 25
A19: =IFERROR(__xludf.DUMMYFUNCTION("""COMPUTED_VALUE"""),1972.0) -> 1972 | B19: =IFERROR(__xludf.DUMMYFUNCTION("""COMPUTED_VALUE"""),14.0) -> 14 | N19: Распределение по возрасту "предлог из"
A20: =IFERROR(__xludf.DUMMYFUNCTION("""COMPUTED_VALUE"""),1973.0) -> 1973 | B20: =IFERROR(__xludf.DUMMYFUNCTION("""COMPUTED_VALUE"""),8.0) -> 8 | N20: 1932 | O20: =O3/O15 -> 0.095238095
A21: =IFERROR(__xludf.DUMMYFUNCTION("""COMPUTED_VALUE"""),1980.0) -> 1980 | B21: =IFERROR(__xludf.DUMMYFUNCTION("""COMPUTED_VALUE"""),3.0) -> 3 | N21: 1934 | O21: =O4/O15 -> 0.023809524
A22: итого | B22: =SUM(B3:B21) -> 333 | N22: 1935 | O22: =O5/O15 -> 0.047619048
A23: всего | B23: =ROWS('предлог_с'!I2:I414) -> 413 | N23: 1937 | O23: =O6/O15 -> 0.16666667
A24: заполнено | B24: =B22/B23 -> 0.8062954 | N24: 1939 | O24: =O7/O15 -> 0.047619048
N25: 1940 | O25: =O8/O15 -> 0.11904762
A26: Распределение по возрасту "предлог с" | N26: 1949 | O26: =O9/O15 -> 0.023809524
A27: 1930 | B27: =B3/B22 -> 0.036036036 | N27: 1950 | O27: =O10/O15 -> 0.023809524
A28: 1932 | B28: =B4/B22 -> 0.12312312 | N28: 1953 | O28: =O11/O15 -> 0.19047619
A29: 1933 | B29: =B5/B22 -> 0.036036036 | N29: 1954 | O29: =O12/O15 -> 0.071428571
A30: 1934 | B30: =B6/B22 -> 0.018018018 | N30: 1958 | O30: =O13/O15 -> 0.11904762
A31: 1935 | B31: =B7/B22 -> 0.039039039 | N31: 1973 | O31: =O14/O15 -> 0.071428571
A32: 1937 | B32: =B8/B22 -> 0.06006006
A33: 1939 | B33: =B9/B22 -> 0.024024024
A34: 1940 | B34: =B10/B22 -> 0.051051051
A35: 1941 | B35: =B11/B22 -> 0.027027027
A36: 1949 | B36: =B12/B22 -> 0.021021021
A37: 1950 | B37: =B13/B22 -> 0.096096096
A38: 1953 | B38: =B14/B22 -> 0.23723724
A39: 1954 | B39: =B15/B22 -> 0.027027027
A40: 1955 | B40: =B16/B22 -> 0.03003003
A41: 1956 | B41: =B17/B22 -> 0.024024024
A42: 1958 | B42: =B18/B22 -> 0.075075075
A43: 1972 | B43: =B19/B22 -> 0.042042042
A44: 1973 | B44: =B20/B22 -> 0.024024024
A45: 1980 | B45: =B21/B22 -> 0.009009009
A46: сумма | B46: =SUM(B27:B45) -> 1
A52: Пятиусово: предлог с | D52: Шетнево и Макеево: предлог с | G52: Опочка: предлог с
A53: =IFERROR(__xludf.DUMMYFUNCTION("QUERY('предлог_с'!A1:J10000, ""SELECT J, COUNT(J) WHERE J IS NOT NULL AND J != 'unknown' AND A = 'Корпус говора деревни Пятиусово' GROUP BY J LABEL COUNT(J) ''"")"),"Education") -> Education | B53: =IFERROR(__xludf.DUMMYFUNCTION("""COMPUTED_VALUE"""),"") | D53: =IFERROR(__xludf.DUMMYFUNCTION("QUERY('предлог_с'!A1:J10000, ""SELECT J, COUNT(J) WHERE J IS NOT NULL AND J != 'unknown' AND A = 'Корпус говора деревень Шетнево и Макеево' GROUP BY J LABEL COUNT(J) ''"")"),"Education") -> Education | E53: =IFERROR(__xludf.DUMMYFUNCTION("""COMPUTED_VALUE"""),"") | G53: =IFERROR(__xludf.DUMMYFUNCTION("QUERY('предлог_с'!A1:J10000, ""SELECT J, COUNT(J) WHERE J IS NOT NULL AND J != 'unknown' AND A = 'Корпус Опочецких говоров' GROUP BY J LABEL COUNT(J) ''"")"),"Education") -> Education | H53: =IFERROR(__xludf.DUMMYFUNCTION("""COMPUTED_VALUE"""),"")
A54: =IFERROR(__xludf.DUMMYFUNCTION("""COMPUTED_VALUE"""),"среднее (10 классов)") -> среднее (10 классов) | B54: =IFERROR(__xludf.DUMMYFUNCTION("""COMPUTED_VALUE"""),4.0) -> 4 | D54: =IFERROR(__xludf.DUMMYFUNCTION("""COMPUTED_VALUE"""),"начальное") -> начальное | E54: =IFERROR(__xludf.DUMMYFUNCTION("""COMPUTED_VALUE"""),22.0) -> 22 | G54: =IFERROR(__xludf.DUMMYFUNCTION("""COMPUTED_VALUE"""),"высшее") -> высшее | H54: =IFERROR(__xludf.DUMMYFUNCTION("""COMPUTED_VALUE"""),8.0) -> 8
A55: =IFERROR(__xludf.DUMMYFUNCTION("""COMPUTED_VALUE"""),"техникум") -> техникум | B55: =IFERROR(__xludf.DUMMYFUNCTION("""COMPUTED_VALUE"""),39.0) -> 39 | D55: =IFERROR(__xludf.DUMMYFUNCTION("""COMPUTED_VALUE"""),"неоконченное среднее") -> неоконченное среднее | E55: =IFERROR(__xludf.DUMMYFUNCTION("""COMPUTED_VALUE"""),3.0) -> 3 | G55: =IFERROR(__xludf.DUMMYFUNCTION("""COMPUTED_VALUE"""),"начальное") -> начальное | H55: =IFERROR(__xludf.DUMMYFUNCTION("""COMPUTED_VALUE"""),19.0) -> 19
D56: =IFERROR(__xludf.DUMMYFUNCTION("""COMPUTED_VALUE"""),"среднее") -> среднее | E56: =IFERROR(__xludf.DUMMYFUNCTION("""COMPUTED_VALUE"""),147.0) -> 147 | G56: =IFERROR(__xludf.DUMMYFUNCTION("""COMPUTED_VALUE"""),"неоконченное начальное") -> неоконченное начальное | H56: =IFERROR(__xludf.DUMMYFUNCTION("""COMPUTED_VALUE"""),30.0) -> 30
G57: =IFERROR(__xludf.DUMMYFUNCTION("""COMPUTED_VALUE"""),"среднее") -> среднее | H57: =IFERROR(__xludf.DUMMYFUNCTION("""COMPUTED_VALUE"""),22.0) -> 22
G58: =IFERROR(__xludf.DUMMYFUNCTION("""COMPUTED_VALUE"""),"среднее специальное") -> среднее специальное | H58: =IFERROR(__xludf.DUMMYFUNCTION("""COMPUTED_VALUE"""),25.0) -> 25
A61: Пятиусово: предлог из | D61: Шетнево и Макеево: предлог из | G61: Опочка: предлог из
A62: =IFERROR(__xludf.DUMMYFUNCTION("QUERY('предлог_из'!A1:J10000, ""SELECT J, COUNT(J) WHERE J IS NOT NULL AND J != 'unknown' AND A = 'корпус говора деревни Пятиусово' GROUP BY J LABEL COUNT(J) ''"")"),"Education") -> Education | B62: =IFERROR(__xludf.DUMMYFUNCTION("""COMPUTED_VALUE"""),"") | D62: =IFERROR(__xludf.DUMMYFUNCTION("QUERY('предлог_из'!A1:J10000, ""SELECT J, COUNT(J) WHERE J IS NOT NULL AND J != 'unknown' AND A = 'Корпус говора деревень Шетнево и Макеево' GROUP BY J LABEL COUNT(J) ''"")"),"Education") -> Education | E62: =IFERROR(__xludf.DUMMYFUNCTION("""COMPUTED_VALUE"""),"") | G62: =IFERROR(__xludf.DUMMYFUNCTION("QUERY('предлог_из'!A1:J10000, ""SELECT J, COUNT(J) WHERE J IS NOT NULL AND J != 'unknown' AND A = 'Корпус Опочецких говоров' GROUP BY J LABEL COUNT(J) ''"")"),"Education") -> Education | H62: =IFERROR(__xludf.DUMMYFUNCTION("""COMPUTED_VALUE"""),"")
A63: =IFERROR(__xludf.DUMMYFUNCTION("""COMPUTED_VALUE"""),"среднее (10 классов)") -> среднее (10 классов) | B63: =IFERROR(__xludf.DUMMYFUNCTION("""COMPUTED_VALUE"""),2.0) -> 2 | D63: =IFERROR(__xludf.DUMMYFUNCTION("""COMPUTED_VALUE"""),"начальное") -> начальное | E63: =IFERROR(__xludf.DUMMYFUNCTION("""COMPUTED_VALUE"""),2.0) -> 2 | G63: =IFERROR(__xludf.DUMMYFUNCTION("""COMPUTED_VALUE"""),"высшее") -> высшее | H63: =IFERROR(__xludf.DUMMYFUNCTION("""COMPUTED_VALUE"""),3.0) -> 3
A64: =IFERROR(__xludf.DUMMYFUNCTION("""COMPUTED_VALUE"""),"техникум") -> техникум | B64: =IFERROR(__xludf.DUMMYFUNCTION("""COMPUTED_VALUE"""),10.0) -> 10 | D64: =IFERROR(__xludf.DUMMYFUNCTION("""COMPUTED_VALUE"""),"среднее") -> среднее | E64: =IFERROR(__xludf.DUMMYFUNCTION("""COMPUTED_VALUE"""),17.0) -> 17 | G64: =IFERROR(__xludf.DUMMYFUNCTION("""COMPUTED_VALUE"""),"начальное") -> начальное | H64: =IFERROR(__xludf.DUMMYFUNCTION("""COMPUTED_VALUE"""),2.0) -> 2
G65: =IFERROR(__xludf.DUMMYFUNCTION("""COMPUTED_VALUE"""),"среднее специальное") -> среднее специальное | H65: =IFERROR(__xludf.DUMMYFUNCTION("""COMPUTED_VALUE"""),5.0) -> 5
A68: Пятиусово, год рождения: предлог с | D68: Шетнево и Макеево, год рождения: предлог с | G68: Опочка, год рождения: предлог с
A69: =IFERROR(__xludf.DUMMYFUNCTION("QUERY('предлог_с'!A2:I10000, ""SELECT I, COUNT(I) WHERE I IS NOT NULL AND A = 'Корпус говора деревни Пятиусово' GROUP BY I LABEL COUNT(I) ''"")"),1934.0) -> 1934 | B69: =IFERROR(__xludf.DUMMYFUNCTION("""COMPUTED_VALUE"""),6.0) -> 6 | D69: =IFERROR(__xludf.DUMMYFUNCTION("QUERY('предлог_с'!A2:I10000, ""SELECT I, COUNT(I) WHERE I IS NOT NULL AND A = 'Корпус говора деревень Шетнево и Макеево' GROUP BY I LABEL COUNT(I) ''"")"),1932.0) -> 1932 | E69: =IFERROR(__xludf.DUMMYFUNCTION("""COMPUTED_VALUE"""),22.0) -> 22 | G69: =IFERROR(__xludf.DUMMYFUNCTION("QUERY('предлог_с'!A2:I10000, ""SELECT I, COUNT(I) WHERE I IS NOT NULL AND A = 'Корпус Опочецких говоров' GROUP BY I LABEL COUNT(I) ''"")"),1930.0) -> 1930 | H69: =IFERROR(__xludf.DUMMYFUNCTION("""COMPUTED_VALUE"""),12.0) -> 12
A70: =IFERROR(__xludf.DUMMYFUNCTION("""COMPUTED_VALUE"""),1935.0) -> 1935 | B70: =IFERROR(__xludf.DUMMYFUNCTION("""COMPUTED_VALUE"""),13.0) -> 13 | D70: =IFERROR(__xludf.DUMMYFUNCTION("""COMPUTED_VALUE"""),1939.0) -> 1939 | E70: =IFERROR(__xludf.DUMMYFUNCTION("""COMPUTED_VALUE"""),8.0) -> 8 | G70: =IFERROR(__xludf.DUMMYFUNCTION("""COMPUTED_VALUE"""),1932.0) -> 1932 | H70: =IFERROR(__xludf.DUMMYFUNCTION("""COMPUTED_VALUE"""),19.0) -> 19
A71: =IFERROR(__xludf.DUMMYFUNCTION("""COMPUTED_VALUE"""),1937.0) -> 1937 | B71: =IFERROR(__xludf.DUMMYFUNCTION("""COMPUTED_VALUE"""),20.0) -> 20 | D71: =IFERROR(__xludf.DUMMYFUNCTION("""COMPUTED_VALUE"""),1940.0) -> 1940 | E71: =IFERROR(__xludf.DUMMYFUNCTION("""COMPUTED_VALUE"""),17.0) -> 17 | G71: =IFERROR(__xludf.DUMMYFUNCTION("""COMPUTED_VALUE"""),1933.0) -> 1933 | H71: =IFERROR(__xludf.DUMMYFUNCTION("""COMPUTED_VALUE"""),12.0) -> 12
A72: =IFERROR(__xludf.DUMMYFUNCTION("""COMPUTED_VALUE"""),1954.0) -> 1954 | B72: =IFERROR(__xludf.DUMMYFUNCTION("""COMPUTED_VALUE"""),4.0) -> 4 | D72: =IFERROR(__xludf.DUMMYFUNCTION("""COMPUTED_VALUE"""),1941.0) -> 1941 | E72: =IFERROR(__xludf.DUMMYFUNCTION("""COMPUTED_VALUE"""),9.0) -> 9 | G72: =IFERROR(__xludf.DUMMYFUNCTION("""COMPUTED_VALUE"""),1949.0) -> 1949 | H72: =IFERROR(__xludf.DUMMYFUNCTION("""COMPUTED_VALUE"""),7.0) -> 7
D73: =IFERROR(__xludf.DUMMYFUNCTION("""COMPUTED_VALUE"""),1950.0) -> 1950 | E73: =IFERROR(__xludf.DUMMYFUNCTION("""COMPUTED_VALUE"""),32.0) -> 32 | G73: =IFERROR(__xludf.DUMMYFUNCTION("""COMPUTED_VALUE"""),1955.0) -> 1955 | H73: =IFERROR(__xludf.DUMMYFUNCTION("""COMPUTED_VALUE"""),10.0) -> 10
D74: =IFERROR(__xludf.DUMMYFUNCTION("""COMPUTED_VALUE"""),1953.0) -> 1953 | E74: =IFERROR(__xludf.DUMMYFUNCTION("""COMPUTED_VALUE"""),79.0) -> 79 | G74: =IFERROR(__xludf.DUMMYFUNCTION("""COMPUTED_VALUE"""),1956.0) -> 1956 | H74: =IFERROR(__xludf.DUMMYFUNCTION("""COMPUTED_VALUE"""),8.0) -> 8
D75: =IFERROR(__xludf.DUMMYFUNCTION("""COMPUTED_VALUE"""),1954.0) -> 1954 | E75: =IFERROR(__xludf.DUMMYFUNCTION("""COMPUTED_VALUE"""),5.0) -> 5 | G75: =IFERROR(__xludf.DUMMYFUNCTION("""COMPUTED_VALUE"""),1958.0) -> 1958 | H75: =IFERROR(__xludf.DUMMYFUNCTION("""COMPUTED_VALUE"""),25.0) -> 25
G76: =IFERROR(__xludf.DUMMYFUNCTION("""COMPUTED_VALUE"""),1972.0) -> 1972 | H76: =IFERROR(__xludf.DUMMYFUNCTION("""COMPUTED_VALUE"""),14.0) -> 14
G77: =IFERROR(__xludf.DUMMYFUNCTION("""COMPUTED_VALUE"""),1973.0) -> 1973 | H77: =IFERROR(__xludf.DUMMYFUNCTION("""COMPUTED_VALUE"""),8.0) -> 8
G78: =IFERROR(__xludf.DUMMYFUNCTION("""COMPUTED_VALUE"""),1980.0) -> 1980 | H78: =IFERROR(__xludf.DUMMYFUNCTION("""COMPUTED_VALUE"""),3.0) -> 3
A80: Пятиусово, год рождения: предлог из | D80: Шетнево и Макеево, год рождения: предлог из | G80: Опочка, год рождения: предлог из
A81: =IFERROR(__xludf.DUMMYFUNCTION("QUERY('предлог_из'!A2:I10000, ""SELECT I, COUNT(I) WHERE I IS NOT NULL AND A = 'корпус говора деревни Пятиусово' GROUP BY I LABEL COUNT(I) ''"")"),1934.0) -> 1934 | B81: =IFERROR(__xludf.DUMMYFUNCTION("""COMPUTED_VALUE"""),1.0) -> 1 | D81: =IFERROR(__xludf.DUMMYFUNCTION("QUERY('предлог_из'!A2:I10000, ""SELECT I, COUNT(I) WHERE I IS NOT NULL AND A = 'Корпус говора деревень Шетнево и Макеево' GROUP BY I LABEL COUNT(I) ''"")"),1932.0) -> 1932 | E81: =IFERROR(__xludf.DUMMYFUNCTION("""COMPUTED_VALUE"""),2.0) -> 2 | G81: =IFERROR(__xludf.DUMMYFUNCTION("QUERY('предлог_из'!A2:I10000, ""SELECT I, COUNT(I) WHERE I IS NOT NULL AND A = 'Корпус Опочецких говоров' GROUP BY I LABEL COUNT(I) ''"")"),1932.0) -> 1932 | H81: =IFERROR(__xludf.DUMMYFUNCTION("""COMPUTED_VALUE"""),2.0) -> 2
A82: =IFERROR(__xludf.DUMMYFUNCTION("""COMPUTED_VALUE"""),1935.0) -> 1935 | B82: =IFERROR(__xludf.DUMMYFUNCTION("""COMPUTED_VALUE"""),2.0) -> 2 | D82: =IFERROR(__xludf.DUMMYFUNCTION("""COMPUTED_VALUE"""),1939.0) -> 1939 | E82: =IFERROR(__xludf.DUMMYFUNCTION("""COMPUTED_VALUE"""),2.0) -> 2 | G82: =IFERROR(__xludf.DUMMYFUNCTION("""COMPUTED_VALUE"""),1949.0) -> 1949 | H82: =IFERROR(__xludf.DUMMYFUNCTION("""COMPUTED_VALUE"""),1.0) -> 1
A83: =IFERROR(__xludf.DUMMYFUNCTION("""COMPUTED_VALUE"""),1937.0) -> 1937 | B83: =IFERROR(__xludf.DUMMYFUNCTION("""COMPUTED_VALUE"""),7.0) -> 7 | D83: =IFERROR(__xludf.DUMMYFUNCTION("""COMPUTED_VALUE"""),1940.0) -> 1940 | E83: =IFERROR(__xludf.DUMMYFUNCTION("""COMPUTED_VALUE"""),5.0) -> 5 | G83: =IFERROR(__xludf.DUMMYFUNCTION("""COMPUTED_VALUE"""),1958.0) -> 1958 | H83: =IFERROR(__xludf.DUMMYFUNCTION("""COMPUTED_VALUE"""),5.0) -> 5
A84: =IFERROR(__xludf.DUMMYFUNCTION("""COMPUTED_VALUE"""),1954.0) -> 1954 | B84: =IFERROR(__xludf.DUMMYFUNCTION("""COMPUTED_VALUE"""),2.0) -> 2 | D84: =IFERROR(__xludf.DUMMYFUNCTION("""COMPUTED_VALUE"""),1950.0) -> 1950 | E84: =IFERROR(__xludf.DUMMYFUNCTION("""COMPUTED_VALUE"""),1.0) -> 1 | G84: =IFERROR(__xludf.DUMMYFUNCTION("""COMPUTED_VALUE"""),1973.0) -> 1973 | H84: =IFERROR(__xludf.DUMMYFUNCTION("""COMPUTED_VALUE"""),3.0) -> 3
D85: =IFERROR(__xludf.DUMMYFUNCTION("""COMPUTED_VALUE"""),1953.0) -> 1953 | E85: =IFERROR(__xludf.DUMMYFUNCTION("""COMPUTED_VALUE"""),8.0) -> 8
D86: =IFERROR(__xludf.DUMMYFUNCTION("""COMPUTED_VALUE"""),1954.0) -> 1954 | E86: =IFERROR(__xludf.DUMMYFUNCTION("""COMPUTED_VALUE"""),1.0) -> 1

Sheet статистика
A1: Таблица 1. Общее количество примеров по корпусам | F1: Таблица 3. Распределение предлога с по семантическим категориям (все корпуса)
A2: Корпус | B2: Всего примеров с с | C2: Всего примеров с из | D2: Всего релевантных примеров | F2: Семантическая категория | G2: Количество примеров с с | H2: Доля от всех примеров с с (%) | I2: Количество примеров с из | J2: Доля от всех примеров с из (%)
A3: Корпус говора деревни Пятиусово | B3: =COUNTIF('предлог_с'!A2:A1000, "Корпус говора деревни Пятиусово") -> 109 | C3: =COUNTIF('предлог_из'!A2:A1000, "Корпус говора деревни Пятиусово") -> 48 | D3: =SUM(B3:C3) -> 157 | F3: топоним | G3: =COUNTIF('предлог_с'!Q2:Q1000, 1) -> 173 | H3: =G3/$G$15 -> 0.4188862 | I3: =COUNTIF('предлог_из'!Q2:Q1000, 1) -> 16 | J3: =I3/$I$15 -> 0.19512195
A4: Корпус говора деревень Шетнево и Макеево | B4: =COUNTIF('предлог_с'!A2:A1001, "Корпус говора деревень Шетнево и Макеево") -> 184 | C4: =COUNTIF('предлог_из'!A2:A1001, "Корпус говора деревень Шетнево и Макеево") -> 22 | D4: =SUM(B4:C4) -> 206 | F4: единица атд | G4: =COUNTIF('предлог_с'!R2:R1000, 1) -> 47 | H4: =G4/$G$15 -> 0.11380145 | I4: =COUNTIF('предлог_из'!R2:R1000, 1) -> 3 | J4: =I4/$I$15 -> 0.036585366
A5: Корпус Опочецких говоров | B5: =COUNTIF('предлог_с'!A2:A1002, "Корпус Опочецких говоров") -> 120 | C5: =COUNTIF('предлог_из'!A2:A1002, "Корпус Опочецких говоров") -> 12 | D5: =SUM(B5:C5) -> 132 | F5: жилище | G5: =COUNTIF('предлог_с'!S2:S1000, 1) -> 13 | H5: =G5/$G$15 -> 0.031476998 | I5: =COUNTIF('предлог_из'!S2:S1000, 1) -> 4 | J5: =I5/$I$15 -> 0.048780488
A6: Объединенные корпуса | B6: =SUM(B3:B5) -> 413 | C6: =SUM(C3:C5) -> 82 | D6: =SUM(B6:C6) -> 495 | F6: природные локации | G6: =COUNTIF('предлог_с'!T2:T1000, 1) -> 13 | H6: =G6/$G$15 -> 0.031476998 | I6: =COUNTIF('предлог_из'!T2:T1000, 1) -> 1 | J6: =I6/$I$15 -> 0.012195122
A7: Проценты | B7: =B6/D6 -> 0.83434343 | C7: =C6/D6 -> 0.16565657 | D7: =SUM(B7:C7) -> 1 | F7: учреждения | G7: =COUNTIF('предлог_с'!U2:U1000, 1) -> 39 | H7: =G7/$G$15 -> 0.094430993 | I7: =COUNTIF('предлог_из'!U2:U1000, 1) -> 9 | J7: =I7/$I$15 -> 0.1097561
F8: контейнер | G8: =COUNTIF('предлог_с'!X2:X1000, 1) -> 34 | H8: =G8/$G$15 -> 0.082324455 | I8: =COUNTIF('предлог_из'!X2:X1000, 1) -> 1 | J8: =I8/$I$15 -> 0.012195122
A9: Таблица 2. Процентное отношение примеров по корпусам | F9: материал | G9: =COUNTIF('предлог_с'!Y2:Y1000, 1) -> 58 | H9: =G9/$G$15 -> 0.14043584 | I9: =COUNTIF('предлог_из'!Y2:Y1000, 1) -> 30 | J9: =I9/$I$15 -> 0.36585366
A10: Корпус | B10: Всего примеров с с | C10: Всего примеров с из | D10: Всего релевантных примеров | F10: армия, тюрьма | G10: =COUNTIF('предлог_с'!Z2:Z1000, 1) -> 19 | H10: =G10/$G$15 -> 0.046004843 | I10: =COUNTIF('предлог_из'!Z2:Z1000, 1) -> 0 | J10: =I10/$I$15 -> 0
A11: Корпус говора деревни Пятиусово | B11: =B3/D3 -> 0.69426752 | C11: =C3/D3 -> 0.30573248 | D11: =D3/$D$6 -> 0.31717172 | F11: коллектив, группа | G11: =COUNTIF('предлог_с'!AA2:AA1000, 1) -> 6 | H11: =G11/$G$15 -> 0.014527845 | I11: =COUNTIF('предлог_из'!AA2:AA1000, 1) -> 13 | J11: =I11/$I$15 -> 0.15853659
A12: Корпус говора деревень Шетнево и Макеево | B12: =B4/D4 -> 0.89320388 | C12: =C4/D4 -> 0.10679612 | D12: =D4/$D$6 -> 0.41616162 | F12: деньги, заработок | G12: =COUNTIF('предлог_с'!AB2:AB1000, 1) -> 1 | H12: =G12/$G$15 -> 0.0024213075 | I12: =COUNTIF('предлог_из'!AB2:AB1000, 1) -> 0 | J12: =I12/$I$15 -> 0
A13: Корпус Опочецких говоров | B13: =B5/D5 -> 0.90909091 | C13: =C5/D5 -> 0.090909091 | D13: =D5/$D$6 -> 0.26666667 | F13: пространственные локации | G13: =COUNTIF('предлог_с'!V2:V1000, 1) -> 5 | H13: =G13/$G$15 -> 0.012106538 | I13: =COUNTIF('предлог_из'!V2:V1000, 1) -> 2 | J13: =I13/$I$15 -> 0.024390244
A14: Объединенные корпуса | B14: =B6/D6 -> 0.83434343 | C14: =C6/D6 -> 0.16565657 | D14: =D6/$D$6 -> 1 | F14: остальные употребления | G14: =COUNTIF('предлог_с'!W2:W1000, 1) -> 5 | H14: =G14/$G$15 -> 0.012106538 | I14: =COUNTIF('предлог_из'!W2:W1000, 1) -> 3 | J14: =I14/$I$15 -> 0.036585366
F15: итого | G15: =SUM(G3:G14) -> 413 | H15: =G15/$G$15 -> 1 | I15: =SUM(I3:I14) -> 82 | J15: =SUM(J3:J14) -> 1
A18: Прайминг | F18: Таблица 4. Распределение предлога с по типам конструкций (все корпуса)
A19: Есть прайминг из | B19: =COUNTIF('предлог_из'!AC2:AC1000, 1) -> 8 | C19: =B19/$B$21 -> 0.097560976 | F19: Тип конструкции | G19: Количество примеров с с | H19: Доля от всех примеров с с (%) | I19: Количество примеров с из | J19: Доля от всех примеров с из (%) | L19: Тип конструкции | M19: Доля от всех примеров с с (%) | P19: Тип конструкции | Q19: Доля от всех примеров с из (%)
A20: Нет прайминга из | B20: =COUNTIF('предлог_из'!AC2:AC1000, 0) -> 74 | C20: =B20/$B$21 -> 0.90243902 | F20: Пространственная (s) | G20: =COUNTIF('предлог_с'!AD2:AD1000, "s") -> 250 | H20: =G20/$G$23 -> 0.60532688 | I20: =COUNTIF('предлог_из'!AD2:AD1000, "s") -> 25 | J20: =I20/$I$23 -> 0.30487805 | L20: Пространственная (s) | M20: 0.60532688 | P20: Пространственная (s) | Q20: 0.30487805
A21: Итого | B21: =sum(B19:B20) -> 82 | C21: =SUM(C19:C20) -> 1 | F21: Объектная (o) | G21: =COUNTIF('предлог_с'!AD2:AD1000, "o") -> 49 | H21: =G21/$G$23 -> 0.11864407 | I21: =COUNTIF('предлог_из'!AD2:AD1000, "o") -> 33 | J21: =I21/$I$23 -> 0.40243902 | L21: Объектная (o) | M21: 0.11864407 | P21: Объектная (o) | Q21: 0.40243902
F22: Атрибутивная (a) | G22: =COUNTIF('предлог_с'!AD2:AD1000, "a") -> 114 | H22: =G22/$G$23 -> 0.27602906 | I22: =COUNTIF('предлог_из'!AD2:AD1000, "a") -> 24 | J22: =I22/$I$23 -> 0.29268293 | L22: Атрибутивная (a) | M22: 0.27602906 | P22: Атрибутивная (a) | Q22: 0.29268293
A23: Прайминг по семантическим категориям | F23: итого | G23: =SUM(G20:G22) -> 413 | H23: =G23/$G$23 -> 1 | I23: =SUM(I20:I22) -> 82 | J23: =I23/$I$23 -> 1 | M23: 1 | P23: итого | Q23: 1
A24: топоним | B24: =COUNTIFS('предлог_из'!Q2:Q1000, 1,'предлог_из'!AC2:AC1000, 1) -> 4
A25: материал | B25: =COUNTIFS('предлог_из'!Y2:Y1000, 1,'предлог_из'!AC2:AC1000, 1) -> 4
A27: Соответствие норме | G27: Тип связи (предлог с)
B28: предлог с | C28: проценты с | D28: предлог из | E28: проценты из | H28: пространственная (s) | I28: объектная (o) | J28: аттрибутивная (a)
A29: соотвествует норме | B29: =COUNTIF('предлог_с'!AF2:AF1000, "y") -> 9 | C29: =B29/$B$31 -> 0.021791768 | D29: =COUNTIF('предлог_из'!AF2:AF1000, "y") -> 79 | E29: =D29/$D$31 -> 0.96341463 | G29: именная (n) | H29: =COUNTIFS('предлог_с'!AD2:AD1000, "s",'предлог_с'!AE2:AE1000, "n") -> 0 | I29: =COUNTIFS('предлог_с'!AD2:AD1000, "o",'предлог_с'!AE2:AE1000, "n") -> 0 | J29: =COUNTIFS('предлог_с'!AD2:AD1000, "a",'предлог_с'!AE2:AE1000, "n") -> 114
A30: не соответствует норме | B30: =COUNTIF('предлог_с'!AF2:AF1000, "n") -> 404 | C30: =B30/$B$31 -> 0.97820823 | D30: =COUNTIF('предлог_из'!AF2:AF1000, "n") -> 3 | E30: =D30/$D$31 -> 0.036585366 | G30: глагольная (v) | H30: =COUNTIFS('предлог_с'!AD2:AD1000, "s",'предлог_с'!AE2:AE1000, "v") -> 250 | I30: =COUNTIFS('предлог_с'!AD2:AD1000, "o",'предлог_с'!AE2:AE1000, "v") -> 49 | J30: =COUNTIFS('предлог_с'!AD3:AD1001, "a",'предлог_с'!AE3:AE1001, "v") -> 0
A31: итого | B31: =SUM(B29:B30) -> 413 | C31: =B31/$B$31 -> 1 | D31: =SUM(D29:D30) -> 82 | E31: =D31/$D$31 -> 1
G33: Тип связи (предлог из)
H34: пространственная (s) | I34: объектная (o) | J34: аттрибутивная (a)
G35: именная (n) | H35: =COUNTIFS('предлог_из'!AD2:AD1000, "s",'предлог_из'!AE2:AE1000, "n") -> 0 | I35: =COUNTIFS('предлог_из'!AD2:AD1000, "o",'предлог_из'!AE2:AE1000, "n") -> 4 | J35: =COUNTIFS('предлог_из'!AD2:AD1000, "a",'предлог_из'!AE2:AE1000, "n") -> 24
G36: глагольная (v) | H36: =COUNTIFS('предлог_из'!AD2:AD1000, "s",'предлог_из'!AE2:AE1000, "v") -> 25 | I36: =COUNTIFS('предлог_из'!AD2:AD1000, "o",'предлог_из'!AE2:AE1000, "v") -> 29 | J36: =COUNTIFS('предлог_из'!AD3:AD1001, "a",'предлог_из'!AE3:AE1001, "v") -> 0
A38: Распределение семантических категорий по типам конструкций для предлога с | G38: Распределение семантических категорий по типам конструкций для предлога с
B39: Пространственная (s) | C39: объектная (o) | D39: аттрибутивная (a) | E39: итого | H39: Пространственная (s) | I39: объектная (o) | J39: аттрибутивная (a)
A40: топоним | B40: =COUNTIFS('предлог_с'!AD2:AD1000, "s",'предлог_с'!Q2:Q1000, 1) -> 111 | C40: =COUNTIFS('предлог_с'!AD2:AD1000, "o",'предлог_с'!Q2:Q1000, 1) -> 0 | D40: =COUNTIFS('предлог_с'!AD2:AD1000, "a",'предлог_с'!Q2:Q1000, 1) -> 62 | E40: =SUM(B40:D40) -> 173 | G40: топоним | H40: =B40/E40 -> 0.6416185 | I40: =C40/E40 -> 0 | J40: =D40/E40 -> 0.3583815
A41: единица атд | B41: =COUNTIFS('предлог_с'!AD2:AD1000, "s",'предлог_с'!R2:R1000, 1) -> 25 | C41: =COUNTIFS('предлог_с'!AD2:AD1000, "o",'предлог_с'!R2:R1000, 1) -> 0 | D41: =COUNTIFS('предлог_с'!AD2:AD1000, "a",'предлог_с'!R2:R1000, 1) -> 22 | E41: =SUM(B41:D41) -> 47 | G41: единица атд | H41: =B41/E41 -> 0.53191489 | I41: =C41/E41 -> 0 | J41: =D41/E41 -> 0.46808511
A42: жилище | B42: =COUNTIFS('предлог_с'!AD2:AD1000, "s",'предлог_с'!S2:S1000, 1) -> 13 | C42: =COUNTIFS('предлог_с'!AD2:AD1000, "o",'предлог_с'!S2:S1000, 1) -> 0 | D42: =COUNTIFS('предлог_с'!AD2:AD1000, "a",'предлог_с'!S2:S1000, 1) -> 0 | E42: =SUM(B42:D42) -> 13 | G42: жилище | H42: =B42/E42 -> 1 | I42: =C42/E42 -> 0 | J42: =D42/E42 -> 0
A43: природные локации | B43: =COUNTIFS('предлог_с'!AD2:AD1000, "s",'предлог_с'!T2:T1000, 1) -> 13 | C43: =COUNTIFS('предлог_с'!AD2:AD1000, "o",'предлог_с'!T2:T1000, 1) -> 0 | D43: =COUNTIFS('предлог_с'!AD2:AD1000, "a",'предлог_с'!T2:T1000, 1) -> 0 | E43: =SUM(B43:D43) -> 13 | G43: природные локации | H43: =B43/E43 -> 1 | I43: =C43/E43 -> 0 | J43: =D43/E43 -> 0
A44: учреждения | B44: =COUNTIFS('предлог_с'!AD2:AD1000, "s",'предлог_с'!U2:U1000, 1) -> 35 | C44: =COUNTIFS('предлог_с'!AD2:AD1000, "o",'предлог_с'!U2:U1000, 1) -> 0 | D44: =COUNTIFS('предлог_с'!AD2:AD1000, "a",'предлог_с'!U2:U1000, 1) -> 4 | E44: =SUM(B44:D44) -> 39 | G44: учреждения | H44: =B44/E44 -> 0.8974359 | I44: =C44/E44 -> 0 | J44: =D44/E44 -> 0.1025641
A45: контейнер | B45: =COUNTIFS('предлог_с'!AD2:AD1000, "s",'предлог_с'!X2:X1000, 1) -> 29 | C45: =COUNTIFS('предлог_с'!AD2:AD1000, "o",'предлог_с'!X2:X1000, 1) -> 2 | D45: =COUNTIFS('предлог_с'!AD2:AD1000, "a",'предлог_с'!X2:X1000, 1) -> 3 | E45: =SUM(B45:D45) -> 34 | G45: контейнер | H45: =B45/E45 -> 0.85294118 | I45: =C45/E45 -> 0.058823529 | J45: =D45/E45 -> 0.088235294
A46: материал | B46: =COUNTIFS('предлог_с'!AD2:AD1000, "s",'предлог_с'!Y2:Y1000, 1) -> 0 | C46: =COUNTIFS('предлог_с'!AD2:AD1000, "o",'предлог_с'!Y2:Y1000, 1) -> 45 | D46: =COUNTIFS('предлог_с'!AD2:AD1000, "a",'предлог_с'!Y2:Y1000, 1) -> 13 | E46: =SUM(B46:D46) -> 58 | G46: материал | H46: =B46/E46 -> 0 | I46: =C46/E46 -> 0.77586207 | J46: =D46/E46 -> 0.22413793
A47: армия, тюрьма | B47: =COUNTIFS('предлог_с'!AD2:AD1000, "s",'предлог_с'!Z2:Z1000, 1) -> 14 | C47: =COUNTIFS('предлог_с'!AD2:AD1000, "o",'предлог_с'!Z2:Z1000, 1) -> 0 | D47: =COUNTIFS('предлог_с'!AD2:AD1000, "a",'предлог_с'!Z2:Z1000, 1) -> 5 | E47: =SUM(B47:D47) -> 19 | G47: армия, тюрьма | H47: =B47/E47 -> 0.73684211 | I47: =C47/E47 -> 0 | J47: =D47/E47 -> 0.26315789
A48: коллектив, группа | B48: =COUNTIFS('предлог_с'!AD2:AD1000, "s",'предлог_с'!AA2:AA1000, 1) -> 2 | C48: =COUNTIFS('предлог_с'!AD2:AD1000, "o",'предлог_с'!AA2:AA1000, 1) -> 0 | D48: =COUNTIFS('предлог_с'!AD2:AD1000, "a",'предлог_с'!AA2:AA1000, 1) -> 4 | E48: =SUM(B48:D48) -> 6 | G48: коллектив, группа | H48: =B48/E48 -> 0.33333333 | I48: =C48/E48 -> 0 | J48: =D48/E48 -> 0.66666667
A49: деньги, заработок | B49: =COUNTIFS('предлог_с'!AD2:AD1000, "s",'предлог_с'!AB2:AB1000, 1) -> 0 | C49: =COUNTIFS('предлог_с'!AD2:AD1000, "o",'предлог_с'!AB2:AB1000, 1) -> 1 | D49: =COUNTIFS('предлог_с'!AD2:AD1000, "a",'предлог_с'!AB2:AB1000, 1) -> 0 | E49: =SUM(B49:D49) -> 1 | G49: деньги, заработок | H49: =B49/E49 -> 0 | I49: =C49/E49 -> 1 | J49: =D49/E49 -> 0
A50: пространственные локации | B50: =COUNTIFS('предлог_с'!AD2:AD1000, "s",'предлог_с'!V2:V1000, 1) -> 4 | C50: =COUNTIFS('предлог_с'!AD2:AD1000, "o",'предлог_с'!V2:V1000, 1) -> 0 | D50: =COUNTIFS('предлог_с'!AD2:AD1000, "a",'предлог_с'!V2:V1000, 1) -> 1 | E50: =SUM(B50:D50) -> 5 | G50: пространственные локации | H50: =B50/E50 -> 0.8 | I50: =C50/E50 -> 0 | J50: =D50/E50 -> 0.2
A51: остальные употребления | B51: =COUNTIFS('предлог_с'!AD2:AD1000, "s",'предлог_с'!W2:W1000, 1) -> 4 | C51: =COUNTIFS('предлог_с'!AD2:AD1000, "o",'предлог_с'!W2:W1000, 1) -> 1 | D51: =COUNTIFS('предлог_с'!AD2:AD1000, "a",'предлог_с'!W2:W1000, 1) -> 0 | E51: =SUM(B51:D51) -> 5 | G51: остальные употребления | H51: =B51/E51 -> 0.8 | I51: =C51/E51 -> 0.2 | J51: =D51/E51 -> 0
A52: итого | B52: =SUM(B39:B51) -> 250 | C52: =SUM(C39:C51) -> 49 | D52: =SUM(D39:D51) -> 114 | E52: =SUM(E39:E51) -> 413 | G52: итого | H52: =B52/E52 -> 0.60532688 | I52: =C52/E52 -> 0.11864407 | J52: =D52/E52 -> 0.27602906
A55: Распределение семантических категорий по типам конструкций для предлога из | G55: Распределение семантических категорий по типам конструкций для предлога из
B56: Пространственная (s) | C56: объектная (o) | D56: аттрибутивная (a) | E56: итого | H56: Пространственная (s) | I56: объектная (o) | J56: аттрибутивная (a)
A57: топоним | B57: =COUNTIFS('предлог_из'!AD2:AD1000, "s",'предлог_из'!Q2:Q1000, 1) -> 8 | C57: =COUNTIFS('предлог_из'!AD2:AD1000, "o",'предлог_из'!Q2:Q1000, 1) -> 0 | D57: =COUNTIFS('предлог_из'!AD2:AD1000, "a",'предлог_из'!Q2:Q1000, 1) -> 8 | E57: =SUM(B57:D57) -> 16 | G57: топоним | H57: =B57/E57 -> 0.5 | I57: =C57/E57 -> 0 | J57: =D57/E57 -> 0.5
A58: единица атд | B58: =COUNTIFS('предлог_из'!AD2:AD1000, "s",'предлог_из'!R2:R1000, 1) -> 0 | C58: =COUNTIFS('предлог_из'!AD2:AD1000, "o",'предлог_из'!R2:R1000, 1) -> 2 | D58: =COUNTIFS('предлог_с'!AD2:AD1000, "a",'предлог_с'!R2:R1000, 1) -> 22 | E58: =SUM(B58:D58) -> 24 | G58: единица атд | H58: =B58/E58 -> 0 | I58: =C58/E58 -> 0.083333333 | J58: =D58/E58 -> 0.91666667
A59: жилище | B59: =COUNTIFS('предлог_из'!AD2:AD1000, "s",'предлог_из'!S2:S1000, 1) -> 4 | C59: =COUNTIFS('предлог_из'!AD2:AD1000, "o",'предлог_из'!S2:S1000, 1) -> 0 | D59: =COUNTIFS('предлог_из'!AD2:AD1000, "a",'предлог_из'!S2:S1000, 1) -> 0 | E59: =SUM(B59:D59) -> 4 | G59: жилище | H59: =B59/E59 -> 1 | I59: =C59/E59 -> 0 | J59: =D59/E59 -> 0
A60: природные локации | B60: =COUNTIFS('предлог_из'!AD2:AD1000, "s",'предлог_из'!T2:T1000, 1) -> 1 | C60: =COUNTIFS('предлог_из'!AD2:AD1000, "o",'предлог_из'!T2:T1000, 1) -> 0 | D60: =COUNTIFS('предлог_из'!AD2:AD1000, "a",'предлог_из'!T2:T1000, 1) -> 0 | E60: =SUM(B60:D60) -> 1 | G60: природные локации | H60: =B60/E60 -> 1 | I60: =C60/E60 -> 0 | J60: =D60/E60 -> 0
A61: учреждения | B61: =COUNTIFS('предлог_из'!AD2:AD1000, "s",'предлог_из'!U2:U1000, 1) -> 9 | C61: =COUNTIFS('предлог_из'!AD2:AD1000, "o",'предлог_из'!U2:U1000, 1) -> 0 | D61: =COUNTIFS('предлог_из'!AD2:AD1000, "a",'предлог_из'!U2:U1000, 1) -> 0 | E61: =SUM(B61:D61) -> 9 | G61: учреждения | H61: =B61/E61 -> 1 | I61: =C61/E61 -> 0 | J61: =D61/E61 -> 0
A62: контейнер | B62: =COUNTIFS('предлог_из'!AD2:AD1000, "s",'предлог_из'!X2:X1000, 1) -> 1 | C62: =COUNTIFS('предлог_из'!AD2:AD1000, "o",'предлог_из'!X2:X1000, 1) -> 0 | D62: =COUNTIFS('предлог_из'!AD2:AD1000, "a",'предлог_из'!X2:X1000, 1) -> 0 | E62: =SUM(B62:D62) -> 1 | G62: контейнер | H62: =B62/E62 -> 1 | I62: =C62/E62 -> 0 | J62: =D62/E62 -> 0
A63: материал | B63: =COUNTIFS('предлог_из'!AD2:AD1000, "s",'предлог_из'!Y2:Y1000, 1) -> 0 | C63: =COUNTIFS('предлог_из'!AD2:AD1000, "o",'предлог_из'!Y2:Y1000, 1) -> 24 | D63: =COUNTIFS('предлог_из'!AD2:AD1000, "a",'предлог_из'!Y2:Y1000, 1) -> 6 | E63: =SUM(B63:D63) -> 30 | G63: материал | H63: =B63/E63 -> 0 | I63: =C63/E63 -> 0.8 | J63: =D63/E63 -> 0.2
A64: армия, тюрьма | B64: =COUNTIFS('предлог_из'!AD2:AD1000, "s",'предлог_из'!Z2:Z1000, 1) -> 0 | C64: =COUNTIFS('предлог_из'!AD2:AD1000, "o",'предлог_из'!Z2:Z1000, 1) -> 0 | D64: =COUNTIFS('предлог_из'!AD2:AD1000, "a",'предлог_из'!Z2:Z1000, 1) -> 0 | E64: =SUM(B64:D64) -> 0 | G64: армия, тюрьма | H64: 0 | I64: 0 | J64: 0
A65: коллектив, группа | B65: =COUNTIFS('предлог_из'!AD2:AD1000, "s",'предлог_из'!AA2:AA1000, 1) -> 0 | C65: =COUNTIFS('предлог_из'!AD2:AD1000, "o",'предлог_из'!AA2:AA1000, 1) -> 6 | D65: =COUNTIFS('предлог_из'!AD2:AD1000, "a",'предлог_из'!AA2:AA1000, 1) -> 7 | E65: =SUM(B65:D65) -> 13 | G65: коллектив, группа | H65: =B65/E65 -> 0 | I65: =C65/E65 -> 0.46153846 | J65: =D65/E65 -> 0.53846154
A66: деньги, заработок | B66: =COUNTIFS('предлог_из'!AD2:AD1000, "s",'предлог_из'!AB2:AB1000, 1) -> 0 | C66: =COUNTIFS('предлог_из'!AD2:AD1000, "o",'предлог_из'!AB2:AB1000, 1) -> 0 | D66: =COUNTIFS('предлог_из'!AD2:AD1000, "a",'предлог_из'!AB2:AB1000, 1) -> 0 | E66: =SUM(B66:D66) -> 0 | G66: деньги, заработок | H66: 0 | I66: 0 | J66: 0
A67: пространственные локации | B67: =COUNTIFS('предлог_из'!AD2:AD1000, "s",'предлог_из'!V2:V1000, 1) -> 2 | C67: =COUNTIFS('предлог_из'!AD2:AD1000, "o",'предлог_из'!V2:V1000, 1) -> 0 | D67: =COUNTIFS('предлог_из'!AD2:AD1000, "a",'предлог_из'!V2:V1000, 1) -> 0 | E67: =SUM(B67:D67) -> 2 | G67: пространственные локации | H67: =B67/E67 -> 1 | I67: =C67/E67 -> 0 | J67: =D67/E67 -> 0
A68: остальные употребления | B68: =COUNTIFS('предлог_из'!AD2:AD1000, "s",'предлог_из'!W2:W1000, 1) -> 0 | C68: =COUNTIFS('предлог_из'!AD2:AD1000, "o",'предлог_из'!W2:W1000, 1) -> 1 | D68: =COUNTIFS('предлог_из'!AD2:AD1000, "a",'предлог_из'!W2:W1000, 1) -> 2 | E68: =SUM(B68:D68) -> 3 | G68: остальные употребления | H68: =B68/E68 -> 0 | I68: =C68/E68 -> 0.33333333 | J68: =D68/E68 -> 0.66666667
A69: итого | B69: =SUM(B55:B68) -> 25 | C69: =SUM(C55:C68) -> 33 | D69: =SUM(D55:D68) -> 45 | E69: =SUM(E57:E68) -> 103 | G69: итого | H69: =B69/E69 -> 0.24271845 | I69: =C69/E69 -> 0.32038835 | J69: =D69/E69 -> 0.4368932
A71: Распределение семантических категорий по типам конструкций для предлога из с поправкой на прайминг | G71: Распределение семантических категорий по типам конструкций для предлога из с поправкой на прайминг
B72: Пространственная (s) | C72: объектная (o) | D72: аттрибутивная (a) | E72: итого | H72: Пространственная (s) | I72: объектная (o) | J72: аттрибутивная (a)
A73: топоним | B73: 8 | C73: 0 | D73: 4 | E73: 12 | G73: топоним | H73: =B73/E73 -> 0.66666667 | I73: =C73/E73 -> 0 | J73: =D73/E73 -> 0.33333333
A74: единица атд | B74: 0 | C74: 2 | D74: 22 | E74: 24 | G74: единица атд | H74: =B74/E74 -> 0 | I74: =C74/E74 -> 0.083333333 | J74: =D74/E74 -> 0.91666667
A75: жилище | B75: 4 | C75: 0 | D75: 0 | E75: 4 | G75: жилище | H75: =B75/E75 -> 1 | I75: =C75/E75 -> 0 | J75: =D75/E75 -> 0
A76: природные локации | B76: 1 | C76: 0 | D76: 0 | E76: 1 | G76: природные локации | H76: =B76/E76 -> 1 | I76: =C76/E76 -> 0 | J76: =D76/E76 -> 0
A77: учреждения | B77: 9 | C77: 0 | D77: 0 | E77: 9 | G77: учреждения | H77: =B77/E77 -> 1 | I77: =C77/E77 -> 0 | J77: =D77/E77 -> 0
A78: контейнер | B78: 1 | C78: 0 | D78: 0 | E78: 1 | G78: контейнер | H78: =B78/E78 -> 1 | I78: =C78/E78 -> 0 | J78: =D78/E78 -> 0
A79: материал | B79: 0 | C79: 20 | D79: 6 | E79: 26 | G79: материал | H79: =B79/E79 -> 0 | I79: =C79/E79 -> 0.76923077 | J79: =D79/E79 -> 0.23076923
A80: армия, тюрьма | B80: 0 | C80: 0 | D80: 0 | E80: 0 | G80: армия, тюрьма | H80: 0 | I80: 0 | J80: 0
A81: коллектив, группа | B81: 0 | C81: 6 | D81: 7 | E81: 13 | G81: коллектив, группа | H81: =B81/E81 -> 0 | I81: =C81/E81 -> 0.46153846 | J81: =D81/E81 -> 0.53846154
A82: деньги, заработок | B82: 0 | C82: 0 | D82: 0 | E82: 0 | G82: деньги, заработок | H82: 0 | I82: 0 | J82: 0
A83: пространственные локации | B83: 2 | C83: 0 | D83: 0 | E83: 2 | G83: пространственные локации | H83: =B83/E83 -> 1 | I83: =C83/E83 -> 0 | J83: =D83/E83 -> 0
A84: остальные употребления | B84: 0 | C84: 1 | D84: 2 | E84: 3 | G84: остальные употребления | H84: =B84/E84 -> 0 | I84: =C84/E84 -> 0.33333333 | J84: =D84/E84 -> 0.66666667
A85: итого | B85: =SUM(B72:B84) -> 25 | C85: =SUM(C72:C84) -> 29 | D85: =SUM(D72:D84) -> 41 | E85: =SUM(E72:E84) -> 95 | G85: итого | H85: =B85/E85 -> 0.26315789 | I85: =C85/E85 -> 0.30526316 | J85: =D85/E85 -> 0.43157895
G90: Распределение по семантическим категориям после поправки на прайминг
G91: Семантическая категория | H91: Количество примеров с из | I91: Доля от всех примеров с из (%)
G92: топоним | H92: 12 | I92: =H92/H104 -> 0.14634146
G93: единица атд | H93: 3 | I93: =H93/$H$104 -> 0.036585366
G94: жилище | H94: 4 | I94: =H94/$H$104 -> 0.048780488
G95: природные локации | H95: 1 | I95: =H95/$H$104 -> 0.012195122
G96: учреждения | H96: 9 | I96: =H96/$H$104 -> 0.1097561
G97: контейнер | H97: 1 | I97: =H97/$H$104 -> 0.012195122
G98: материал | H98: 26 | I98: =H98/$H$104 -> 0.31707317
G99: армия, тюрьма | H99: 0 | I99: =H99/$H$104 -> 0
G100: коллектив, группа | H100: 13 | I100: =H100/$H$104 -> 0.15853659
G101: деньги, заработок | H101: 0 | I101: =H101/$H$104 -> 0
G102: пространственные локации | H102: 2 | I102: =H102/$H$104 -> 0.024390244
G103: остальные употребления | H103: 3 | I103: =H103/$H$104 -> 0.036585366
G104: итого | H104: 82

Sheet прайминг
A1: ID | B1: пример с предполагаемым праймингом | C1: употребление с предлогом с | D1: использование из в той же семантической категории без из от интервьюера
A2: 20240802zes1942 | B2: Да, она родом из Каськова, да. | C2: Ну знаю, моя бабушка, по - моему, ж = жила, родом с Антонова. | D2: отсутствует
A3: 20240804zes1942 | B3: Из молока, которое в хозяйствве, во все времена и даже в пятьдесят восьмом году у нас уже был сепаратор, ещё не замужем была, а нас только приняли в совхоз, совхоз был на деньгах, поэтому нас соединили. И перегоняли, перегон, хочешь на творог перегон, хочешь, держали поросёнка, поросё = поросятам давали и белили, а ну, а молоко, делали масло, творог, ой ели ну такое, своё, ну. | C3: Ну ну если у ва = если у вас курица есть, обрежете лопатки все, я как делаю, ну я одна же у вас компания большая, я не знаю, как вы, я делаю этой самой все мякоть, кости эти варю, разрублю и кидаю, а с мякоти можете хоть котлет (котлетин) изпечь, хоть там что вы делаете, картошку в сделаете как фарш что, что захотите (захочите). | D3: Я = яйца, да, и яйца сдавали в совхоз, ну сами са = сами эти (эты) не, я думаю, ни разу, я не помню, чтобы мы сдавали мясо. А вот когда куры были, сдавали, кур было много, и каждый день возили в в ящиках (ящикам) больших (большим) по шестьсот штук в ящике были. Быва = бывало, это яйца, наверное, летом, летом, наверное, по шесть ящиков и даже в день были, ну много было кур и много яи = яиц было, и были большие расклёвы, а = курица курицу может расклевать, потому что не хватает, мяса давали, мяса, если какая - то, там < нрзб > что - то, то резали, там привозили к нам, и мы варили в котлах, в котлах вместе с картошкой с < нрзб > и давали, тогда вроде поменьше клю =, ну если расклёв был, то нас мы заста нас заставляли сразу её резать, ну в кипяток сажали, вычищали, и только голову себе оставляли, ноги потро = потроха, это себе оставляли, а если, а это сдавали. Вот это самое < нрзб > каждый день суп готовили из потрохов, вкусно были, боже мой, хорошо, сейчас в магазине возьму курицу, я даже есть её не могу, она чем - то пахнет, не понимаю я, обвариваю, обвариваю кипятком, и как - то не з = не понимаю, что такое раньше, то ли корм может (може) не такой, что, не знаю.
A4: 20230427gip1953 | B4: Из Стевии ? | C4: С шерсти (шерсть). Овец держали, шерсть. | D4: отсутствует
A5: 20220710zns1939 | B5: Из Москвы? | C5: Познакомились? Ну, мы с одной деревни. | D5: отсутствует
A6: 20210706lnt1950 | B6: А из фруктов ничего, ни с каких не делала. | C6: С малин тоже делают как хорошо, тоже говорят вкусная. | D6: отсутствует
A7: 20220711zns1939 | B7: Да и =из шерсти, исподки эти. | C7: С овец. | D7: отсутствует
A8: 20210707gip1953 | B8: Не, из льна мы не делали, увозили куда - то его на машина увозила, наверное, специально на эти... | D8: Крятки такие, два колеса из дерева, вырезанные с этого...
A9: 20210707gip1953 | B9: Из Щелкино, сынок. С той деревни. Она в магазин ходила, потом уже в последнее время она старая, не стала ходить. | C9: С той деревни | D9: Из города? Ага

Sheet Сводные таблицы и графики
A1: Предлог с | G1: Предлог из | P1: Распределение семантических категорий по пространственной конструкции для предлога с | AD1: Распределение семантических категорий по пространственной конструкции для предлога из
A2: Семантическая категория | B2: Общее | C2: Пятиусово | D2: Шетнево | E2: Опочка | G2: Семантическая категория | H2: Общее | I2: Пятиусово | J2: Шетнево | K2: Опочка | P2: Общее | S2: Пятиусово | V2: Шетнево | Y2: Опочка | AD2: Общее | AG2: Пятиусово | AJ2: Шетнево | AM2: Опочка
P3: s | Q3: o | R3: a | S3: s | T3: o | U3: a | V3: s | W3: o | X3: a | Y3: s | Z3: o | AA3: a | AD3: s | AE3: o | AF3: a | AG3: s | AH3: o | AI3: a | AJ3: s | AK3: o | AL3: a | AM3: s | AN3: o | AO3: a
A4: топоним | B4: 0.4189 | C4: 0.4495 | D4: 0.3804 | E4: 0.45 | G4: топоним | H4: 0.1951 | I4: 0.1042 | J4: 0.3182 | K4: 0.3333 | O4: топоним | P4: 0.6416 | Q4: 0 | R4: 0.3584 | S4: 0.6735 | T4: 0 | U4: 0.3265 | V4: 0.6429 | W4: 0 | X4: 0.3571 | Y4: 0.6111 | Z4: 0 | AA4: 0.3889 | AC4: топоним | AD4: 0.5 | AE4: 0 | AF4: 0.5 | AG4: 0.6 | AH4: 0 | AI4: 0.4 | AJ4: 0.4286 | AK4: 0 | AL4: 0.5714 | AM4: 0.5 | AN4: 0 | AO4: 0.5
A5: единица атд | B5: 0.1138 | C5: 0.1193 | D5: 0.0924 | E5: 0.1417 | G5: единица атд | H5: 0.0366 | I5: 0.0417 | J5: 0.0455 | K5: 0 | O5: единица атд | P5: 0.5319 | Q5: 0 | R5: 0.4681 | S5: 0.4615 | T5: 0 | U5: 0.5385 | V5: 0.4706 | W5: 0 | X5: 0.5294 | Y5: 0.6471 | Z5: 0 | AA5: 0.3529 | AC5: единица атд | AD5: 0 | AE5: 0.0833 | AF5: 0.9167 | AG5: 0 | AH5: 1 | AI5: 0 | AJ5: 0 | AK5: 0 | AL5: 1 | AM5: 0 | AN5: 0 | AO5: 0
A6: жилище | B6: 0.0315 | C6: 0.0183 | D6: 0.038 | E6: 0.0333 | G6: жилище | H6: 0.0488 | I6: 0.0417 | J6: 0.0909 | K6: 0 | O6: жилище | P6: 1 | Q6: 0 | R6: 0 | S6: 1 | T6: 0 | U6: 0 | V6: 1 | W6: 0 | X6: 0 | Y6: 1 | Z6: 0 | AA6: 0 | AC6: жилище | AD6: 1 | AE6: 0 | AF6: 0 | AG6: 1 | AH6: 0 | AI6: 0 | AJ6: 1 | AK6: 0 | AL6: 0 | AM6: 0 | AN6: 0 | AO6: 0
A7: природные локации | B7: 0.0315 | C7: 0.0367 | D7: 0.0272 | E7: 0.0333 | G7: природные локации | H7: 0.0122 | I7: 0.0208 | J7: 0 | K7: 0 | O7: природные локации | P7: 1 | Q7: 0 | R7: 0 | S7: 1 | T7: 0 | U7: 0 | V7: 1 | W7: 0 | X7: 0 | Y7: 1 | Z7: 0 | AA7: 0 | AC7: природные локации | AD7: 1 | AE7: 0 | AF7: 0 | AG7: 1 | AH7: 0 | AI7: 0 | AJ7: 0 | AK7: 0 | AL7: 0 | AM7: 0 | AN7: 0 | AO7: 0
A8: учреждения | B8: 0.0944 | C8: 0.0826 | D8: 0.1196 | E8: 0.0667 | G8: учреждения | H8: 0.1098 | I8: 0.0208 | J8: 0.1818 | K8: 0.3333 | O8: учреждения | P8: 0.8974 | Q8: 0 | R8: 0.1026 | S8: 1 | T8: 0 | U8: 0 | V8: 0.9545 | W8: 0 | X8: 0.0455 | Y8: 0.625 | Z8: 0 | AA8: 0.375 | AC8: учреждения | AD8: 1 | AE8: 0 | AF8: 0 | AG8: 1 | AH8: 0 | AI8: 0 | AJ8: 1 | AK8: 0 | AL8: 0 | AM8: 1 | AN8: 0 | AO8: 0
A9: контейнер | B9: 0.0823 | C9: 0.0826 | D9: 0.0761 | E9: 0.0917 | G9: контейнер | H9: 0.0122 | I9: 0 | J9: 0 | K9: 0.0833 | O9: контейнер | P9: 0.8529 | Q9: 0.0588 | R9: 0.0882 | S9: 1 | T9: 0 | U9: 0 | V9: 0.7857 | W9: 0.1429 | X9: 0.0714 | Y9: 0.8182 | Z9: 0 | AA9: 0.1818 | AC9: контейнер | AD9: 1 | AE9: 0 | AF9: 0 | AG9: 0 | AH9: 0 | AI9: 0 | AJ9: 0 | AK9: 0 | AL9: 0 | AM9: 1 | AN9: 0 | AO9: 0
A10: материал | B10: 0.1404 | C10: 0.1101 | D10: 0.2011 | E10: 0.075 | G10: материал | H10: 0.3659 | I10: 0.4167 | J10: 0.3636 | K10: 0.1667 | O10: материал | P10: 0 | Q10: 0.7759 | R10: 0.2241 | S10: 0 | T10: 1 | U10: 0 | V10: 0 | W10: 0.6757 | X10: 0.3243 | Y10: 0 | Z10: 0.8889 | AA10: 0.1111 | AC10: материал | AD10: 0 | AE10: 0.8 | AF10: 0.2 | AG10: 0 | AH10: 0.9 | AI10: 0.1 | AJ10: 0 | AK10: 0.5 | AL10: 0.5 | AM10: 0 | AN10: 1 | AO10: 0
A11: армия, тюрьма | B11: 0.046 | C11: 0.0459 | D11: 0.0435 | E11: 0.05 | G11: армия, тюрьма | H11: 0 | I11: 0 | J11: 0 | K11: 0 | O11: армия, тюрьма | P11: 0.7368 | Q11: 0 | R11: 0.2632 | S11: 0.6 | T11: 0 | U11: 0.4 | V11: 0.875 | W11: 0 | X11: 0.125 | Y11: 0.6667 | Z11: 0 | AA11: 0.3333 | AC11: армия, тюрьма | AD11: 0 | AE11: 0 | AF11: 0 | AG11: 0 | AH11: 0 | AI11: 0 | AJ11: 0 | AK11: 0 | AL11: 0 | AM11: 0 | AN11: 0 | AO11: 0
A12: коллектив, группа | B12: 0.0145 | C12: 0.0183 | D12: 0.0054 | E12: 0.025 | G12: коллектив, группа | H12: 0.1585 | I12: 0.25 | J12: 0 | K12: 0.0833 | O12: коллектив, группа | P12: 0.3333 | Q12: 0 | R12: 0.6667 | S12: 0.5 | T12: 0 | U12: 0.5 | V12: 1 | W12: 0 | X12: 0 | Y12: 0 | Z12: 0 | AA12: 1 | AC12: коллектив, группа | AD12: 0 | AE12: 0.4615 | AF12: 0.5385 | AG12: 0 | AH12: 0.4167 | AI12: 0.5833 | AJ12: 0 | AK12: 0 | AL12: 0 | AM12: 0 | AN12: 1 | AO12: 0
A13: деньги, заработок | B13: 0.0024 | C13: 0.0092 | D13: 0 | E13: 0 | G13: деньги, заработок | H13: 0 | I13: 0 | J13: 0 | K13: 0 | O13: деньги, заработок | P13: 0 | Q13: 1 | R13: 0 | S13: 0 | T13: 1 | U13: 0 | V13: 0 | W13: 0 | X13: 0 | Y13: 0 | Z13: 0 | AA13: 0 | AC13: деньги, заработок | AD13: 0 | AE13: 0 | AF13: 0 | AG13: 0 | AH13: 0 | AI13: 0 | AJ13: 0 | AK13: 0 | AL13: 0 | AM13: 0 | AN13: 0 | AO13: 0
A14: пространственные локации | B14: 0.0121 | C14: 0.0183 | D14: 0.0163 | E14: 0 | G14: пространственные локации | H14: 0.0244 | I14: 0.0417 | J14: 0 | K14: 0 | O14: пространственные локации | P14: 0.8 | Q14: 0 | R14: 0.2 | S14: 1 | T14: 0 | U14: 0 | V14: 0.6667 | W14: 0 | X14: 0.3333 | Y14: 0 | Z14: 0 | AA14: 0 | AC14: пространственные локации | AD14: 1 | AE14: 0 | AF14: 0 | AG14: 1 | AH14: 0 | AI14: 0 | AJ14: 0 | AK14: 0 | AL14: 0 | AM14: 0 | AN14: 0 | AO14: 0
A15: остальные употребления | B15: 0.0121 | C15: 0.0092 | D15: 0 | E15: 0.0333 | G15: остальные употребления | H15: 0.0366 | I15: 0.0625 | J15: 0 | K15: 0 | O15: остальные употребления | P15: 0.8 | Q15: 0.2 | R15: 0 | S15: 1 | T15: 0 | U15: 0 | V15: 0 | W15: 0 | X15: 0 | Y15: 0.75 | Z15: 0.25 | AA15: 0 | AC15: остальные употребления | AD15: 0 | AE15: 0.3333 | AF15: 0.6667 | AG15: 0 | AH15: 0.3333 | AI15: 0.6667 | AJ15: 0 | AK15: 0 | AL15: 0 | AM15: 0 | AN15: 0 | AO15: 0
A16: итого | B16: 1 | C16: 1 | D16: 1 | E16: 1 | G16: итого | H16: 1 | I16: 1 | J16: 1 | K16: 1 | O16: итого | P16: 0.6053 | Q16: 0.1186 | R16: 0.276 | S16: 0.6422 | T16: 0.1193 | U16: 0.2385 | V16: 0.5815 | W16: 0.1467 | X16: 0.2717 | Y16: 0.6083 | Z16: 0.075 | AA16: 0.3167 | AC16: итого | AD16: 0.2427 | AE16: 0.3204 | AF16: 0.4369 | AG16: 0.1875 | AH16: 0.5417 | AI16: 0.2708 | AJ16: 0.4091 | AK16: 0.1818 | AL16: 0.4091 | AM16: 0.5833 | AN16: 0.25 | AO16: 0.1667
P18: Пятиусово (s) | Q18: Шетнево (s) | R18: Опочка (s) | S18: Общее (s) | AD18: Пятиусово (s) | AE18: Шетнево (s) | AF18: Опочка (s) | AG18: Общее (s)
O19: топоним | P19: 0.6735 | Q19: 0.6429 | R19: 0.6111 | S19: 0.6416 | AC19: топоним | AD19: 0.6 | AE19: 0.4286 | AF19: 0.5 | AG19: 0.5
O20: единица атд | P20: 0.4615 | Q20: 0.4706 | R20: 0.6471 | S20: 0.5319 | AC20: единица атд | AD20: 0 | AE20: 0 | AF20: 0 | AG20: 0
O21: жилище | P21: 1 | Q21: 1 | R21: 1 | S21: 1 | AC21: жилище | AD21: 1 | AE21: 1 | AF21: 0 | AG21: 1
O22: природные локации | P22: 1 | Q22: 1 | R22: 1 | S22: 1 | AC22: природные локации | AD22: 1 | AE22: 0 | AF22: 0 | AG22: 1
O23: учреждения | P23: 1 | Q23: 0.9545 | R23: 0.625 | S23: 0.8974 | AC23: учреждения | AD23: 1 | AE23: 1 | AF23: 1 | AG23: 1
O24: контейнер | P24: 1 | Q24: 0.7857 | R24: 0.8182 | S24: 0.8529 | AC24: контейнер | AD24: 0 | AE24: 0 | AF24: 1 | AG24: 1
O25: материал | P25: 0 | Q25: 0 | R25: 0 | S25: 0 | AC25: материал | AD25: 0 | AE25: 0 | AF25: 0 | AG25: 0
O26: армия, тюрьма | P26: 0.6 | Q26: 0.875 | R26: 0.6667 | S26: 0.7368 | AC26: армия, тюрьма | AD26: 0 | AE26: 0 | AF26: 0 | AG26: 0
O27: коллектив, группа | P27: 0.5 | Q27: 1 | R27: 0 | S27: 0.3333 | AC27: коллектив, группа | AD27: 0 | AE27: 0 | AF27: 0 | AG27: 0
O28: деньги, заработок | P28: 0 | Q28: 0 | R28: 0 | S28: 0 | AC28: деньги, заработок | AD28: 0 | AE28: 0 | AF28: 0 | AG28: 0
O29: пространственные локации | P29: 1 | Q29: 0.6667 | R29: 0 | S29: 0.8 | AC29: пространственные локации | AD29: 1 | AE29: 0 | AF29: 0 | AG29: 1
O30: остальные употребления | P30: 1 | Q30: 0 | R30: 0.75 | S30: 0.8 | AC30: остальные употребления | AD30: 0 | AE30: 0 | AF30: 0 | AG30: 0
O31: итого | P31: 0.6422 | Q31: 0.5815 | R31: 0.6083 | S31: 0.6053 | AC31: итого | AD31: 0.1875 | AE31: 0.4091 | AF31: 0.5833 | AG31: 0.2427
P37: Пятиусово (o) | Q37: Шетнево (o) | R37: Опочка (o) | S37: Общее (o) | AD37: Пятиусово (o) | AE37: Шетнево (o) | AF37: Опочка (o) | AG37: Общее (o)
A38: Таблица 2. Процентное отношение примеров по корпусам | O38: топоним | P38: 0 | Q38: 0 | R38: 0 | S38: 0 | AC38: топоним | AD38: 0 | AE38: 0 | AF38: 0 | AG38: 0
A39: Корпус | B39: Всего примеров с с | C39: Всего примеров с из | D39: Всего релевантных примеров | O39: единица атд | P39: 0 | Q39: 0 | R39: 0 | S39: 0 | AC39: единица атд | AD39: 1 | AE39: 0 | AF39: 0 | AG39: 0.0833
A40: Корпус говора деревни Пятиусово | B40: 0.6943 | C40: 0.3057 | D40: 0.3172 | O40: жилище | P40: 0 | Q40: 0 | R40: 0 | S40: 0 | AC40: жилище | AD40: 0 | AE40: 0 | AF40: 0 | AG40: 0
A41: Корпус говора деревень Шетнево и Макеево | B41: 0.8932 | C41: 0.1068 | D41: 0.4162 | O41: природные локации | P41: 0 | Q41: 0 | R41: 0 | S41: 0 | AC41: природные локации | AD41: 0 | AE41: 0 | AF41: 0 | AG41: 0
A42: Корпус Опочецких говоров | B42: 0.9091 | C42: 0.0909 | D42: 0.2667 | O42: учреждения | P42: 0 | Q42: 0 | R42: 0 | S42: 0 | AC42: учреждения | AD42: 0 | AE42: 0 | AF42: 0 | AG42: 0
A43: Объединенные корпуса | B43: 0.8343 | C43: 0.1657 | D43: 1 | O43: контейнер | P43: 0 | Q43: 0.1429 | R43: 0 | S43: 0 | AC43: контейнер | AD43: 0 | AE43: 0 | AF43: 0 | AG43: 0
O44: материал | P44: 1 | Q44: 0.6757 | R44: 0.8889 | S44: 0.8889 | AC44: материал | AD44: 0.9 | AE44: 0.5 | AF44: 1 | AG44: 0.8
O45: армия, тюрьма | P45: 0 | Q45: 0 | R45: 0 | S45: 0 | AC45: армия, тюрьма | AD45: 0 | AE45: 0 | AF45: 0 | AG45: 0
O46: коллектив, группа | P46: 0 | Q46: 0 | R46: 0 | S46: 0 | AC46: коллектив, группа | AD46: 0.4167 | AE46: 0 | AF46: 1 | AG46: 0.4615
O47: деньги, заработок | P47: 1 | Q47: 0 | R47: 0 | S47: 0 | AC47: деньги, заработок | AD47: 0 | AE47: 0 | AF47: 0 | AG47: 0
O48: пространственные локации | P48: 0 | Q48: 0 | R48: 0 | S48: 0 | AC48: пространственные локации | AD48: 0 | AE48: 0 | AF48: 0 | AG48: 0
O49: остальные употребления | P49: 0 | Q49: 0 | R49: 0.25 | S49: 0.25 | AC49: остальные употребления | AD49: 0.3333 | AE49: 0 | AF49: 0 | AG49: 0.3333
O50: итого | P50: 0.1193 | Q50: 0.1467 | R50: 0.075 | S50: 0.075 | AC50: итого | AD50: 0.5417 | AE50: 0.1818 | AF50: 0.25 | AG50: 0.3204
P55: Пятиусово (a) | Q55: Шетнево (a) | R55: Опочка (a) | S55: Общее (a) | AD55: Пятиусово (a) | AE55: Шетнево (a) | AF55: Опочка (a) | AG55: Общее (a)
O56: топоним | P56: 0.3265 | Q56: 0.3571 | R56: 0.3889 | S56: 0.3584 | AC56: топоним | AD56: 0.4 | AE56: 0.5714 | AF56: 0.5 | AG56: 0.5
O57: единица атд | P57: 0.5385 | Q57: 0.5294 | R57: 0.3529 | S57: 0.4681 | AC57: единица атд | AD57: 0 | AE57: 1 | AF57: 0 | AG57: 0.9167
O58: жилище | P58: 0 | Q58: 0 | R58: 0 | S58: 0 | AC58: жилище | AD58: 0 | AE58: 0 | AF58: 0 | AG58: 0
O59: природные локации | P59: 0 | Q59: 0 | R59: 0 | S59: 0 | AC59: природные локации | AD59: 0 | AE59: 0 | AF59: 0 | AG59: 0
O60: учреждения | P60: 0 | Q60: 0.0455 | R60: 0.375 | S60: 0.1026 | AC60: учреждения | AD60: 0 | AE60: 0 | AF60: 0 | AG60: 0
O61: контейнер | P61: 0 | Q61: 0.0714 | R61: 0.1818 | S61: 0.0882 | AC61: контейнер | AD61: 0 | AE61: 0 | AF61: 0 | AG61: 0
O62: материал | P62: 0 | Q62: 0.3243 | R62: 0.1111 | S62: 0.2241 | AC62: материал | AD62: 0.1 | AE62: 0.5 | AF62: 0 | AG62: 0.2
O63: армия, тюрьма | P63: 0.4 | Q63: 0.125 | R63: 0.3333 | S63: 0.2632 | AC63: армия, тюрьма | AD63: 0 | AE63: 0 | AF63: 0 | AG63: 0
A64: Таблица 4. Распределение предлога с по типам конструкций (все корпуса) | O64: коллектив, группа | P64: 0.5 | Q64: 0 | R64: 1 | S64: 0.6667 | AC64: коллектив, группа | AD64: 0.5833 | AE64: 0 | AF64: 0 | AG64: 0.5385
A65: Тип конструкции | B65: Общее | C65: Пятиусово | D65: Шетнево | E65: Опочка | O65: деньги, заработок | P65: 0 | Q65: 0 | R65: 0 | S65: 0 | AC65: деньги, заработок | AD65: 0 | AE65: 0 | AF65: 0 | AG65: 0
A66: Пространственная (s) | B66: 0.6053 | C66: 0.6422 | D66: 0.5815 | E66: 0.6083 | O66: пространственные локации | P66: 0 | Q66: 0.3333 | R66: 0 | S66: 0.2 | AC66: пространственные локации | AD66: 0 | AE66: 0 | AF66: 0 | AG66: 0
A67: Объектная (o) | B67: 0.1186 | C67: 0.1193 | D67: 0.1467 | E67: 0.075 | O67: остальные употребления | P67: 0 | Q67: 0 | R67: 0 | S67: 0 | AC67: остальные употребления | AD67: 0.6667 | AE67: 0 | AF67: 0 | AG67: 0.6667
A68: Атрибутивная (a) | B68: 0.276 | C68: 0.2385 | D68: 0.2717 | E68: 0.3167 | O68: итого | P68: 0.2385 | Q68: 0.2717 | R68: 0.3167 | S68: 0.276 | AC68: итого | AD68: 0.2708 | AE68: 0.4091 | AF68: 0.1667 | AG68: 0.4369
A69: итого | B69: 1 | C69: 1 | D69: 1 | E69: 1
A90: Таблица 4. Распределение предлога из по типам конструкций (все корпуса)
A91: Тип конструкции | B91: Общее | C91: Пятиусово | D91: Шетнево | E91: Опочка
A92: Пространственная (s) | B92: 0.30487805 | C92: 0.1875 | D92: 0.40909091 | E92: 0.58333333
A93: Объектная (o) | B93: 0.40243902 | C93: 0.54166667 | D93: 0.18181818 | E93: 0.25
A94: Атрибутивная (a) | B94: 0.29268293 | C94: 0.27083333 | D94: 0.40909091 | E94: 0.16666667
A95: итого | B95: 1 | C95: 1 | D95: 1 | E95: 1
A117: Семантическая категория | B117: Доля от всех примеров с с (%)
A118: топоним | B118: 0.4188862
A119: единица атд | B119: 0.11380145
A120: жилище | B120: 0.031476998
A121: природные локации | B121: 0.031476998
A122: учреждения | B122: 0.094430993
A123: контейнер | B123: 0.082324455
A124: материал | B124: 0.14043584
A125: армия, тюрьма | B125: 0.046004843
A126: коллектив, группа | B126: 0.014527845
A127: деньги, заработок | B127: 0.0024213075
A128: пространственные локации | B128: 0.012106538
